Workbook

Sheet instruments
A1: row_id | B1: name | C1: identifier | D1: policy_area_ceps | E1: ceps_table_status | F1: proposal_date | G1: confidence_proposal_date | H1: adoption_date | I1: oj_publication_date | J1: entry_into_force | K1: status_ceps_jul2025 | L1: status_oct2026 | M1: celex_measured | N1: text_measured | O1: source_url | P1: pages | Q1: words_legal_text | R1: words_preamble | S1: words_recitals | T1: words_articles | U1: words_annexes | V1: words_memorandum | W1: words_financial_statement | X1: restrictions_total | Y1: r_obligation | Z1: r_prohibition | AA1: r_restricted_permission | AB1: r_explicit_requirement | AC1: r_duty_of_result | AD1: addr_private_parties | AE1: addr_member_states | AF1: addr_eu_institutions | AG1: addr_unclear | AH1: consolidated_celex | AI1: consolidated_restrictions_total | AJ1: consolidated_addr_private_parties | AK1: n_implementing_acts | AL1: n_delegated_acts | AM1: n_other_commission_council_acts | AN1: n_guidance_eurlex | AO1: n_guidance_web | AP1: n_guidance_edpb | AQ1: n_guidance_eba | AR1: n_guidance_esma | AS1: restrictions_in_implementing_and_delegated_acts | AT1: national_transposition_measures | AU1: member_states_with_measures | AV1: n_amending_acts | AW1: first_amendment_date | AX1: latest_amendment_date | AY1: n_corrigenda | AZ1: proposal_celex | BA1: proposal_text_source | BB1: proposal_words_legal_text | BC1: proposal_restrictions_total | BD1: proposal_addr_private_parties | BE1: change_words | BF1: change_words_pct | BG1: change_restrictions | BH1: change_restrictions_pct | BI1: change_restrictions_private | BJ1: note
A2: 1 | B2: Frequency Bands Directive (GSM) | C2: Directive 87/372/EEC | D2: Connectivity | E2: enacted | F2: 1986-09-01 | G2: low | H2: 1987-06-25 | I2: 1987-06-25 | J2: 1987-06-30 | K2: adopted | L2: adopted | M2: 31987L0372 | N2: Original act as published in the OJ | O2: https://eur-lex.europa.eu/legal-content/EN/TXT/?uri=CELEX:31987L0372 | P2: 2 | Q2: 866 | R2: 618 | S2: 483 | T2: 248 | U2: 0 | V2: 0 | W2: 0 | X2: 6 | Y2: 4 | Z2: 0 | AA2: 0 | AB2: 0 | AC2: 2 | AD2: 0 | AE2: 5 | AF2: 1 | AG2: 0 | AH2: 01987L0372-19870630 | AI2: 0 | AJ2: 0 | AK2: =COUNTIFS(secondary_acts!$A$2:$A$771,$A2,secondary_acts!$E$2:$E$771,"implementing") -> 0 | AL2: =COUNTIFS(secondary_acts!$A$2:$A$771,$A2,secondary_acts!$E$2:$E$771,"delegated") -> 0 | AM2: =COUNTIFS(secondary_acts!$A$2:$A$771,$A2,secondary_acts!$E$2:$E$771,"other Commission/Council act") -> 0 | AN2: =COUNTIFS(secondary_acts!$A$2:$A$771,$A2,secondary_acts!$E$2:$E$771,"guidance") -> 0 | AO2: =COUNTIF(guidance_web!$A$2:$A$7,$A2) -> 0 | AP2: =COUNTIFS(guidance_agencies!$A$2:$A$81,$A2,guidance_agencies!$D$2:$D$81,"EDPB") -> 0 | AQ2: =COUNTIFS(guidance_agencies!$A$2:$A$81,$A2,guidance_agencies!$D$2:$D$81,"EBA") -> 0 | AR2: =COUNTIFS(guidance_agencies!$A$2:$A$81,$A2,guidance_agencies!$D$2:$D$81,"ESMA") -> 0 | AS2: =SUMIFS(secondary_acts!$S$2:$S$771,secondary_acts!$A$2:$A$771,$A2,secondary_acts!$E$2:$E$771,"implementing")+SUMIFS(secondary_acts!$S$2:$S$771,secondary_acts!$A$2:$A$771,$A2,secondary_acts!$E$2:$E$771,"delegated") -> 0 | AT2: 207 | AU2: 24 | AV2: 1 | AW2: 2009-09-16 | AX2: 2009-09-16 | AY2: 2 | AZ2: 51987PC0035(02) | BA2: PDF text (approximate) | BB2: 841 | BC2: 5 | BD2: 0 | BE2: =IF(ISNUMBER(BB2),Q2-BB2,"") -> 25 | BF2: =IF(AND(ISNUMBER(BB2),BB2>0),(Q2-BB2)/BB2,"") -> 0.029726516 | BG2: =IF(ISNUMBER(BC2),X2-BC2,"") -> 1 | BH2: =IF(AND(ISNUMBER(BC2),BC2>0),(X2-BC2)/BC2,"") -> 0.2 | BI2: =IF(ISNUMBER(BD2),AD2-BD2,"") -> 0
A3: 2 | B3: Unfair Contract Terms Directive | C3: Directive 93/13/EEC | D3: E-commerce & Consumer Protection | E3: enacted | F3: 1990-07-24 | G3: medium | H3: 1993-04-05 | I3: 1993-04-21 | J3: 1993-04-16 | K3: adopted | L3: adopted | M3: 31993L0013 | N3: Original act as published in the OJ | O3: https://eur-lex.europa.eu/legal-content/EN/TXT/?uri=CELEX:31993L0013 | P3: 6 | Q3: 3320 | R3: 1402 | S3: 1323 | T3: 1008 | U3: 910 | V3: 0 | W3: 0 | X3: 26 | Y3: 20 | Z3: 2 | AA3: 0 | AB3: 3 | AC3: 1 | AD3: 6 | AE3: 11 | AF3: 1 | AG3: 8 | AH3: 01993L0013-20220528 | AI3: 39 | AJ3: 6 | AK3: =COUNTIFS(secondary_acts!$A$2:$A$771,$A3,secondary_acts!$E$2:$E$771,"implementing") -> 0 | AL3: =COUNTIFS(secondary_acts!$A$2:$A$771,$A3,secondary_acts!$E$2:$E$771,"delegated") -> 0 | AM3: =COUNTIFS(secondary_acts!$A$2:$A$771,$A3,secondary_acts!$E$2:$E$771,"other Commission/Council act") -> 0 | AN3: =COUNTIFS(secondary_acts!$A$2:$A$771,$A3,secondary_acts!$E$2:$E$771,"guidance") -> 1 | AO3: =COUNTIF(guidance_web!$A$2:$A$7,$A3) -> 0 | AP3: =COUNTIFS(guidance_agencies!$A$2:$A$81,$A3,guidance_agencies!$D$2:$D$81,"EDPB") -> 0 | AQ3: =COUNTIFS(guidance_agencies!$A$2:$A$81,$A3,guidance_agencies!$D$2:$D$81,"EBA") -> 0 | AR3: =COUNTIFS(guidance_agencies!$A$2:$A$81,$A3,guidance_agencies!$D$2:$D$81,"ESMA") -> 0 | AS3: =SUMIFS(secondary_acts!$S$2:$S$771,secondary_acts!$A$2:$A$771,$A3,secondary_acts!$E$2:$E$771,"implementing")+SUMIFS(secondary_acts!$S$2:$S$771,secondary_acts!$A$2:$A$771,$A3,secondary_acts!$E$2:$E$771,"delegated") -> 0 | AT3: 1342 | AU3: 25 | AV3: 2 | AW3: 2011-10-25 | AX3: 2019-11-27 | AY3: 13 | AZ3: 51990PC0322 | BA3: PDF text (approximate) | BB3: 2059 | BC3: 11 | BD3: 0 | BE3: =IF(ISNUMBER(BB3),Q3-BB3,"") -> 1261 | BF3: =IF(AND(ISNUMBER(BB3),BB3>0),(Q3-BB3)/BB3,"") -> 0.61243322 | BG3: =IF(ISNUMBER(BC3),X3-BC3,"") -> 15 | BH3: =IF(AND(ISNUMBER(BC3),BC3>0),(X3-BC3)/BC3,"") -> 1.3636364 | BI3: =IF(ISNUMBER(BD3),AD3-BD3,"") -> 6
A4: 3 | B4: Satellite and Cable Directive | C4: Directive 93/83/EEC | D4: Media | E4: enacted | F4: 1991-09-11 | G4: medium | H4: 1993-09-27 | I4: 1993-10-06 | J4: 1993-10-04 | K4: adopted | L4: adopted | M4: 31993L0083 | N4: Original act as published in the OJ | O4: https://eur-lex.europa.eu/legal-content/EN/TXT/?uri=CELEX:31993L0083 | P4: 7 | Q4: 4550 | R4: 2545 | S4: 2449 | T4: 2005 | U4: 0 | V4: 0 | W4: 0 | X4: 35 | Y4: 27 | Z4: 1 | AA4: 1 | AB4: 0 | AC4: 6 | AD4: 4 | AE4: 18 | AF4: 2 | AG4: 11 | AH4: 01993L0083-19931004 | AI4: 35 | AJ4: 4 | AK4: =COUNTIFS(secondary_acts!$A$2:$A$771,$A4,secondary_acts!$E$2:$E$771,"implementing") -> 0 | AL4: =COUNTIFS(secondary_acts!$A$2:$A$771,$A4,secondary_acts!$E$2:$E$771,"delegated") -> 0 | AM4: =COUNTIFS(secondary_acts!$A$2:$A$771,$A4,secondary_acts!$E$2:$E$771,"other Commission/Council act") -> 0 | AN4: =COUNTIFS(secondary_acts!$A$2:$A$771,$A4,secondary_acts!$E$2:$E$771,"guidance") -> 0 | AO4: =COUNTIF(guidance_web!$A$2:$A$7,$A4) -> 0 | AP4: =COUNTIFS(guidance_agencies!$A$2:$A$81,$A4,guidance_agencies!$D$2:$D$81,"EDPB") -> 0 | AQ4: =COUNTIFS(guidance_agencies!$A$2:$A$81,$A4,guidance_agencies!$D$2:$D$81,"EBA") -> 0 | AR4: =COUNTIFS(guidance_agencies!$A$2:$A$81,$A4,guidance_agencies!$D$2:$D$81,"ESMA") -> 0 | AS4: =SUMIFS(secondary_acts!$S$2:$S$771,secondary_acts!$A$2:$A$771,$A4,secondary_acts!$E$2:$E$771,"implementing")+SUMIFS(secondary_acts!$S$2:$S$771,secondary_acts!$A$2:$A$771,$A4,secondary_acts!$E$2:$E$771,"delegated") -> 0 | AT4: 207 | AU4: 23 | AV4: 1 | AW4: 2019-04-17 | AX4: 2019-04-17 | AY4: 1 | AZ4: 51991PC0276 | BA4: PDF text (approximate) | BB4: 3122 | BC4: 30 | BD4: 0 | BE4: =IF(ISNUMBER(BB4),Q4-BB4,"") -> 1428 | BF4: =IF(AND(ISNUMBER(BB4),BB4>0),(Q4-BB4)/BB4,"") -> 0.4573991 | BG4: =IF(ISNUMBER(BC4),X4-BC4,"") -> 5 | BH4: =IF(AND(ISNUMBER(BC4),BC4>0),(X4-BC4)/BC4,"") -> 0.16666667 | BI4: =IF(ISNUMBER(BD4),AD4-BD4,"") -> 4 | BJ4: no consolidated text with amendments in EUR-Lex; consolidated count = original
A5: 4 | B5: Database Directive | C5: Directive 96/9/EC | D5: IPR | E5: enacted | F5: 1992-05-13 | G5: medium | H5: 1996-03-11 | I5: 1996-03-27 | J5: 1996-04-16 | K5: adopted | L5: adopted | M5: 31996L0009 | N5: Original act as published in the OJ | O5: https://eur-lex.europa.eu/legal-content/EN/TXT/?uri=CELEX:31996L0009 | P5: 9 | Q5: 5494 | R5: 3257 | S5: 3156 | T5: 2237 | U5: 0 | V5: 0 | W5: 0 | X5: 33 | Y5: 24 | Z5: 9 | AA5: 0 | AB5: 0 | AC5: 0 | AD5: 8 | AE5: 10 | AF5: 2 | AG5: 13 | AH5: 01996L0009-20190606 | AI5: 33 | AJ5: 8 | AK5: =COUNTIFS(secondary_acts!$A$2:$A$771,$A5,secondary_acts!$E$2:$E$771,"implementing") -> 0 | AL5: =COUNTIFS(secondary_acts!$A$2:$A$771,$A5,secondary_acts!$E$2:$E$771,"delegated") -> 0 | AM5: =COUNTIFS(secondary_acts!$A$2:$A$771,$A5,secondary_acts!$E$2:$E$771,"other Commission/Council act") -> 0 | AN5: =COUNTIFS(secondary_acts!$A$2:$A$771,$A5,secondary_acts!$E$2:$E$771,"guidance") -> 0 | AO5: =COUNTIF(guidance_web!$A$2:$A$7,$A5) -> 0 | AP5: =COUNTIFS(guidance_agencies!$A$2:$A$81,$A5,guidance_agencies!$D$2:$D$81,"EDPB") -> 0 | AQ5: =COUNTIFS(guidance_agencies!$A$2:$A$81,$A5,guidance_agencies!$D$2:$D$81,"EBA") -> 0 | AR5: =COUNTIFS(guidance_agencies!$A$2:$A$81,$A5,guidance_agencies!$D$2:$D$81,"ESMA") -> 0 | AS5: =SUMIFS(secondary_acts!$S$2:$S$771,secondary_acts!$A$2:$A$771,$A5,secondary_acts!$E$2:$E$771,"implementing")+SUMIFS(secondary_acts!$S$2:$S$771,secondary_acts!$A$2:$A$771,$A5,secondary_acts!$E$2:$E$771,"delegated") -> 0 | AT5: 1049 | AU5: 22 | AV5: 1 | AW5: 2019-04-17 | AX5: 2019-04-17 | AY5: 1 | AZ5: 51992PC0024 | BA5: PDF text (approximate) | BB5: 4314 | BC5: 28 | BD5: 2 | BE5: =IF(ISNUMBER(BB5),Q5-BB5,"") -> 1180 | BF5: =IF(AND(ISNUMBER(BB5),BB5>0),(Q5-BB5)/BB5,"") -> 0.27352805 | BG5: =IF(ISNUMBER(BC5),X5-BC5,"") -> 5 | BH5: =IF(AND(ISNUMBER(BC5),BC5>0),(X5-BC5)/BC5,"") -> 0.17857143 | BI5: =IF(ISNUMBER(BD5),AD5-BD5,"") -> 6
A6: 5 | B6: Community Design Regulation | C6: Regulation (EC) 6/2002 | D6: IPR | E6: enacted | F6: 1993-12-03 | G6: medium | H6: 2001-12-12 | I6: 2002-01-09 | J6: 2002-03-06 | K6: adopted | L6: adopted | M6: 32002R0006 | N6: Original act as published in the OJ | O6: https://eur-lex.europa.eu/legal-content/EN/TXT/?uri=CELEX:32002R0006 | P6: 24 | Q6: 17870 | R6: 2070 | S6: 1978 | T6: 15800 | U6: 0 | V6: 0 | W6: 0 | X6: 280 | Y6: 241 | Z6: 31 | AA6: 7 | AB6: 1 | AC6: 0 | AD6: 29 | AE6: 50 | AF6: 65 | AG6: 136 | AH6: 02002R0006-20260701 | AI6: 481 | AJ6: 51 | AK6: =COUNTIFS(secondary_acts!$A$2:$A$771,$A6,secondary_acts!$E$2:$E$771,"implementing") -> 2 | AL6: =COUNTIFS(secondary_acts!$A$2:$A$771,$A6,secondary_acts!$E$2:$E$771,"delegated") -> 1 | AM6: =COUNTIFS(secondary_acts!$A$2:$A$771,$A6,secondary_acts!$E$2:$E$771,"other Commission/Council act") -> 4 | AN6: =COUNTIFS(secondary_acts!$A$2:$A$771,$A6,secondary_acts!$E$2:$E$771,"guidance") -> 0 | AO6: =COUNTIF(guidance_web!$A$2:$A$7,$A6) -> 0 | AP6: =COUNTIFS(guidance_agencies!$A$2:$A$81,$A6,guidance_agencies!$D$2:$D$81,"EDPB") -> 0 | AQ6: =COUNTIFS(guidance_agencies!$A$2:$A$81,$A6,guidance_agencies!$D$2:$D$81,"EBA") -> 0 | AR6: =COUNTIFS(guidance_agencies!$A$2:$A$81,$A6,guidance_agencies!$D$2:$D$81,"ESMA") -> 0 | AS6: =SUMIFS(secondary_acts!$S$2:$S$771,secondary_acts!$A$2:$A$771,$A6,secondary_acts!$E$2:$E$771,"implementing")+SUMIFS(secondary_acts!$S$2:$S$771,secondary_acts!$A$2:$A$771,$A6,secondary_acts!$E$2:$E$771,"delegated") -> 143 | AV6: 2 | AW6: 2006-12-18 | AX6: 2024-10-23 | AY6: 20 | AZ6: 51993PC0342 | BA6: not comparable: 1993 proposal PDF bundles the companion Design Directive proposal | BE6: =IF(ISNUMBER(BB6),Q6-BB6,"") | BF6: =IF(AND(ISNUMBER(BB6),BB6>0),(Q6-BB6)/BB6,"") | BG6: =IF(ISNUMBER(BC6),X6-BC6,"") | BH6: =IF(AND(ISNUMBER(BC6),BC6>0),(X6-BC6)/BC6,"") | BI6: =IF(ISNUMBER(BD6),AD6-BD6,"")
A7: 6 | B7: Price Indication Directive | C7: Directive 98/6/EC | D7: E-commerce & Consumer Protection | E7: enacted | F7: 1995-07-24 | G7: low | H7: 1998-02-16 | I7: 1998-03-25 | J7: 1998-03-18 | K7: adopted | L7: adopted | M7: 31998L0006 | N7: Original act as published in the OJ | O7: https://eur-lex.europa.eu/legal-content/EN/TXT/?uri=CELEX:31998L0006 | P7: 5 | Q7: 1901 | R7: 853 | S7: 731 | T7: 1048 | U7: 0 | V7: 0 | W7: 0 | X7: 23 | Y7: 22 | Z7: 1 | AA7: 0 | AB7: 0 | AC7: 0 | AD7: 1 | AE7: 10 | AF7: 3 | AG7: 9 | AH7: 01998L0006-20220528 | AI7: 27 | AJ7: 0 | AK7: =COUNTIFS(secondary_acts!$A$2:$A$771,$A7,secondary_acts!$E$2:$E$771,"implementing") -> 0 | AL7: =COUNTIFS(secondary_acts!$A$2:$A$771,$A7,secondary_acts!$E$2:$E$771,"delegated") -> 0 | AM7: =COUNTIFS(secondary_acts!$A$2:$A$771,$A7,secondary_acts!$E$2:$E$771,"other Commission/Council act") -> 0 | AN7: =COUNTIFS(secondary_acts!$A$2:$A$771,$A7,secondary_acts!$E$2:$E$771,"guidance") -> 1 | AO7: =COUNTIF(guidance_web!$A$2:$A$7,$A7) -> 0 | AP7: =COUNTIFS(guidance_agencies!$A$2:$A$81,$A7,guidance_agencies!$D$2:$D$81,"EDPB") -> 0 | AQ7: =COUNTIFS(guidance_agencies!$A$2:$A$81,$A7,guidance_agencies!$D$2:$D$81,"EBA") -> 0 | AR7: =COUNTIFS(guidance_agencies!$A$2:$A$81,$A7,guidance_agencies!$D$2:$D$81,"ESMA") -> 0 | AS7: =SUMIFS(secondary_acts!$S$2:$S$771,secondary_acts!$A$2:$A$771,$A7,secondary_acts!$E$2:$E$771,"implementing")+SUMIFS(secondary_acts!$S$2:$S$771,secondary_acts!$A$2:$A$771,$A7,secondary_acts!$E$2:$E$771,"delegated") -> 0 | AT7: 359 | AU7: 26 | AV7: 1 | AW7: 2019-11-27 | AX7: 2019-11-27 | AY7: 1 | AZ7: 51995PC0276 | BA7: EUR-Lex HTML | BB7: 1809 | BC7: 21 | BD7: 0 | BE7: =IF(ISNUMBER(BB7),Q7-BB7,"") -> 92 | BF7: =IF(AND(ISNUMBER(BB7),BB7>0),(Q7-BB7)/BB7,"") -> 0.050856827 | BG7: =IF(ISNUMBER(BC7),X7-BC7,"") -> 2 | BH7: =IF(AND(ISNUMBER(BC7),BC7>0),(X7-BC7)/BC7,"") -> 0.095238095 | BI7: =IF(ISNUMBER(BD7),AD7-BD7,"") -> 1
A8: 7 | B8: Information Society (InfoSoc) Directive | C8: Directive 2001/29/EC | D8: Media | E8: enacted | F8: 1997-12-10 | G8: high | H8: 2001-05-22 | I8: 2001-06-25 | J8: 2001-06-22 | K8: adopted | L8: adopted | M8: 32001L0029 | N8: Original act as published in the OJ | O8: https://eur-lex.europa.eu/legal-content/EN/TXT/?uri=CELEX:32001L0029 | P8: 10 | Q8: 8127 | R8: 4811 | S8: 4670 | T8: 3316 | U8: 0 | V8: 0 | W8: 0 | X8: 35 | Y8: 29 | Z8: 3 | AA8: 2 | AB8: 0 | AC8: 1 | AD8: 0 | AE8: 21 | AF8: 3 | AG8: 11 | AH8: 02001L0029-20190606 | AI8: 35 | AJ8: 0 | AK8: =COUNTIFS(secondary_acts!$A$2:$A$771,$A8,secondary_acts!$E$2:$E$771,"implementing") -> 0 | AL8: =COUNTIFS(secondary_acts!$A$2:$A$771,$A8,secondary_acts!$E$2:$E$771,"delegated") -> 0 | AM8: =COUNTIFS(secondary_acts!$A$2:$A$771,$A8,secondary_acts!$E$2:$E$771,"other Commission/Council act") -> 0 | AN8: =COUNTIFS(secondary_acts!$A$2:$A$771,$A8,secondary_acts!$E$2:$E$771,"guidance") -> 0 | AO8: =COUNTIF(guidance_web!$A$2:$A$7,$A8) -> 0 | AP8: =COUNTIFS(guidance_agencies!$A$2:$A$81,$A8,guidance_agencies!$D$2:$D$81,"EDPB") -> 0 | AQ8: =COUNTIFS(guidance_agencies!$A$2:$A$81,$A8,guidance_agencies!$D$2:$D$81,"EBA") -> 0 | AR8: =COUNTIFS(guidance_agencies!$A$2:$A$81,$A8,guidance_agencies!$D$2:$D$81,"ESMA") -> 0 | AS8: =SUMIFS(secondary_acts!$S$2:$S$771,secondary_acts!$A$2:$A$771,$A8,secondary_acts!$E$2:$E$771,"implementing")+SUMIFS(secondary_acts!$S$2:$S$771,secondary_acts!$A$2:$A$771,$A8,secondary_acts!$E$2:$E$771,"delegated") -> 0 | AT8: 1103 | AU8: 28 | AV8: 2 | AW8: 2017-09-13 | AX8: 2019-04-17 | AY8: 8 | AZ8: 51997PC0628 | BA8: EUR-Lex HTML | BB8: 5152 | BC8: 27 | BD8: 0 | BE8: =IF(ISNUMBER(BB8),Q8-BB8,"") -> 2975 | BF8: =IF(AND(ISNUMBER(BB8),BB8>0),(Q8-BB8)/BB8,"") -> 0.57744565 | BG8: =IF(ISNUMBER(BC8),X8-BC8,"") -> 8 | BH8: =IF(AND(ISNUMBER(BC8),BC8>0),(X8-BC8)/BC8,"") -> 0.2962963 | BI8: =IF(ISNUMBER(BD8),AD8-BD8,"") -> 0
A9: 8 | B9: E-commerce Directive | C9: Directive 2000/31/EC | D9: E-commerce & Consumer Protection | E9: enacted | F9: 1998-11-18 | G9: high | H9: 2000-06-08 | I9: 2000-06-08 | J9: 2000-07-17 | K9: adopted | L9: adopted | M9: 32000L0031 | N9: Original act as published in the OJ | O9: https://eur-lex.europa.eu/legal-content/EN/TXT/?uri=CELEX:32000L0031 | P9: 16 | Q9: 10148 | R9: 5471 | S9: 5320 | T9: 4370 | U9: 307 | V9: 0 | W9: 0 | X9: 72 | Y9: 50 | Z9: 3 | AA9: 0 | AB9: 2 | AC9: 17 | AD9: 6 | AE9: 42 | AF9: 9 | AG9: 15 | AH9: 02000L0031-20240217 | AI9: 68 | AJ9: 6 | AK9: =COUNTIFS(secondary_acts!$A$2:$A$771,$A9,secondary_acts!$E$2:$E$771,"implementing") -> 0 | AL9: =COUNTIFS(secondary_acts!$A$2:$A$771,$A9,secondary_acts!$E$2:$E$771,"delegated") -> 0 | AM9: =COUNTIFS(secondary_acts!$A$2:$A$771,$A9,secondary_acts!$E$2:$E$771,"other Commission/Council act") -> 0 | AN9: =COUNTIFS(secondary_acts!$A$2:$A$771,$A9,secondary_acts!$E$2:$E$771,"guidance") -> 0 | AO9: =COUNTIF(guidance_web!$A$2:$A$7,$A9) -> 0 | AP9: =COUNTIFS(guidance_agencies!$A$2:$A$81,$A9,guidance_agencies!$D$2:$D$81,"EDPB") -> 0 | AQ9: =COUNTIFS(guidance_agencies!$A$2:$A$81,$A9,guidance_agencies!$D$2:$D$81,"EBA") -> 0 | AR9: =COUNTIFS(guidance_agencies!$A$2:$A$81,$A9,guidance_agencies!$D$2:$D$81,"ESMA") -> 0 | AS9: =SUMIFS(secondary_acts!$S$2:$S$771,secondary_acts!$A$2:$A$771,$A9,secondary_acts!$E$2:$E$771,"implementing")+SUMIFS(secondary_acts!$S$2:$S$771,secondary_acts!$A$2:$A$771,$A9,secondary_acts!$E$2:$E$771,"delegated") -> 0 | AT9: 2522 | AU9: 27 | AV9: 1 | AW9: 2022-10-19 | AX9: 2022-10-19 | AY9: 4 | AZ9: 51998PC0586 | BA9: EUR-Lex HTML | BB9: 7063 | BC9: 78 | BD9: 7 | BE9: =IF(ISNUMBER(BB9),Q9-BB9,"") -> 3085 | BF9: =IF(AND(ISNUMBER(BB9),BB9>0),(Q9-BB9)/BB9,"") -> 0.43678324 | BG9: =IF(ISNUMBER(BC9),X9-BC9,"") -> -6 | BH9: =IF(AND(ISNUMBER(BC9),BC9>0),(X9-BC9)/BC9,"") -> -0.076923077 | BI9: =IF(ISNUMBER(BD9),AD9-BD9,"") -> -1
A10: 9 | B10: ePrivacy Directive | C10: Directive 2002/58/EC | D10: Data & Privacy | E10: enacted | F10: 2000-07-12 | G10: high | H10: 2002-07-12 | I10: 2002-08-01 | J10: 2002-07-31 | K10: adopted | L10: adopted | M10: 32002L0058 | N10: Original act as published in the OJ | O10: https://eur-lex.europa.eu/legal-content/EN/TXT/?uri=CELEX:32002L0058 | P10: 11 | Q10: 8620 | R10: 5001 | S10: 4843 | T10: 3619 | U10: 0 | V10: 0 | W10: 0 | X10: 49 | Y10: 34 | Z10: 3 | AA10: 2 | AB10: 1 | AC10: 9 | AD10: 17 | AE10: 23 | AF10: 4 | AG10: 5 | AH10: 02002L0058-20091219 | AI10: 79 | AJ10: 29 | AK10: =COUNTIFS(secondary_acts!$A$2:$A$771,$A10,secondary_acts!$E$2:$E$771,"implementing") -> 0 | AL10: =COUNTIFS(secondary_acts!$A$2:$A$771,$A10,secondary_acts!$E$2:$E$771,"delegated") -> 0 | AM10: =COUNTIFS(secondary_acts!$A$2:$A$771,$A10,secondary_acts!$E$2:$E$771,"other Commission/Council act") -> 1 | AN10: =COUNTIFS(secondary_acts!$A$2:$A$771,$A10,secondary_acts!$E$2:$E$771,"guidance") -> 0 | AO10: =COUNTIF(guidance_web!$A$2:$A$7,$A10) -> 0 | AP10: =COUNTIFS(guidance_agencies!$A$2:$A$81,$A10,guidance_agencies!$D$2:$D$81,"EDPB") -> 1 | AQ10: =COUNTIFS(guidance_agencies!$A$2:$A$81,$A10,guidance_agencies!$D$2:$D$81,"EBA") -> 0 | AR10: =COUNTIFS(guidance_agencies!$A$2:$A$81,$A10,guidance_agencies!$D$2:$D$81,"ESMA") -> 0 | AS10: =SUMIFS(secondary_acts!$S$2:$S$771,secondary_acts!$A$2:$A$771,$A10,secondary_acts!$E$2:$E$771,"implementing")+SUMIFS(secondary_acts!$S$2:$S$771,secondary_acts!$A$2:$A$771,$A10,secondary_acts!$E$2:$E$771,"delegated") -> 0 | AT10: 1004 | AU10: 28 | AV10: 2 | AW10: 2006-03-15 | AX10: 2009-11-25 | AY10: 4 | AZ10: 52000PC0385 | BA10: EUR-Lex HTML | BB10: 5154 | BC10: 39 | BD10: 14 | BE10: =IF(ISNUMBER(BB10),Q10-BB10,"") -> 3466 | BF10: =IF(AND(ISNUMBER(BB10),BB10>0),(Q10-BB10)/BB10,"") -> 0.67248739 | BG10: =IF(ISNUMBER(BC10),X10-BC10,"") -> 10 | BH10: =IF(AND(ISNUMBER(BC10),BC10>0),(X10-BC10)/BC10,"") -> 0.25641026 | BI10: =IF(ISNUMBER(BD10),AD10-BD10,"") -> 3
A11: 10 | B11: Radio Spectrum Decision | C11: Decision 676/2002/EC | D11: Connectivity | E11: enacted | F11: 2000-07-12 | G11: medium | H11: 2002-03-07 | I11: 2002-04-25 | J11: 2002-04-24 | K11: adopted | L11: adopted | M11: 32002D0676 | N11: Original act as published in the OJ | O11: https://eur-lex.europa.eu/legal-content/EN/TXT/?uri=CELEX:32002D0676 | P11: 6 | Q11: 4197 | R11: 2770 | S11: 2631 | T11: 1427 | U11: 0 | V11: 0 | W11: 0 | X11: 26 | Y11: 24 | Z11: 1 | AA11: 0 | AB11: 0 | AC11: 1 | AD11: 0 | AE11: 10 | AF11: 11 | AG11: 5 | AH11: 02002D0676-20020424 | AI11: 26 | AJ11: 0 | AK11: =COUNTIFS(secondary_acts!$A$2:$A$771,$A11,secondary_acts!$E$2:$E$771,"implementing") -> 47 | AL11: =COUNTIFS(secondary_acts!$A$2:$A$771,$A11,secondary_acts!$E$2:$E$771,"delegated") -> 0 | AM11: =COUNTIFS(secondary_acts!$A$2:$A$771,$A11,secondary_acts!$E$2:$E$771,"other Commission/Council act") -> 0 | AN11: =COUNTIFS(secondary_acts!$A$2:$A$771,$A11,secondary_acts!$E$2:$E$771,"guidance") -> 0 | AO11: =COUNTIF(guidance_web!$A$2:$A$7,$A11) -> 0 | AP11: =COUNTIFS(guidance_agencies!$A$2:$A$81,$A11,guidance_agencies!$D$2:$D$81,"EDPB") -> 0 | AQ11: =COUNTIFS(guidance_agencies!$A$2:$A$81,$A11,guidance_agencies!$D$2:$D$81,"EBA") -> 0 | AR11: =COUNTIFS(guidance_agencies!$A$2:$A$81,$A11,guidance_agencies!$D$2:$D$81,"ESMA") -> 0 | AS11: =SUMIFS(secondary_acts!$S$2:$S$771,secondary_acts!$A$2:$A$771,$A11,secondary_acts!$E$2:$E$771,"implementing")+SUMIFS(secondary_acts!$S$2:$S$771,secondary_acts!$A$2:$A$771,$A11,secondary_acts!$E$2:$E$771,"delegated") -> 818 | AV11: 0 | AY11: 1 | AZ11: 52000PC0407 | BA11: PDF text (approximate) | BB11: 4076 | BC11: 33 | BD11: 0 | BE11: =IF(ISNUMBER(BB11),Q11-BB11,"") -> 121 | BF11: =IF(AND(ISNUMBER(BB11),BB11>0),(Q11-BB11)/BB11,"") -> 0.029685967 | BG11: =IF(ISNUMBER(BC11),X11-BC11,"") -> -7 | BH11: =IF(AND(ISNUMBER(BC11),BC11>0),(X11-BC11)/BC11,"") -> -0.21212121 | BI11: =IF(ISNUMBER(BD11),AD11-BD11,"") -> 0 | BJ11: no consolidated text with amendments in EUR-Lex; consolidated count = original
A12: 11 | B12: EC Merger Regulation | C12: Regulation (EC) 139/2004 | D12: Competition & Single Market | E12: enacted | F12: 2002-12-11 | G12: high | H12: 2004-01-20 | I12: 2004-01-30 | J12: 2004-02-18 | K12: adopted | L12: adopted | M12: 32004R0139 | N12: Original act as published in the OJ | O12: https://eur-lex.europa.eu/legal-content/EN/TXT/?uri=CELEX:32004R0139 | P12: 22 | Q12: 14967 | R12: 4554 | S12: 4435 | T12: 10409 | U12: 4 | V12: 0 | W12: 0 | X12: 157 | Y12: 142 | Z12: 13 | AA12: 0 | AB12: 1 | AC12: 1 | AD12: 12 | AE12: 26 | AF12: 67 | AG12: 52 | AH12: 02004R0139-20040218 | AI12: 157 | AJ12: 12 | AK12: =COUNTIFS(secondary_acts!$A$2:$A$771,$A12,secondary_acts!$E$2:$E$771,"implementing") -> 3 | AL12: =COUNTIFS(secondary_acts!$A$2:$A$771,$A12,secondary_acts!$E$2:$E$771,"delegated") -> 0 | AM12: =COUNTIFS(secondary_acts!$A$2:$A$771,$A12,secondary_acts!$E$2:$E$771,"other Commission/Council act") -> 2 | AN12: =COUNTIFS(secondary_acts!$A$2:$A$771,$A12,secondary_acts!$E$2:$E$771,"guidance") -> 3 | AO12: =COUNTIF(guidance_web!$A$2:$A$7,$A12) -> 0 | AP12: =COUNTIFS(guidance_agencies!$A$2:$A$81,$A12,guidance_agencies!$D$2:$D$81,"EDPB") -> 0 | AQ12: =COUNTIFS(guidance_agencies!$A$2:$A$81,$A12,guidance_agencies!$D$2:$D$81,"EBA") -> 0 | AR12: =COUNTIFS(guidance_agencies!$A$2:$A$81,$A12,guidance_agencies!$D$2:$D$81,"ESMA") -> 0 | AS12: =SUMIFS(secondary_acts!$S$2:$S$771,secondary_acts!$A$2:$A$771,$A12,secondary_acts!$E$2:$E$771,"implementing")+SUMIFS(secondary_acts!$S$2:$S$771,secondary_acts!$A$2:$A$771,$A12,secondary_acts!$E$2:$E$771,"delegated") -> 355 | AV12: 0 | AY12: 8 | BA12: not comparable: proposal COM(2002) 711 not available in EUR-Lex | BE12: =IF(ISNUMBER(BB12),Q12-BB12,"") | BF12: =IF(AND(ISNUMBER(BB12),BB12>0),(Q12-BB12)/BB12,"") | BG12: =IF(ISNUMBER(BC12),X12-BC12,"") | BH12: =IF(AND(ISNUMBER(BC12),BC12>0),(X12-BC12)/BC12,"") | BI12: =IF(ISNUMBER(BD12),AD12-BD12,"") | BJ12: no consolidated text with amendments in EUR-Lex; consolidated count = original
A13: 12 | B13: IPR Enforcement Directive | C13: Directive 2004/48/EC | D13: IPR | E13: enacted | F13: 2003-01-30 | G13: high | H13: 2004-04-29 | I13: 2004-07-08 | J13: 2004-05-20 | K13: adopted | L13: adopted | M13: 32004L0048 | N13: Original act as published in the OJ | O13: https://eur-lex.europa.eu/legal-content/EN/TXT/?uri=CELEX:32004L0048 | P13: 42 | Q13: 5981 | R13: 2560 | S13: 2452 | T13: 3421 | U13: 0 | V13: 0 | W13: 0 | X13: 54 | Y13: 39 | Z13: 1 | AA13: 0 | AB13: 0 | AC13: 14 | AD13: 4 | AE13: 37 | AF13: 2 | AG13: 11 | AH13: 02004L0048-20040430 | AI13: 54 | AJ13: 4 | AK13: =COUNTIFS(secondary_acts!$A$2:$A$771,$A13,secondary_acts!$E$2:$E$771,"implementing") -> 0 | AL13: =COUNTIFS(secondary_acts!$A$2:$A$771,$A13,secondary_acts!$E$2:$E$771,"delegated") -> 0 | AM13: =COUNTIFS(secondary_acts!$A$2:$A$771,$A13,secondary_acts!$E$2:$E$771,"other Commission/Council act") -> 0 | AN13: =COUNTIFS(secondary_acts!$A$2:$A$771,$A13,secondary_acts!$E$2:$E$771,"guidance") -> 1 | AO13: =COUNTIF(guidance_web!$A$2:$A$7,$A13) -> 0 | AP13: =COUNTIFS(guidance_agencies!$A$2:$A$81,$A13,guidance_agencies!$D$2:$D$81,"EDPB") -> 0 | AQ13: =COUNTIFS(guidance_agencies!$A$2:$A$81,$A13,guidance_agencies!$D$2:$D$81,"EBA") -> 0 | AR13: =COUNTIFS(guidance_agencies!$A$2:$A$81,$A13,guidance_agencies!$D$2:$D$81,"ESMA") -> 0 | AS13: =SUMIFS(secondary_acts!$S$2:$S$771,secondary_acts!$A$2:$A$771,$A13,secondary_acts!$E$2:$E$771,"implementing")+SUMIFS(secondary_acts!$S$2:$S$771,secondary_acts!$A$2:$A$771,$A13,secondary_acts!$E$2:$E$771,"delegated") -> 0 | AT13: 2025 | AU13: 28 | AV13: 0 | AY13: 4 | AZ13: 52003PC0046 | BA13: PDF text (approximate) | BB13: 8819 | BC13: 77 | BD13: 5 | BE13: =IF(ISNUMBER(BB13),Q13-BB13,"") -> -2838 | BF13: =IF(AND(ISNUMBER(BB13),BB13>0),(Q13-BB13)/BB13,"") -> -0.32180519 | BG13: =IF(ISNUMBER(BC13),X13-BC13,"") -> -23 | BH13: =IF(AND(ISNUMBER(BC13),BC13>0),(X13-BC13)/BC13,"") -> -0.2987013 | BI13: =IF(ISNUMBER(BD13),AD13-BD13,"") -> -1
A14: 13 | B14: Unfair Commercial Practices Directive | C14: Directive 2005/29/EC | D14: E-commerce & Consumer Protection | E14: enacted | F14: 2003-06-18 | G14: high | H14: 2005-05-11 | I14: 2005-06-16 | J14: 2005-06-12 | K14: adopted | L14: adopted | M14: 32005L0029 | N14: Original act as published in the OJ | O14: https://eur-lex.europa.eu/legal-content/EN/TXT/?uri=CELEX:32005L0029 | P14: 18 | Q14: 9287 | R14: 3037 | S14: 2890 | T14: 4387 | U14: 1863 | V14: 0 | W14: 0 | X14: 48 | Y14: 44 | Z14: 1 | AA14: 1 | AB14: 0 | AC14: 2 | AD14: 5 | AE14: 29 | AF14: 2 | AG14: 12 | AH14: 02005L0029-20260927 | AI14: 56 | AJ14: 5 | AK14: =COUNTIFS(secondary_acts!$A$2:$A$771,$A14,secondary_acts!$E$2:$E$771,"implementing") -> 0 | AL14: =COUNTIFS(secondary_acts!$A$2:$A$771,$A14,secondary_acts!$E$2:$E$771,"delegated") -> 0 | AM14: =COUNTIFS(secondary_acts!$A$2:$A$771,$A14,secondary_acts!$E$2:$E$771,"other Commission/Council act") -> 0 | AN14: =COUNTIFS(secondary_acts!$A$2:$A$771,$A14,secondary_acts!$E$2:$E$771,"guidance") -> 2 | AO14: =COUNTIF(guidance_web!$A$2:$A$7,$A14) -> 0 | AP14: =COUNTIFS(guidance_agencies!$A$2:$A$81,$A14,guidance_agencies!$D$2:$D$81,"EDPB") -> 0 | AQ14: =COUNTIFS(guidance_agencies!$A$2:$A$81,$A14,guidance_agencies!$D$2:$D$81,"EBA") -> 0 | AR14: =COUNTIFS(guidance_agencies!$A$2:$A$81,$A14,guidance_agencies!$D$2:$D$81,"ESMA") -> 0 | AS14: =SUMIFS(secondary_acts!$S$2:$S$771,secondary_acts!$A$2:$A$771,$A14,secondary_acts!$E$2:$E$771,"implementing")+SUMIFS(secondary_acts!$S$2:$S$771,secondary_acts!$A$2:$A$771,$A14,secondary_acts!$E$2:$E$771,"delegated") -> 0 | AT14: 3206 | AU14: 28 | AV14: 2 | AW14: 2019-11-27 | AX14: 2024-02-28 | AY14: 4 | AZ14: 52003PC0356 | BA14: PDF text (approximate) | BB14: 6830 | BC14: 33 | BD14: 1 | BE14: =IF(ISNUMBER(BB14),Q14-BB14,"") -> 2457 | BF14: =IF(AND(ISNUMBER(BB14),BB14>0),(Q14-BB14)/BB14,"") -> 0.35973646 | BG14: =IF(ISNUMBER(BC14),X14-BC14,"") -> 15 | BH14: =IF(AND(ISNUMBER(BC14),BC14>0),(X14-BC14)/BC14,"") -> 0.45454545 | BI14: =IF(ISNUMBER(BD14),AD14-BD14,"") -> 4
A15: 14 | B15: Common VAT system Directive | C15: Directive 2006/112/EC | D15: Finance | E15: enacted | F15: 2004-04-15 | G15: medium | H15: 2006-11-28 | I15: 2006-12-12 | J15: 2007-01-01 | K15: adopted | L15: adopted | M15: 32006L0112 | N15: Original act as published in the OJ | O15: https://eur-lex.europa.eu/legal-content/EN/TXT/?uri=CELEX:32006L0112 | P15: 118 | Q15: 58443 | R15: 3612 | S15: 3532 | T15: 43412 | U15: 11419 | V15: 0 | W15: 0 | X15: 406 | Y15: 349 | Z15: 48 | AA15: 0 | AB15: 6 | AC15: 3 | AD15: 57 | AE15: 144 | AF15: 40 | AG15: 165 | AH15: 02006L0112-20100811 | AI15: 425 | AJ15: 64 | AK15: =COUNTIFS(secondary_acts!$A$2:$A$771,$A15,secondary_acts!$E$2:$E$771,"implementing") -> 183 | AL15: =COUNTIFS(secondary_acts!$A$2:$A$771,$A15,secondary_acts!$E$2:$E$771,"delegated") -> 0 | AM15: =COUNTIFS(secondary_acts!$A$2:$A$771,$A15,secondary_acts!$E$2:$E$771,"other Commission/Council act") -> 1 | AN15: =COUNTIFS(secondary_acts!$A$2:$A$771,$A15,secondary_acts!$E$2:$E$771,"guidance") -> 0 | AO15: =COUNTIF(guidance_web!$A$2:$A$7,$A15) -> 0 | AP15: =COUNTIFS(guidance_agencies!$A$2:$A$81,$A15,guidance_agencies!$D$2:$D$81,"EDPB") -> 0 | AQ15: =COUNTIFS(guidance_agencies!$A$2:$A$81,$A15,guidance_agencies!$D$2:$D$81,"EBA") -> 0 | AR15: =COUNTIFS(guidance_agencies!$A$2:$A$81,$A15,guidance_agencies!$D$2:$D$81,"ESMA") -> 0 | AS15: =SUMIFS(secondary_acts!$S$2:$S$771,secondary_acts!$A$2:$A$771,$A15,secondary_acts!$E$2:$E$771,"implementing")+SUMIFS(secondary_acts!$S$2:$S$771,secondary_acts!$A$2:$A$771,$A15,secondary_acts!$E$2:$E$771,"delegated") -> 487 | AT15: 1745 | AU15: 26 | AV15: 35 | AW15: 2006-12-19 | AX15: 2025-07-18 | AY15: 23 | AZ15: 52004PC0246 | BA15: not comparable: recast proposal: PDF includes struck-through and correlation material | BE15: =IF(ISNUMBER(BB15),Q15-BB15,"") | BF15: =IF(AND(ISNUMBER(BB15),BB15>0),(Q15-BB15)/BB15,"") | BG15: =IF(ISNUMBER(BC15),X15-BC15,"") | BH15: =IF(AND(ISNUMBER(BC15),BC15>0),(X15-BC15)/BC15,"") | BI15: =IF(ISNUMBER(BD15),AD15-BD15,"")
A16: 15 | B16: Audiovisual Media Services Directive | C16: Directive 2010/13/EU | D16: Media | E16: enacted | F16: 2005-12-13 | G16: medium | H16: 2010-03-10 | I16: 2010-03-10 | J16: 2010-05-05 | K16: adopted | L16: adopted | M16: 32010L0013 | N16: Original act as published in the OJ | O16: https://eur-lex.europa.eu/legal-content/EN/TXT/?uri=CELEX:32010L0013 | P16: 24 | Q16: 15640 | R16: 8388 | S16: 8276 | T16: 6686 | U16: 566 | V16: 0 | W16: 0 | X16: 117 | Y16: 67 | Z16: 29 | AA16: 2 | AB16: 1 | AC16: 18 | AD16: 9 | AE16: 52 | AF16: 14 | AG16: 42 | AH16: 02010L0013-20250208 | AI16: 235 | AJ16: 17 | AK16: =COUNTIFS(secondary_acts!$A$2:$A$771,$A16,secondary_acts!$E$2:$E$771,"implementing") -> 0 | AL16: =COUNTIFS(secondary_acts!$A$2:$A$771,$A16,secondary_acts!$E$2:$E$771,"delegated") -> 0 | AM16: =COUNTIFS(secondary_acts!$A$2:$A$771,$A16,secondary_acts!$E$2:$E$771,"other Commission/Council act") -> 0 | AN16: =COUNTIFS(secondary_acts!$A$2:$A$771,$A16,secondary_acts!$E$2:$E$771,"guidance") -> 3 | AO16: =COUNTIF(guidance_web!$A$2:$A$7,$A16) -> 0 | AP16: =COUNTIFS(guidance_agencies!$A$2:$A$81,$A16,guidance_agencies!$D$2:$D$81,"EDPB") -> 0 | AQ16: =COUNTIFS(guidance_agencies!$A$2:$A$81,$A16,guidance_agencies!$D$2:$D$81,"EBA") -> 0 | AR16: =COUNTIFS(guidance_agencies!$A$2:$A$81,$A16,guidance_agencies!$D$2:$D$81,"ESMA") -> 0 | AS16: =SUMIFS(secondary_acts!$S$2:$S$771,secondary_acts!$A$2:$A$771,$A16,secondary_acts!$E$2:$E$771,"implementing")+SUMIFS(secondary_acts!$S$2:$S$771,secondary_acts!$A$2:$A$771,$A16,secondary_acts!$E$2:$E$771,"delegated") -> 0 | AT16: 471 | AU16: 19 | AV16: 2 | AW16: 2018-11-14 | AX16: 2024-04-11 | AY16: 3 | AZ16: 52009PC0185 | BA16: EUR-Lex HTML | BB16: 17291 | BC16: 117 | BD16: 9 | BE16: =IF(ISNUMBER(BB16),Q16-BB16,"") -> -1651 | BF16: =IF(AND(ISNUMBER(BB16),BB16>0),(Q16-BB16)/BB16,"") -> -0.095483199 | BG16: =IF(ISNUMBER(BC16),X16-BC16,"") -> 0 | BH16: =IF(AND(ISNUMBER(BC16),BC16>0),(X16-BC16)/BC16,"") -> 0 | BI16: =IF(ISNUMBER(BD16),AD16-BD16,"") -> 0
A17: 16 | B17: European Statistics Regulation | C17: Regulation (EC) 223/2009 | D17: Data & Privacy | E17: enacted | F17: 2007-10-16 | G17: high | H17: 2009-03-11 | I17: 2009-04-02 | J17: 2009-04-01 | K17: adopted | L17: adopted | M17: 32009R0223 | N17: Original act as published in the OJ | O17: https://eur-lex.europa.eu/legal-content/EN/TXT/?uri=CELEX:32009R0223 | P17: 10 | Q17: 6514 | R17: 2317 | S17: 2143 | T17: 4197 | U17: 0 | V17: 0 | W17: 0 | X17: 85 | Y17: 81 | Z17: 1 | AA17: 0 | AB17: 2 | AC17: 1 | AD17: 5 | AE17: 5 | AF17: 37 | AG17: 38 | AH17: 02009R0223-20241226 | AI17: 175 | AJ17: 10 | AK17: =COUNTIFS(secondary_acts!$A$2:$A$771,$A17,secondary_acts!$E$2:$E$771,"implementing") -> 1 | AL17: =COUNTIFS(secondary_acts!$A$2:$A$771,$A17,secondary_acts!$E$2:$E$771,"delegated") -> 0 | AM17: =COUNTIFS(secondary_acts!$A$2:$A$771,$A17,secondary_acts!$E$2:$E$771,"other Commission/Council act") -> 2 | AN17: =COUNTIFS(secondary_acts!$A$2:$A$771,$A17,secondary_acts!$E$2:$E$771,"guidance") -> 0 | AO17: =COUNTIF(guidance_web!$A$2:$A$7,$A17) -> 0 | AP17: =COUNTIFS(guidance_agencies!$A$2:$A$81,$A17,guidance_agencies!$D$2:$D$81,"EDPB") -> 0 | AQ17: =COUNTIFS(guidance_agencies!$A$2:$A$81,$A17,guidance_agencies!$D$2:$D$81,"EBA") -> 0 | AR17: =COUNTIFS(guidance_agencies!$A$2:$A$81,$A17,guidance_agencies!$D$2:$D$81,"ESMA") -> 0 | AS17: =SUMIFS(secondary_acts!$S$2:$S$771,secondary_acts!$A$2:$A$771,$A17,secondary_acts!$E$2:$E$771,"implementing")+SUMIFS(secondary_acts!$S$2:$S$771,secondary_acts!$A$2:$A$771,$A17,secondary_acts!$E$2:$E$771,"delegated") -> 43 | AV17: 2 | AW17: 2015-04-29 | AX17: 2024-11-27 | AY17: 2 | AZ17: 52007PC0625 | BA17: EUR-Lex HTML | BB17: 5421 | BC17: 68 | BD17: 4 | BE17: =IF(ISNUMBER(BB17),Q17-BB17,"") -> 1093 | BF17: =IF(AND(ISNUMBER(BB17),BB17>0),(Q17-BB17)/BB17,"") -> 0.20162332 | BG17: =IF(ISNUMBER(BC17),X17-BC17,"") -> 17 | BH17: =IF(AND(ISNUMBER(BC17),BC17>0),(X17-BC17)/BC17,"") -> 0.25 | BI17: =IF(ISNUMBER(BD17),AD17-BD17,"") -> 1
A18: 17 | B18: Toys Safety Directive | C18: Directive 2009/48/EC | D18: Trust & Safety | E18: enacted | F18: 2008-01-25 | G18: high | H18: 2009-06-18 | I18: 2009-06-18 | J18: 2009-07-20 | K18: adopted | L18: adopted | M18: 32009L0048 | N18: Original act as published in the OJ | O18: https://eur-lex.europa.eu/legal-content/EN/TXT/?uri=CELEX:32009L0048 | P18: 37 | Q18: 19379 | R18: 3870 | S18: 3771 | T18: 9594 | U18: 5915 | V18: 0 | W18: 0 | X18: 329 | Y18: 270 | Z18: 37 | AA18: 3 | AB18: 0 | AC18: 19 | AD18: 88 | AE18: 59 | AF18: 37 | AG18: 145 | AH18: 02009L0048-20260829 | AI18: 329 | AJ18: 88 | AK18: =COUNTIFS(secondary_acts!$A$2:$A$771,$A18,secondary_acts!$E$2:$E$771,"implementing") -> 1 | AL18: =COUNTIFS(secondary_acts!$A$2:$A$771,$A18,secondary_acts!$E$2:$E$771,"delegated") -> 0 | AM18: =COUNTIFS(secondary_acts!$A$2:$A$771,$A18,secondary_acts!$E$2:$E$771,"other Commission/Council act") -> 18 | AN18: =COUNTIFS(secondary_acts!$A$2:$A$771,$A18,secondary_acts!$E$2:$E$771,"guidance") -> 0 | AO18: =COUNTIF(guidance_web!$A$2:$A$7,$A18) -> 0 | AP18: =COUNTIFS(guidance_agencies!$A$2:$A$81,$A18,guidance_agencies!$D$2:$D$81,"EDPB") -> 0 | AQ18: =COUNTIFS(guidance_agencies!$A$2:$A$81,$A18,guidance_agencies!$D$2:$D$81,"EBA") -> 0 | AR18: =COUNTIFS(guidance_agencies!$A$2:$A$81,$A18,guidance_agencies!$D$2:$D$81,"ESMA") -> 0 | AS18: =SUMIFS(secondary_acts!$S$2:$S$771,secondary_acts!$A$2:$A$771,$A18,secondary_acts!$E$2:$E$771,"implementing")+SUMIFS(secondary_acts!$S$2:$S$771,secondary_acts!$A$2:$A$771,$A18,secondary_acts!$E$2:$E$771,"delegated") -> 0 | AT18: 1613 | AU18: 15 | AV18: 18 | AW18: 2012-03-02 | AX18: 2026-01-28 | AY18: 5 | AZ18: 52008PC0009 | BA18: EUR-Lex HTML | BB18: 14934 | BC18: 283 | BD18: 85 | BE18: =IF(ISNUMBER(BB18),Q18-BB18,"") -> 4445 | BF18: =IF(AND(ISNUMBER(BB18),BB18>0),(Q18-BB18)/BB18,"") -> 0.29764296 | BG18: =IF(ISNUMBER(BC18),X18-BC18,"") -> 46 | BH18: =IF(AND(ISNUMBER(BC18),BC18>0),(X18-BC18)/BC18,"") -> 0.16254417 | BI18: =IF(ISNUMBER(BD18),AD18-BD18,"") -> 3
A19: 18 | B19: Consumer Rights Directive | C19: Directive 2011/83/EU | D19: E-commerce & Consumer Protection | E19: enacted | F19: 2008-10-08 | G19: high | H19: 2011-10-25 | I19: 2011-11-22 | J19: 2011-12-12 | K19: adopted | L19: adopted | M19: 32011L0083 | N19: Original act as published in the OJ | O19: https://eur-lex.europa.eu/legal-content/EN/TXT/?uri=CELEX:32011L0083 | P19: 25 | Q19: 16782 | R19: 7167 | S19: 7021 | T19: 7762 | U19: 1853 | V19: 0 | W19: 0 | X19: 105 | Y19: 82 | Z19: 17 | AA19: 1 | AB19: 1 | AC19: 4 | AD19: 47 | AE19: 23 | AF19: 5 | AG19: 30 | AH19: 02011L0083-20260927 | AI19: 182 | AJ19: 87 | AK19: =COUNTIFS(secondary_acts!$A$2:$A$771,$A19,secondary_acts!$E$2:$E$771,"implementing") -> 1 | AL19: =COUNTIFS(secondary_acts!$A$2:$A$771,$A19,secondary_acts!$E$2:$E$771,"delegated") -> 0 | AM19: =COUNTIFS(secondary_acts!$A$2:$A$771,$A19,secondary_acts!$E$2:$E$771,"other Commission/Council act") -> 0 | AN19: =COUNTIFS(secondary_acts!$A$2:$A$771,$A19,secondary_acts!$E$2:$E$771,"guidance") -> 1 | AO19: =COUNTIF(guidance_web!$A$2:$A$7,$A19) -> 0 | AP19: =COUNTIFS(guidance_agencies!$A$2:$A$81,$A19,guidance_agencies!$D$2:$D$81,"EDPB") -> 0 | AQ19: =COUNTIFS(guidance_agencies!$A$2:$A$81,$A19,guidance_agencies!$D$2:$D$81,"EBA") -> 0 | AR19: =COUNTIFS(guidance_agencies!$A$2:$A$81,$A19,guidance_agencies!$D$2:$D$81,"ESMA") -> 0 | AS19: =SUMIFS(secondary_acts!$S$2:$S$771,secondary_acts!$A$2:$A$771,$A19,secondary_acts!$E$2:$E$771,"implementing")+SUMIFS(secondary_acts!$S$2:$S$771,secondary_acts!$A$2:$A$771,$A19,secondary_acts!$E$2:$E$771,"delegated") -> 13 | AT19: 1559 | AU19: 28 | AV19: 4 | AW19: 2015-11-25 | AX19: 2024-02-28 | AY19: 6 | AZ19: 52008PC0614 | BA19: EUR-Lex HTML | BB19: 14168 | BC19: 98 | BD19: 40 | BE19: =IF(ISNUMBER(BB19),Q19-BB19,"") -> 2614 | BF19: =IF(AND(ISNUMBER(BB19),BB19>0),(Q19-BB19)/BB19,"") -> 0.18450028 | BG19: =IF(ISNUMBER(BC19),X19-BC19,"") -> 7 | BH19: =IF(AND(ISNUMBER(BC19),BC19>0),(X19-BC19)/BC19,"") -> 0.071428571 | BI19: =IF(ISNUMBER(BD19),AD19-BD19,"") -> 7
A20: 19 | B20: Administrative cooperation in taxation (DAC) | C20: Directive 2011/16/EU | D20: Finance | E20: enacted | F20: 2009-02-02 | G20: high | H20: 2011-02-15 | I20: 2011-02-15 | J20: 2011-03-11 | K20: adopted | L20: adopted | M20: 32011L0016 | N20: Original act as published in the OJ | O20: https://eur-lex.europa.eu/legal-content/EN/TXT/?uri=CELEX:32011L0016 | P20: 12 | Q20: 7830 | R20: 1814 | S20: 1712 | T20: 6016 | U20: 0 | V20: 0 | W20: 0 | X20: 111 | Y20: 100 | Z20: 5 | AA20: 3 | AB20: 3 | AC20: 0 | AD20: 2 | AE20: 69 | AF20: 17 | AG20: 23 | AH20: 02011L0016-20260101 | AI20: 613 | AJ20: 158 | AK20: =COUNTIFS(secondary_acts!$A$2:$A$771,$A20,secondary_acts!$E$2:$E$771,"implementing") -> 14 | AL20: =COUNTIFS(secondary_acts!$A$2:$A$771,$A20,secondary_acts!$E$2:$E$771,"delegated") -> 0 | AM20: =COUNTIFS(secondary_acts!$A$2:$A$771,$A20,secondary_acts!$E$2:$E$771,"other Commission/Council act") -> 0 | AN20: =COUNTIFS(secondary_acts!$A$2:$A$771,$A20,secondary_acts!$E$2:$E$771,"guidance") -> 0 | AO20: =COUNTIF(guidance_web!$A$2:$A$7,$A20) -> 0 | AP20: =COUNTIFS(guidance_agencies!$A$2:$A$81,$A20,guidance_agencies!$D$2:$D$81,"EDPB") -> 0 | AQ20: =COUNTIFS(guidance_agencies!$A$2:$A$81,$A20,guidance_agencies!$D$2:$D$81,"EBA") -> 0 | AR20: =COUNTIFS(guidance_agencies!$A$2:$A$81,$A20,guidance_agencies!$D$2:$D$81,"ESMA") -> 0 | AS20: =SUMIFS(secondary_acts!$S$2:$S$771,secondary_acts!$A$2:$A$771,$A20,secondary_acts!$E$2:$E$771,"implementing")+SUMIFS(secondary_acts!$S$2:$S$771,secondary_acts!$A$2:$A$771,$A20,secondary_acts!$E$2:$E$771,"delegated") -> 100 | AT20: 380 | AU20: 28 | AV20: 9 | AW20: 2014-12-09 | AX20: 2025-04-14 | AY20: 5 | AZ20: 52009PC0029 | BA20: EUR-Lex HTML | BB20: 6065 | BC20: 93 | BD20: 2 | BE20: =IF(ISNUMBER(BB20),Q20-BB20,"") -> 1765 | BF20: =IF(AND(ISNUMBER(BB20),BB20>0),(Q20-BB20)/BB20,"") -> 0.29101401 | BG20: =IF(ISNUMBER(BC20),X20-BC20,"") -> 18 | BH20: =IF(AND(ISNUMBER(BC20),BC20>0),(X20-BC20)/BC20,"") -> 0.19354839 | BI20: =IF(ISNUMBER(BD20),AD20-BD20,"") -> 0
A21: 20 | B21: General Data Protection Regulation | C21: Regulation (EU) 2016/679 | D21: Data & Privacy | E21: enacted | F21: 2012-01-25 | G21: high | H21: 2016-04-27 | I21: 2016-05-04 | J21: 2016-05-24 | K21: adopted | L21: adopted | M21: 32016R0679 | N21: Original act as published in the OJ | O21: https://eur-lex.europa.eu/legal-content/EN/TXT/?uri=CELEX:32016R0679 | P21: 88 | Q21: 54331 | R21: 23839 | S21: 23692 | T21: 30492 | U21: 0 | V21: 0 | W21: 0 | X21: 417 | Y21: 370 | Z21: 24 | AA21: 3 | AB21: 8 | AC21: 12 | AD21: 99 | AE21: 129 | AF21: 81 | AG21: 108 | AH21: 02016R0679-20160504 | AI21: 415 | AJ21: 99 | AK21: =COUNTIFS(secondary_acts!$A$2:$A$771,$A21,secondary_acts!$E$2:$E$771,"implementing") -> 11 | AL21: =COUNTIFS(secondary_acts!$A$2:$A$771,$A21,secondary_acts!$E$2:$E$771,"delegated") -> 0 | AM21: =COUNTIFS(secondary_acts!$A$2:$A$771,$A21,secondary_acts!$E$2:$E$771,"other Commission/Council act") -> 0 | AN21: =COUNTIFS(secondary_acts!$A$2:$A$771,$A21,secondary_acts!$E$2:$E$771,"guidance") -> 2 | AO21: =COUNTIF(guidance_web!$A$2:$A$7,$A21) -> 0 | AP21: =COUNTIFS(guidance_agencies!$A$2:$A$81,$A21,guidance_agencies!$D$2:$D$81,"EDPB") -> 47 | AQ21: =COUNTIFS(guidance_agencies!$A$2:$A$81,$A21,guidance_agencies!$D$2:$D$81,"EBA") -> 0 | AR21: =COUNTIFS(guidance_agencies!$A$2:$A$81,$A21,guidance_agencies!$D$2:$D$81,"ESMA") -> 0 | AS21: =SUMIFS(secondary_acts!$S$2:$S$771,secondary_acts!$A$2:$A$771,$A21,secondary_acts!$E$2:$E$771,"implementing")+SUMIFS(secondary_acts!$S$2:$S$771,secondary_acts!$A$2:$A$771,$A21,secondary_acts!$E$2:$E$771,"delegated") -> 927 | AV21: 0 | AY21: 3 | AZ21: 52012PC0011 | BA21: EUR-Lex HTML | BB21: 35380 | BC21: 362 | BD21: 78 | BE21: =IF(ISNUMBER(BB21),Q21-BB21,"") -> 18951 | BF21: =IF(AND(ISNUMBER(BB21),BB21>0),(Q21-BB21)/BB21,"") -> 0.53564161 | BG21: =IF(ISNUMBER(BC21),X21-BC21,"") -> 55 | BH21: =IF(AND(ISNUMBER(BC21),BC21>0),(X21-BC21)/BC21,"") -> 0.1519337 | BI21: =IF(ISNUMBER(BD21),AD21-BD21,"") -> 21
A22: 21 | B22: Law Enforcement Directive | C22: Directive (EU) 2016/680 | D22: Law Enforcement | E22: enacted | F22: 2012-01-25 | G22: high | H22: 2016-04-27 | I22: 2016-05-04 | J22: 2016-05-05 | K22: adopted | L22: adopted | M22: 32016L0680 | N22: Original act as published in the OJ | O22: https://eur-lex.europa.eu/legal-content/EN/TXT/?uri=CELEX:32016L0680 | P22: 43 | Q22: 26710 | R22: 12941 | S22: 12790 | T22: 13769 | U22: 0 | V22: 0 | W22: 0 | X22: 225 | Y22: 206 | Z22: 11 | AA22: 1 | AB22: 2 | AC22: 5 | AD22: 25 | AE22: 129 | AF22: 26 | AG22: 45 | AH22: 02016L0680-20160504 | AI22: 225 | AJ22: 25 | AK22: =COUNTIFS(secondary_acts!$A$2:$A$771,$A22,secondary_acts!$E$2:$E$771,"implementing") -> 3 | AL22: =COUNTIFS(secondary_acts!$A$2:$A$771,$A22,secondary_acts!$E$2:$E$771,"delegated") -> 0 | AM22: =COUNTIFS(secondary_acts!$A$2:$A$771,$A22,secondary_acts!$E$2:$E$771,"other Commission/Council act") -> 0 | AN22: =COUNTIFS(secondary_acts!$A$2:$A$771,$A22,secondary_acts!$E$2:$E$771,"guidance") -> 0 | AO22: =COUNTIF(guidance_web!$A$2:$A$7,$A22) -> 0 | AP22: =COUNTIFS(guidance_agencies!$A$2:$A$81,$A22,guidance_agencies!$D$2:$D$81,"EDPB") -> 2 | AQ22: =COUNTIFS(guidance_agencies!$A$2:$A$81,$A22,guidance_agencies!$D$2:$D$81,"EBA") -> 0 | AR22: =COUNTIFS(guidance_agencies!$A$2:$A$81,$A22,guidance_agencies!$D$2:$D$81,"ESMA") -> 0 | AS22: =SUMIFS(secondary_acts!$S$2:$S$771,secondary_acts!$A$2:$A$771,$A22,secondary_acts!$E$2:$E$771,"implementing")+SUMIFS(secondary_acts!$S$2:$S$771,secondary_acts!$A$2:$A$771,$A22,secondary_acts!$E$2:$E$771,"delegated") -> 5 | AT22: 3772 | AU22: 28 | AV22: 0 | AY22: 3 | AZ22: 52012PC0010 | BA22: EUR-Lex HTML | BB22: 16067 | BC22: 193 | BD22: 26 | BE22: =IF(ISNUMBER(BB22),Q22-BB22,"") -> 10643 | BF22: =IF(AND(ISNUMBER(BB22),BB22>0),(Q22-BB22)/BB22,"") -> 0.66241364 | BG22: =IF(ISNUMBER(BC22),X22-BC22,"") -> 32 | BH22: =IF(AND(ISNUMBER(BC22),BC22>0),(X22-BC22)/BC22,"") -> 0.16580311 | BI22: =IF(ISNUMBER(BD22),AD22-BD22,"") -> -1
A23: 22 | B23: eIDAS Regulation | C23: Regulation (EU) 910/2014 | D23: Trust & Safety | E23: enacted | F23: 2012-06-04 | G23: high | H23: 2014-07-23 | I23: 2014-08-28 | J23: 2014-09-17 | K23: adopted | L23: adopted | M23: 32014R0910 | N23: Original act as published in the OJ | O23: https://eur-lex.europa.eu/legal-content/EN/TXT/?uri=CELEX:32014R0910 | P23: 42 | Q23: 18535 | R23: 5975 | S23: 5856 | T23: 11516 | U23: 1044 | V23: 0 | W23: 0 | X23: 181 | Y23: 154 | Z23: 16 | AA23: 5 | AB23: 2 | AC23: 4 | AD23: 26 | AE23: 45 | AF23: 52 | AG23: 58 | AH23: 02014R0910-20240520 | AI23: 428 | AJ23: 76 | AK23: =COUNTIFS(secondary_acts!$A$2:$A$771,$A23,secondary_acts!$E$2:$E$771,"implementing") -> 43 | AL23: =COUNTIFS(secondary_acts!$A$2:$A$771,$A23,secondary_acts!$E$2:$E$771,"delegated") -> 0 | AM23: =COUNTIFS(secondary_acts!$A$2:$A$771,$A23,secondary_acts!$E$2:$E$771,"other Commission/Council act") -> 0 | AN23: =COUNTIFS(secondary_acts!$A$2:$A$771,$A23,secondary_acts!$E$2:$E$771,"guidance") -> 0 | AO23: =COUNTIF(guidance_web!$A$2:$A$7,$A23) -> 0 | AP23: =COUNTIFS(guidance_agencies!$A$2:$A$81,$A23,guidance_agencies!$D$2:$D$81,"EDPB") -> 0 | AQ23: =COUNTIFS(guidance_agencies!$A$2:$A$81,$A23,guidance_agencies!$D$2:$D$81,"EBA") -> 0 | AR23: =COUNTIFS(guidance_agencies!$A$2:$A$81,$A23,guidance_agencies!$D$2:$D$81,"ESMA") -> 0 | AS23: =SUMIFS(secondary_acts!$S$2:$S$771,secondary_acts!$A$2:$A$771,$A23,secondary_acts!$E$2:$E$771,"implementing")+SUMIFS(secondary_acts!$S$2:$S$771,secondary_acts!$A$2:$A$771,$A23,secondary_acts!$E$2:$E$771,"delegated") -> 1377 | AV23: 2 | AW23: 2022-12-14 | AX23: 2024-04-11 | AY23: 12 | AZ23: 52012PC0238 | BA23: EUR-Lex HTML | BB23: 12741 | BC23: 163 | BD23: 15 | BE23: =IF(ISNUMBER(BB23),Q23-BB23,"") -> 5794 | BF23: =IF(AND(ISNUMBER(BB23),BB23>0),(Q23-BB23)/BB23,"") -> 0.45475237 | BG23: =IF(ISNUMBER(BC23),X23-BC23,"") -> 18 | BH23: =IF(AND(ISNUMBER(BC23),BC23>0),(X23-BC23)/BC23,"") -> 0.11042945 | BI23: =IF(ISNUMBER(BD23),AD23-BD23,"") -> 11
A24: 23 | B24: Payment Services Directive 2 (PSD2) | C24: Directive (EU) 2015/2366 | D24: Finance | E24: enacted | F24: 2013-07-24 | G24: high | H24: 2015-11-25 | I24: 2015-12-23 | J24: 2016-01-12 | K24: adopted | L24: adopted | M24: 32015L2366 | N24: Original act as published in the OJ | O24: https://eur-lex.europa.eu/legal-content/EN/TXT/?uri=CELEX:32015L2366 | P24: 93 | Q24: 47656 | R24: 14399 | S24: 14254 | T24: 31276 | U24: 1981 | V24: 0 | W24: 0 | X24: 462 | Y24: 354 | Z24: 46 | AA24: 7 | AB24: 4 | AC24: 51 | AD24: 172 | AE24: 171 | AF24: 44 | AG24: 75 | AH24: 02015L2366-20250117 | AI24: 470 | AJ24: 173 | AK24: =COUNTIFS(secondary_acts!$A$2:$A$771,$A24,secondary_acts!$E$2:$E$771,"implementing") -> 1 | AL24: =COUNTIFS(secondary_acts!$A$2:$A$771,$A24,secondary_acts!$E$2:$E$771,"delegated") -> 8 | AM24: =COUNTIFS(secondary_acts!$A$2:$A$771,$A24,secondary_acts!$E$2:$E$771,"other Commission/Council act") -> 0 | AN24: =COUNTIFS(secondary_acts!$A$2:$A$771,$A24,secondary_acts!$E$2:$E$771,"guidance") -> 0 | AO24: =COUNTIF(guidance_web!$A$2:$A$7,$A24) -> 0 | AP24: =COUNTIFS(guidance_agencies!$A$2:$A$81,$A24,guidance_agencies!$D$2:$D$81,"EDPB") -> 1 | AQ24: =COUNTIFS(guidance_agencies!$A$2:$A$81,$A24,guidance_agencies!$D$2:$D$81,"EBA") -> 11 | AR24: =COUNTIFS(guidance_agencies!$A$2:$A$81,$A24,guidance_agencies!$D$2:$D$81,"ESMA") -> 0 | AS24: =SUMIFS(secondary_acts!$S$2:$S$771,secondary_acts!$A$2:$A$771,$A24,secondary_acts!$E$2:$E$771,"implementing")+SUMIFS(secondary_acts!$S$2:$S$771,secondary_acts!$A$2:$A$771,$A24,secondary_acts!$E$2:$E$771,"delegated") -> 468 | AT24: 2499 | AU24: 28 | AV24: 2 | AW24: 2022-12-14 | AX24: 2024-03-13 | AY24: 8 | AZ24: 52013PC0547 | BA24: EUR-Lex HTML | BB24: 34397 | BC24: 360 | BD24: 116 | BE24: =IF(ISNUMBER(BB24),Q24-BB24,"") -> 13259 | BF24: =IF(AND(ISNUMBER(BB24),BB24>0),(Q24-BB24)/BB24,"") -> 0.38546966 | BG24: =IF(ISNUMBER(BC24),X24-BC24,"") -> 102 | BH24: =IF(AND(ISNUMBER(BC24),BC24>0),(X24-BC24)/BC24,"") -> 0.28333333 | BI24: =IF(ISNUMBER(BD24),AD24-BD24,"") -> 56
A25: 24 | B25: Open Internet Access Regulation | C25: Regulation (EU) 2015/2120 | D25: Connectivity | E25: enacted | F25: 2013-09-11 | G25: high | H25: 2015-11-25 | I25: 2015-11-26 | J25: 2015-11-29 | K25: adopted | L25: adopted | M25: 32015R2120 | N25: Original act as published in the OJ | O25: https://eur-lex.europa.eu/legal-content/EN/TXT/?uri=CELEX:32015R2120 | P25: 18 | Q25: 11290 | R25: 4983 | S25: 4826 | T25: 6307 | U25: 0 | V25: 0 | W25: 0 | X25: 72 | Y25: 59 | Z25: 10 | AA25: 2 | AB25: 0 | AC25: 1 | AD25: 29 | AE25: 11 | AF25: 18 | AG25: 14 | AH25: 02015R2120-20151126 | AI25: 72 | AJ25: 29 | AK25: =COUNTIFS(secondary_acts!$A$2:$A$771,$A25,secondary_acts!$E$2:$E$771,"implementing") -> 1 | AL25: =COUNTIFS(secondary_acts!$A$2:$A$771,$A25,secondary_acts!$E$2:$E$771,"delegated") -> 0 | AM25: =COUNTIFS(secondary_acts!$A$2:$A$771,$A25,secondary_acts!$E$2:$E$771,"other Commission/Council act") -> 0 | AN25: =COUNTIFS(secondary_acts!$A$2:$A$771,$A25,secondary_acts!$E$2:$E$771,"guidance") -> 0 | AO25: =COUNTIF(guidance_web!$A$2:$A$7,$A25) -> 0 | AP25: =COUNTIFS(guidance_agencies!$A$2:$A$81,$A25,guidance_agencies!$D$2:$D$81,"EDPB") -> 0 | AQ25: =COUNTIFS(guidance_agencies!$A$2:$A$81,$A25,guidance_agencies!$D$2:$D$81,"EBA") -> 0 | AR25: =COUNTIFS(guidance_agencies!$A$2:$A$81,$A25,guidance_agencies!$D$2:$D$81,"ESMA") -> 0 | AS25: =SUMIFS(secondary_acts!$S$2:$S$771,secondary_acts!$A$2:$A$771,$A25,secondary_acts!$E$2:$E$771,"implementing")+SUMIFS(secondary_acts!$S$2:$S$771,secondary_acts!$A$2:$A$771,$A25,secondary_acts!$E$2:$E$771,"delegated") -> 10 | AV25: 2 | AW25: 2018-12-11 | AX25: 2024-04-29 | AY25: 3 | AZ25: 52013PC0627 | BA25: EUR-Lex HTML | BB25: 30255 | BC25: 293 | BD25: 44 | BE25: =IF(ISNUMBER(BB25),Q25-BB25,"") -> -18965 | BF25: =IF(AND(ISNUMBER(BB25),BB25>0),(Q25-BB25)/BB25,"") -> -0.62683854 | BG25: =IF(ISNUMBER(BC25),X25-BC25,"") -> -221 | BH25: =IF(AND(ISNUMBER(BC25),BC25>0),(X25-BC25)/BC25,"") -> -0.75426621 | BI25: =IF(ISNUMBER(BD25),AD25-BD25,"") -> -15 | BJ25: no consolidated text with amendments in EUR-Lex; consolidated count = original
A26: 25 | B26: Technology Transfer Block Exemption | C26: Regulation (EU) 316/2014 | D26: Competition & Single Market | E26: enacted | F26: 2013-02-20 | G26: low | H26: 2014-03-21 | I26: 2014-03-28 | J26: 2014-05-01 | K26: adopted | L26: adopted | M26: 32014R0316 | N26: Original act as published in the OJ | O26: https://eur-lex.europa.eu/legal-content/EN/TXT/?uri=CELEX:32014R0316 | P26: 7 | Q26: 4660 | R26: 1553 | S26: 1431 | T26: 3107 | U26: 0 | V26: 0 | W26: 0 | X26: 0 | Y26: 0 | Z26: 0 | AA26: 0 | AB26: 0 | AC26: 0 | AD26: 0 | AE26: 0 | AF26: 0 | AG26: 0 | AH26: 02014R0316-20140501 | AI26: 0 | AJ26: 0 | AK26: =COUNTIFS(secondary_acts!$A$2:$A$771,$A26,secondary_acts!$E$2:$E$771,"implementing") -> 0 | AL26: =COUNTIFS(secondary_acts!$A$2:$A$771,$A26,secondary_acts!$E$2:$E$771,"delegated") -> 0 | AM26: =COUNTIFS(secondary_acts!$A$2:$A$771,$A26,secondary_acts!$E$2:$E$771,"other Commission/Council act") -> 0 | AN26: =COUNTIFS(secondary_acts!$A$2:$A$771,$A26,secondary_acts!$E$2:$E$771,"guidance") -> 0 | AO26: =COUNTIF(guidance_web!$A$2:$A$7,$A26) -> 0 | AP26: =COUNTIFS(guidance_agencies!$A$2:$A$81,$A26,guidance_agencies!$D$2:$D$81,"EDPB") -> 0 | AQ26: =COUNTIFS(guidance_agencies!$A$2:$A$81,$A26,guidance_agencies!$D$2:$D$81,"EBA") -> 0 | AR26: =COUNTIFS(guidance_agencies!$A$2:$A$81,$A26,guidance_agencies!$D$2:$D$81,"ESMA") -> 0 | AS26: =SUMIFS(secondary_acts!$S$2:$S$771,secondary_acts!$A$2:$A$771,$A26,secondary_acts!$E$2:$E$771,"implementing")+SUMIFS(secondary_acts!$S$2:$S$771,secondary_acts!$A$2:$A$771,$A26,secondary_acts!$E$2:$E$771,"delegated") -> 0 | AV26: 0 | AY26: 2 | BA26: no legislative proposal (Commission act) | BE26: =IF(ISNUMBER(BB26),Q26-BB26,"") | BF26: =IF(AND(ISNUMBER(BB26),BB26>0),(Q26-BB26)/BB26,"") | BG26: =IF(ISNUMBER(BC26),X26-BC26,"") | BH26: =IF(AND(ISNUMBER(BC26),BC26>0),(X26-BC26)/BC26,"") | BI26: =IF(ISNUMBER(BD26),AD26-BD26,"") | BJ26: Block exemption: defines a safe harbour ('the exemption shall not apply to...'), so few direct restrictions are counted; no consolidated text with amendments in EUR-Lex; consolidated count = original
A27: 26 | B27: Trade Secrets Directive | C27: Directive (EU) 2016/943 | D27: IPR | E27: enacted | F27: 2013-11-28 | G27: high | H27: 2016-06-08 | I27: 2016-06-15 | J27: 2016-07-05 | K27: adopted | L27: adopted | M27: 32016L0943 | N27: Original act as published in the OJ | O27: https://eur-lex.europa.eu/legal-content/EN/TXT/?uri=CELEX:32016L0943 | P27: 18 | Q27: 9919 | R27: 5447 | S27: 5326 | T27: 4472 | U27: 0 | V27: 0 | W27: 0 | X27: 60 | Y27: 38 | Z27: 5 | AA27: 0 | AB27: 1 | AC27: 16 | AD27: 4 | AE27: 38 | AF27: 4 | AG27: 14 | AH27: 02016L0943-20160615 | AI27: 60 | AJ27: 4 | AK27: =COUNTIFS(secondary_acts!$A$2:$A$771,$A27,secondary_acts!$E$2:$E$771,"implementing") -> 0 | AL27: =COUNTIFS(secondary_acts!$A$2:$A$771,$A27,secondary_acts!$E$2:$E$771,"delegated") -> 0 | AM27: =COUNTIFS(secondary_acts!$A$2:$A$771,$A27,secondary_acts!$E$2:$E$771,"other Commission/Council act") -> 0 | AN27: =COUNTIFS(secondary_acts!$A$2:$A$771,$A27,secondary_acts!$E$2:$E$771,"guidance") -> 0 | AO27: =COUNTIF(guidance_web!$A$2:$A$7,$A27) -> 0 | AP27: =COUNTIFS(guidance_agencies!$A$2:$A$81,$A27,guidance_agencies!$D$2:$D$81,"EDPB") -> 0 | AQ27: =COUNTIFS(guidance_agencies!$A$2:$A$81,$A27,guidance_agencies!$D$2:$D$81,"EBA") -> 0 | AR27: =COUNTIFS(guidance_agencies!$A$2:$A$81,$A27,guidance_agencies!$D$2:$D$81,"ESMA") -> 0 | AS27: =SUMIFS(secondary_acts!$S$2:$S$771,secondary_acts!$A$2:$A$771,$A27,secondary_acts!$E$2:$E$771,"implementing")+SUMIFS(secondary_acts!$S$2:$S$771,secondary_acts!$A$2:$A$771,$A27,secondary_acts!$E$2:$E$771,"delegated") -> 0 | AT27: 1446 | AU27: 28 | AV27: 0 | AY27: 1 | AZ27: 52013PC0813 | BA27: EUR-Lex HTML | BB27: 7646 | BC27: 53 | BD27: 1 | BE27: =IF(ISNUMBER(BB27),Q27-BB27,"") -> 2273 | BF27: =IF(AND(ISNUMBER(BB27),BB27>0),(Q27-BB27)/BB27,"") -> 0.29727962 | BG27: =IF(ISNUMBER(BC27),X27-BC27,"") -> 7 | BH27: =IF(AND(ISNUMBER(BC27),BC27>0),(X27-BC27)/BC27,"") -> 0.13207547 | BI27: =IF(ISNUMBER(BD27),AD27-BD27,"") -> 3 | BJ27: no consolidated text with amendments in EUR-Lex; consolidated count = original
A28: 27 | B28: Digital Content Directive | C28: Directive (EU) 2019/770 | D28: E-commerce & Consumer Protection | E28: enacted | F28: 2015-12-09 | G28: high | H28: 2019-05-20 | I28: 2019-05-22 | J28: 2019-06-11 | K28: adopted | L28: adopted | M28: 32019L0770 | N28: Original act as published in the OJ | O28: https://eur-lex.europa.eu/legal-content/EN/TXT/?uri=CELEX:32019L0770 | P28: 27 | Q28: 18391 | R28: 12610 | S28: 12493 | T28: 5781 | U28: 0 | V28: 0 | W28: 0 | X28: 51 | Y28: 41 | Z28: 4 | AA28: 0 | AB28: 1 | AC28: 5 | AD28: 21 | AE28: 12 | AF28: 1 | AG28: 17 | AH28: 02019L0770-20190522 | AI28: 51 | AJ28: 21 | AK28: =COUNTIFS(secondary_acts!$A$2:$A$771,$A28,secondary_acts!$E$2:$E$771,"implementing") -> 0 | AL28: =COUNTIFS(secondary_acts!$A$2:$A$771,$A28,secondary_acts!$E$2:$E$771,"delegated") -> 0 | AM28: =COUNTIFS(secondary_acts!$A$2:$A$771,$A28,secondary_acts!$E$2:$E$771,"other Commission/Council act") -> 0 | AN28: =COUNTIFS(secondary_acts!$A$2:$A$771,$A28,secondary_acts!$E$2:$E$771,"guidance") -> 0 | AO28: =COUNTIF(guidance_web!$A$2:$A$7,$A28) -> 0 | AP28: =COUNTIFS(guidance_agencies!$A$2:$A$81,$A28,guidance_agencies!$D$2:$D$81,"EDPB") -> 0 | AQ28: =COUNTIFS(guidance_agencies!$A$2:$A$81,$A28,guidance_agencies!$D$2:$D$81,"EBA") -> 0 | AR28: =COUNTIFS(guidance_agencies!$A$2:$A$81,$A28,guidance_agencies!$D$2:$D$81,"ESMA") -> 0 | AS28: =SUMIFS(secondary_acts!$S$2:$S$771,secondary_acts!$A$2:$A$771,$A28,secondary_acts!$E$2:$E$771,"implementing")+SUMIFS(secondary_acts!$S$2:$S$771,secondary_acts!$A$2:$A$771,$A28,secondary_acts!$E$2:$E$771,"delegated") -> 0 | AT28: 1331 | AU28: 27 | AV28: 0 | AY28: 4 | AZ28: 52015PC0634 | BA28: EUR-Lex HTML | BB28: 9777 | BC28: 50 | BD28: 21 | BE28: =IF(ISNUMBER(BB28),Q28-BB28,"") -> 8614 | BF28: =IF(AND(ISNUMBER(BB28),BB28>0),(Q28-BB28)/BB28,"") -> 0.88104736 | BG28: =IF(ISNUMBER(BC28),X28-BC28,"") -> 1 | BH28: =IF(AND(ISNUMBER(BC28),BC28>0),(X28-BC28)/BC28,"") -> 0.02 | BI28: =IF(ISNUMBER(BD28),AD28-BD28,"") -> 0 | BJ28: no consolidated text with amendments in EUR-Lex; consolidated count = original
A29: 28 | B29: Sale of Goods Directive | C29: Directive (EU) 2019/771 | D29: E-commerce & Consumer Protection | E29: enacted | F29: 2015-12-09 | G29: high | H29: 2019-05-20 | I29: 2019-05-22 | J29: 2019-06-11 | K29: adopted | L29: adopted | M29: 32019L0771 | N29: Original act as published in the OJ | O29: https://eur-lex.europa.eu/legal-content/EN/TXT/?uri=CELEX:32019L0771 | P29: 23 | Q29: 14331 | R29: 9215 | S29: 9086 | T29: 4770 | U29: 346 | V29: 0 | W29: 0 | X29: 42 | Y29: 31 | Z29: 4 | AA29: 1 | AB29: 1 | AC29: 5 | AD29: 11 | AE29: 12 | AF29: 1 | AG29: 18 | AH29: 02019L0771-20260731 | AI29: 44 | AJ29: 12 | AK29: =COUNTIFS(secondary_acts!$A$2:$A$771,$A29,secondary_acts!$E$2:$E$771,"implementing") -> 0 | AL29: =COUNTIFS(secondary_acts!$A$2:$A$771,$A29,secondary_acts!$E$2:$E$771,"delegated") -> 0 | AM29: =COUNTIFS(secondary_acts!$A$2:$A$771,$A29,secondary_acts!$E$2:$E$771,"other Commission/Council act") -> 0 | AN29: =COUNTIFS(secondary_acts!$A$2:$A$771,$A29,secondary_acts!$E$2:$E$771,"guidance") -> 0 | AO29: =COUNTIF(guidance_web!$A$2:$A$7,$A29) -> 0 | AP29: =COUNTIFS(guidance_agencies!$A$2:$A$81,$A29,guidance_agencies!$D$2:$D$81,"EDPB") -> 0 | AQ29: =COUNTIFS(guidance_agencies!$A$2:$A$81,$A29,guidance_agencies!$D$2:$D$81,"EBA") -> 0 | AR29: =COUNTIFS(guidance_agencies!$A$2:$A$81,$A29,guidance_agencies!$D$2:$D$81,"ESMA") -> 0 | AS29: =SUMIFS(secondary_acts!$S$2:$S$771,secondary_acts!$A$2:$A$771,$A29,secondary_acts!$E$2:$E$771,"implementing")+SUMIFS(secondary_acts!$S$2:$S$771,secondary_acts!$A$2:$A$771,$A29,secondary_acts!$E$2:$E$771,"delegated") -> 0 | AT29: 1291 | AU29: 27 | AV29: 1 | AW29: 2024-06-13 | AX29: 2024-06-13 | AY29: 3 | AZ29: 52015PC0635 | BA29: EUR-Lex HTML | BB29: 6775 | BC29: 30 | BD29: 13 | BE29: =IF(ISNUMBER(BB29),Q29-BB29,"") -> 7556 | BF29: =IF(AND(ISNUMBER(BB29),BB29>0),(Q29-BB29)/BB29,"") -> 1.1152768 | BG29: =IF(ISNUMBER(BC29),X29-BC29,"") -> 12 | BH29: =IF(AND(ISNUMBER(BC29),BC29>0),(X29-BC29)/BC29,"") -> 0.4 | BI29: =IF(ISNUMBER(BD29),AD29-BD29,"") -> -2
A30: 29 | B30: Company Law Directive | C30: Directive (EU) 2017/1132 | D30: Competition & Single Market | E30: enacted | F30: 2015-12-03 | G30: medium | H30: 2017-06-14 | I30: 2017-06-30 | J30: 2017-07-20 | K30: adopted | L30: adopted | M30: 32017L1132 | N30: Original act as published in the OJ | O30: https://eur-lex.europa.eu/legal-content/EN/TXT/?uri=CELEX:32017L1132 | P30: 82 | Q30: 39977 | R30: 5821 | S30: 5409 | T30: 32119 | U30: 2037 | V30: 0 | W30: 0 | X30: 436 | Y30: 314 | Z30: 78 | AA30: 16 | AB30: 8 | AC30: 20 | AD30: 116 | AE30: 132 | AF30: 22 | AG30: 166 | AH30: 02017L1132-20220812 | AI30: 777 | AJ30: 156 | AK30: =COUNTIFS(secondary_acts!$A$2:$A$771,$A30,secondary_acts!$E$2:$E$771,"implementing") -> 2 | AL30: =COUNTIFS(secondary_acts!$A$2:$A$771,$A30,secondary_acts!$E$2:$E$771,"delegated") -> 0 | AM30: =COUNTIFS(secondary_acts!$A$2:$A$771,$A30,secondary_acts!$E$2:$E$771,"other Commission/Council act") -> 0 | AN30: =COUNTIFS(secondary_acts!$A$2:$A$771,$A30,secondary_acts!$E$2:$E$771,"guidance") -> 0 | AO30: =COUNTIF(guidance_web!$A$2:$A$7,$A30) -> 0 | AP30: =COUNTIFS(guidance_agencies!$A$2:$A$81,$A30,guidance_agencies!$D$2:$D$81,"EDPB") -> 0 | AQ30: =COUNTIFS(guidance_agencies!$A$2:$A$81,$A30,guidance_agencies!$D$2:$D$81,"EBA") -> 0 | AR30: =COUNTIFS(guidance_agencies!$A$2:$A$81,$A30,guidance_agencies!$D$2:$D$81,"ESMA") -> 0 | AS30: =SUMIFS(secondary_acts!$S$2:$S$771,secondary_acts!$A$2:$A$771,$A30,secondary_acts!$E$2:$E$771,"implementing")+SUMIFS(secondary_acts!$S$2:$S$771,secondary_acts!$A$2:$A$771,$A30,secondary_acts!$E$2:$E$771,"delegated") -> 292 | AT30: 1440 | AU30: 10 | AV30: 6 | AW30: 2019-06-20 | AX30: 2024-12-19 | AY30: 3 | AZ30: 52015PC0616 | BA30: EUR-Lex HTML | BB30: 41520 | BC30: 471 | BD30: 123 | BE30: =IF(ISNUMBER(BB30),Q30-BB30,"") -> -1543 | BF30: =IF(AND(ISNUMBER(BB30),BB30>0),(Q30-BB30)/BB30,"") -> -0.037162813 | BG30: =IF(ISNUMBER(BC30),X30-BC30,"") -> -35 | BH30: =IF(AND(ISNUMBER(BC30),BC30>0),(X30-BC30)/BC30,"") -> -0.074309979 | BI30: =IF(ISNUMBER(BD30),AD30-BD30,"") -> -7
A31: 30 | B31: Geo-blocking Regulation | C31: Regulation (EU) 2018/302 | D31: E-commerce & Consumer Protection | E31: enacted | F31: 2016-05-25 | G31: high | H31: 2018-02-28 | I31: 2018-03-02 | J31: 2018-03-22 | K31: adopted | L31: adopted | M31: 32018R0302 | N31: Original act as published in the OJ | O31: https://eur-lex.europa.eu/legal-content/EN/TXT/?uri=CELEX:32018R0302 | P31: 15 | Q31: 8827 | R31: 6051 | S31: 5908 | T31: 2776 | U31: 0 | V31: 0 | W31: 0 | X31: 24 | Y31: 12 | Z31: 10 | AA31: 0 | AB31: 1 | AC31: 1 | AD31: 6 | AE31: 5 | AF31: 2 | AG31: 11 | AH31: 02018R0302-20180302 | AI31: 24 | AJ31: 6 | AK31: =COUNTIFS(secondary_acts!$A$2:$A$771,$A31,secondary_acts!$E$2:$E$771,"implementing") -> 0 | AL31: =COUNTIFS(secondary_acts!$A$2:$A$771,$A31,secondary_acts!$E$2:$E$771,"delegated") -> 0 | AM31: =COUNTIFS(secondary_acts!$A$2:$A$771,$A31,secondary_acts!$E$2:$E$771,"other Commission/Council act") -> 0 | AN31: =COUNTIFS(secondary_acts!$A$2:$A$771,$A31,secondary_acts!$E$2:$E$771,"guidance") -> 0 | AO31: =COUNTIF(guidance_web!$A$2:$A$7,$A31) -> 0 | AP31: =COUNTIFS(guidance_agencies!$A$2:$A$81,$A31,guidance_agencies!$D$2:$D$81,"EDPB") -> 0 | AQ31: =COUNTIFS(guidance_agencies!$A$2:$A$81,$A31,guidance_agencies!$D$2:$D$81,"EBA") -> 0 | AR31: =COUNTIFS(guidance_agencies!$A$2:$A$81,$A31,guidance_agencies!$D$2:$D$81,"ESMA") -> 0 | AS31: =SUMIFS(secondary_acts!$S$2:$S$771,secondary_acts!$A$2:$A$771,$A31,secondary_acts!$E$2:$E$771,"implementing")+SUMIFS(secondary_acts!$S$2:$S$771,secondary_acts!$A$2:$A$771,$A31,secondary_acts!$E$2:$E$771,"delegated") -> 0 | AV31: 0 | AY31: 3 | AZ31: 52016PC0289 | BA31: EUR-Lex HTML | BB31: 6093 | BC31: 21 | BD31: 5 | BE31: =IF(ISNUMBER(BB31),Q31-BB31,"") -> 2734 | BF31: =IF(AND(ISNUMBER(BB31),BB31>0),(Q31-BB31)/BB31,"") -> 0.44871164 | BG31: =IF(ISNUMBER(BC31),X31-BC31,"") -> 3 | BH31: =IF(AND(ISNUMBER(BC31),BC31>0),(X31-BC31)/BC31,"") -> 0.14285714 | BI31: =IF(ISNUMBER(BD31),AD31-BD31,"") -> 1 | BJ31: no consolidated text with amendments in EUR-Lex; consolidated count = original
A32: 31 | B32: Consumer Protection Cooperation Regulation | C32: Regulation (EU) 2017/2394 | D32: E-commerce & Consumer Protection | E32: enacted | F32: 2016-05-25 | G32: high | H32: 2017-12-12 | I32: 2017-12-27 | J32: 2018-01-16 | K32: adopted | L32: adopted | M32: 32017R2394 | N32: Original act as published in the OJ | O32: https://eur-lex.europa.eu/legal-content/EN/TXT/?uri=CELEX:32017R2394 | P32: 26 | Q32: 15509 | R32: 5040 | S32: 4917 | T32: 9233 | U32: 1236 | V32: 0 | W32: 0 | X32: 151 | Y32: 135 | Z32: 5 | AA32: 3 | AB32: 0 | AC32: 8 | AD32: 7 | AE32: 83 | AF32: 32 | AG32: 29 | AH32: 02017R2394-20260731 | AI32: 151 | AJ32: 7 | AK32: =COUNTIFS(secondary_acts!$A$2:$A$771,$A32,secondary_acts!$E$2:$E$771,"implementing") -> 1 | AL32: =COUNTIFS(secondary_acts!$A$2:$A$771,$A32,secondary_acts!$E$2:$E$771,"delegated") -> 0 | AM32: =COUNTIFS(secondary_acts!$A$2:$A$771,$A32,secondary_acts!$E$2:$E$771,"other Commission/Council act") -> 0 | AN32: =COUNTIFS(secondary_acts!$A$2:$A$771,$A32,secondary_acts!$E$2:$E$771,"guidance") -> 0 | AO32: =COUNTIF(guidance_web!$A$2:$A$7,$A32) -> 0 | AP32: =COUNTIFS(guidance_agencies!$A$2:$A$81,$A32,guidance_agencies!$D$2:$D$81,"EDPB") -> 0 | AQ32: =COUNTIFS(guidance_agencies!$A$2:$A$81,$A32,guidance_agencies!$D$2:$D$81,"EBA") -> 0 | AR32: =COUNTIFS(guidance_agencies!$A$2:$A$81,$A32,guidance_agencies!$D$2:$D$81,"ESMA") -> 0 | AS32: =SUMIFS(secondary_acts!$S$2:$S$771,secondary_acts!$A$2:$A$771,$A32,secondary_acts!$E$2:$E$771,"implementing")+SUMIFS(secondary_acts!$S$2:$S$771,secondary_acts!$A$2:$A$771,$A32,secondary_acts!$E$2:$E$771,"delegated") -> 4 | AV32: 6 | AW32: 2018-02-28 | AX32: 2024-12-19 | AY32: 0 | AZ32: 52016PC0283 | BA32: EUR-Lex HTML | BB32: 14223 | BC32: 179 | BD32: 6 | BE32: =IF(ISNUMBER(BB32),Q32-BB32,"") -> 1286 | BF32: =IF(AND(ISNUMBER(BB32),BB32>0),(Q32-BB32)/BB32,"") -> 0.09041693 | BG32: =IF(ISNUMBER(BC32),X32-BC32,"") -> -28 | BH32: =IF(AND(ISNUMBER(BC32),BC32>0),(X32-BC32)/BC32,"") -> -0.15642458 | BI32: =IF(ISNUMBER(BD32),AD32-BD32,"") -> 1
A33: 32 | B33: European Electronic Communications Code | C33: Directive (EU) 2018/1972 | D33: Connectivity | E33: enacted | F33: 2016-09-14 | G33: high | H33: 2018-12-11 | I33: 2018-12-17 | J33: 2018-12-20 | K33: adopted | L33: adopted | M33: 32018L1972 | N33: Original act as published in the OJ | O33: https://eur-lex.europa.eu/legal-content/EN/TXT/?uri=CELEX:32018L1972 | P33: 179 | Q33: 97406 | R33: 42601 | S33: 42479 | T33: 46896 | U33: 7909 | V33: 0 | W33: 0 | X33: 835 | Y33: 630 | Z33: 53 | AA33: 6 | AB33: 8 | AC33: 138 | AD33: 95 | AE33: 464 | AF33: 114 | AG33: 162 | AH33: 02018L1972-20241018 | AI33: 815 | AJ33: 89 | AK33: =COUNTIFS(secondary_acts!$A$2:$A$771,$A33,secondary_acts!$E$2:$E$771,"implementing") -> 7 | AL33: =COUNTIFS(secondary_acts!$A$2:$A$771,$A33,secondary_acts!$E$2:$E$771,"delegated") -> 2 | AM33: =COUNTIFS(secondary_acts!$A$2:$A$771,$A33,secondary_acts!$E$2:$E$771,"other Commission/Council act") -> 0 | AN33: =COUNTIFS(secondary_acts!$A$2:$A$771,$A33,secondary_acts!$E$2:$E$771,"guidance") -> 2 | AO33: =COUNTIF(guidance_web!$A$2:$A$7,$A33) -> 0 | AP33: =COUNTIFS(guidance_agencies!$A$2:$A$81,$A33,guidance_agencies!$D$2:$D$81,"EDPB") -> 0 | AQ33: =COUNTIFS(guidance_agencies!$A$2:$A$81,$A33,guidance_agencies!$D$2:$D$81,"EBA") -> 0 | AR33: =COUNTIFS(guidance_agencies!$A$2:$A$81,$A33,guidance_agencies!$D$2:$D$81,"ESMA") -> 0 | AS33: =SUMIFS(secondary_acts!$S$2:$S$771,secondary_acts!$A$2:$A$771,$A33,secondary_acts!$E$2:$E$771,"implementing")+SUMIFS(secondary_acts!$S$2:$S$771,secondary_acts!$A$2:$A$771,$A33,secondary_acts!$E$2:$E$771,"delegated") -> 135 | AT33: 3034 | AU33: 28 | AV33: 1 | AW33: 2022-12-14 | AX33: 2022-12-14 | AY33: 7 | AZ33: 52016PC0590 | BA33: EUR-Lex HTML | BB33: 109321 | BC33: 893 | BD33: 72 | BE33: =IF(ISNUMBER(BB33),Q33-BB33,"") -> -11915 | BF33: =IF(AND(ISNUMBER(BB33),BB33>0),(Q33-BB33)/BB33,"") -> -0.10899095 | BG33: =IF(ISNUMBER(BC33),X33-BC33,"") -> -58 | BH33: =IF(AND(ISNUMBER(BC33),BC33>0),(X33-BC33)/BC33,"") -> -0.064949608 | BI33: =IF(ISNUMBER(BD33),AD33-BD33,"") -> 23
A34: 33 | B34: Copyright in the Digital Single Market Directive | C34: Directive (EU) 2019/790 | D34: Media | E34: enacted | F34: 2016-09-14 | G34: high | H34: 2019-04-17 | I34: 2019-05-17 | J34: 2019-06-06 | K34: adopted | L34: adopted | M34: 32019L0790 | N34: Original act as published in the OJ | O34: https://eur-lex.europa.eu/legal-content/EN/TXT/?uri=CELEX:32019L0790 | P34: 34 | Q34: 22678 | R34: 15128 | S34: 14987 | T34: 7550 | U34: 0 | V34: 0 | W34: 0 | X34: 100 | Y34: 75 | Z34: 9 | AA34: 1 | AB34: 1 | AC34: 14 | AD34: 9 | AE34: 55 | AF34: 7 | AG34: 29 | AH34: 02019L0790-20190517 | AI34: 100 | AJ34: 9 | AK34: =COUNTIFS(secondary_acts!$A$2:$A$771,$A34,secondary_acts!$E$2:$E$771,"implementing") -> 0 | AL34: =COUNTIFS(secondary_acts!$A$2:$A$771,$A34,secondary_acts!$E$2:$E$771,"delegated") -> 0 | AM34: =COUNTIFS(secondary_acts!$A$2:$A$771,$A34,secondary_acts!$E$2:$E$771,"other Commission/Council act") -> 0 | AN34: =COUNTIFS(secondary_acts!$A$2:$A$771,$A34,secondary_acts!$E$2:$E$771,"guidance") -> 1 | AO34: =COUNTIF(guidance_web!$A$2:$A$7,$A34) -> 0 | AP34: =COUNTIFS(guidance_agencies!$A$2:$A$81,$A34,guidance_agencies!$D$2:$D$81,"EDPB") -> 0 | AQ34: =COUNTIFS(guidance_agencies!$A$2:$A$81,$A34,guidance_agencies!$D$2:$D$81,"EBA") -> 0 | AR34: =COUNTIFS(guidance_agencies!$A$2:$A$81,$A34,guidance_agencies!$D$2:$D$81,"ESMA") -> 0 | AS34: =SUMIFS(secondary_acts!$S$2:$S$771,secondary_acts!$A$2:$A$771,$A34,secondary_acts!$E$2:$E$771,"implementing")+SUMIFS(secondary_acts!$S$2:$S$771,secondary_acts!$A$2:$A$771,$A34,secondary_acts!$E$2:$E$771,"delegated") -> 0 | AT34: 1039 | AU34: 27 | AV34: 0 | AY34: 3 | AZ34: 52016PC0593 | BA34: EUR-Lex HTML | BB34: 8820 | BC34: 45 | BD34: 6 | BE34: =IF(ISNUMBER(BB34),Q34-BB34,"") -> 13858 | BF34: =IF(AND(ISNUMBER(BB34),BB34>0),(Q34-BB34)/BB34,"") -> 1.5712018 | BG34: =IF(ISNUMBER(BC34),X34-BC34,"") -> 55 | BH34: =IF(AND(ISNUMBER(BC34),BC34>0),(X34-BC34)/BC34,"") -> 1.2222222 | BI34: =IF(ISNUMBER(BD34),AD34-BD34,"") -> 3 | BJ34: no consolidated text with amendments in EUR-Lex; consolidated count = original
A35: 34 | B35: Satellite and Cable II Directive | C35: Directive (EU) 2019/789 | D35: Media | E35: enacted | F35: 2016-09-14 | G35: high | H35: 2019-04-17 | I35: 2019-05-17 | J35: 2019-06-06 | K35: adopted | L35: adopted | M35: 32019L0789 | N35: Original act as published in the OJ | O35: https://eur-lex.europa.eu/legal-content/EN/TXT/?uri=CELEX:32019L0789 | P35: 10 | Q35: 5980 | R35: 4056 | S35: 3909 | T35: 1924 | U35: 0 | V35: 0 | W35: 0 | X35: 23 | Y35: 17 | Z35: 1 | AA35: 0 | AB35: 0 | AC35: 5 | AD35: 1 | AE35: 16 | AF35: 1 | AG35: 5 | AH35: 02019L0789-20190517 | AI35: 23 | AJ35: 1 | AK35: =COUNTIFS(secondary_acts!$A$2:$A$771,$A35,secondary_acts!$E$2:$E$771,"implementing") -> 0 | AL35: =COUNTIFS(secondary_acts!$A$2:$A$771,$A35,secondary_acts!$E$2:$E$771,"delegated") -> 0 | AM35: =COUNTIFS(secondary_acts!$A$2:$A$771,$A35,secondary_acts!$E$2:$E$771,"other Commission/Council act") -> 0 | AN35: =COUNTIFS(secondary_acts!$A$2:$A$771,$A35,secondary_acts!$E$2:$E$771,"guidance") -> 0 | AO35: =COUNTIF(guidance_web!$A$2:$A$7,$A35) -> 0 | AP35: =COUNTIFS(guidance_agencies!$A$2:$A$81,$A35,guidance_agencies!$D$2:$D$81,"EDPB") -> 0 | AQ35: =COUNTIFS(guidance_agencies!$A$2:$A$81,$A35,guidance_agencies!$D$2:$D$81,"EBA") -> 0 | AR35: =COUNTIFS(guidance_agencies!$A$2:$A$81,$A35,guidance_agencies!$D$2:$D$81,"ESMA") -> 0 | AS35: =SUMIFS(secondary_acts!$S$2:$S$771,secondary_acts!$A$2:$A$771,$A35,secondary_acts!$E$2:$E$771,"implementing")+SUMIFS(secondary_acts!$S$2:$S$771,secondary_acts!$A$2:$A$771,$A35,secondary_acts!$E$2:$E$771,"delegated") -> 0 | AT35: 550 | AU35: 26 | AV35: 0 | AY35: 1 | AZ35: 52016PC0594 | BA35: EUR-Lex HTML | BB35: 3313 | BC35: 10 | BD35: 5 | BE35: =IF(ISNUMBER(BB35),Q35-BB35,"") -> 2667 | BF35: =IF(AND(ISNUMBER(BB35),BB35>0),(Q35-BB35)/BB35,"") -> 0.80501056 | BG35: =IF(ISNUMBER(BC35),X35-BC35,"") -> 13 | BH35: =IF(AND(ISNUMBER(BC35),BC35>0),(X35-BC35)/BC35,"") -> 1.3 | BI35: =IF(ISNUMBER(BD35),AD35-BD35,"") -> -4 | BJ35: no consolidated text with amendments in EUR-Lex; consolidated count = original
A36: 35 | B36: Data protection by EU institutions Regulation | C36: Regulation (EU) 2018/1725 | D36: Data & Privacy | E36: enacted | F36: 2017-01-10 | G36: high | H36: 2018-10-23 | I36: 2018-11-21 | J36: 2018-12-11 | K36: adopted | L36: adopted | M36: 32018R1725 | N36: Original act as published in the OJ | O36: https://eur-lex.europa.eu/legal-content/EN/TXT/?uri=CELEX:32018R1725 | P36: 60 | Q36: 37418 | R36: 12539 | S36: 12392 | T36: 24879 | U36: 0 | V36: 0 | W36: 0 | X36: 333 | Y36: 289 | Z36: 24 | AA36: 3 | AB36: 9 | AC36: 8 | AD36: 142 | AE36: 6 | AF36: 91 | AG36: 94 | AH36: 02018R1725-20181121 | AI36: 333 | AJ36: 142 | AK36: =COUNTIFS(secondary_acts!$A$2:$A$771,$A36,secondary_acts!$E$2:$E$771,"implementing") -> 2 | AL36: =COUNTIFS(secondary_acts!$A$2:$A$771,$A36,secondary_acts!$E$2:$E$771,"delegated") -> 0 | AM36: =COUNTIFS(secondary_acts!$A$2:$A$771,$A36,secondary_acts!$E$2:$E$771,"other Commission/Council act") -> 0 | AN36: =COUNTIFS(secondary_acts!$A$2:$A$771,$A36,secondary_acts!$E$2:$E$771,"guidance") -> 0 | AO36: =COUNTIF(guidance_web!$A$2:$A$7,$A36) -> 0 | AP36: =COUNTIFS(guidance_agencies!$A$2:$A$81,$A36,guidance_agencies!$D$2:$D$81,"EDPB") -> 0 | AQ36: =COUNTIFS(guidance_agencies!$A$2:$A$81,$A36,guidance_agencies!$D$2:$D$81,"EBA") -> 0 | AR36: =COUNTIFS(guidance_agencies!$A$2:$A$81,$A36,guidance_agencies!$D$2:$D$81,"ESMA") -> 0 | AS36: =SUMIFS(secondary_acts!$S$2:$S$771,secondary_acts!$A$2:$A$771,$A36,secondary_acts!$E$2:$E$771,"implementing")+SUMIFS(secondary_acts!$S$2:$S$771,secondary_acts!$A$2:$A$771,$A36,secondary_acts!$E$2:$E$771,"delegated") -> 115 | AV36: 0 | AY36: 3 | AZ36: 52017PC0008 | BA36: EUR-Lex HTML | BB36: 28900 | BC36: 232 | BD36: 80 | BE36: =IF(ISNUMBER(BB36),Q36-BB36,"") -> 8518 | BF36: =IF(AND(ISNUMBER(BB36),BB36>0),(Q36-BB36)/BB36,"") -> 0.29474048 | BG36: =IF(ISNUMBER(BC36),X36-BC36,"") -> 101 | BH36: =IF(AND(ISNUMBER(BC36),BC36>0),(X36-BC36)/BC36,"") -> 0.43534483 | BI36: =IF(ISNUMBER(BD36),AD36-BD36,"") -> 62 | BJ36: no consolidated text with amendments in EUR-Lex; consolidated count = original
A37: 36 | B37: Single Digital Gateway Regulation | C37: Regulation (EU) 2018/1724 | D37: Trust & Safety | E37: enacted | F37: 2017-05-02 | G37: high | H37: 2018-10-02 | I37: 2018-11-21 | J37: 2018-12-11 | K37: adopted | L37: adopted | M37: 32018R1724 | N37: Original act as published in the OJ | O37: https://eur-lex.europa.eu/legal-content/EN/TXT/?uri=CELEX:32018R1724 | P37: 38 | Q37: 20255 | R37: 9449 | S37: 9316 | T37: 8396 | U37: 2410 | V37: 0 | W37: 0 | X37: 138 | Y37: 110 | Z37: 4 | AA37: 3 | AB37: 5 | AC37: 16 | AD37: 6 | AE37: 39 | AF37: 67 | AG37: 26 | AH37: 02018R1724-20260520 | AI37: 135 | AJ37: 6 | AK37: =COUNTIFS(secondary_acts!$A$2:$A$771,$A37,secondary_acts!$E$2:$E$771,"implementing") -> 2 | AL37: =COUNTIFS(secondary_acts!$A$2:$A$771,$A37,secondary_acts!$E$2:$E$771,"delegated") -> 0 | AM37: =COUNTIFS(secondary_acts!$A$2:$A$771,$A37,secondary_acts!$E$2:$E$771,"other Commission/Council act") -> 0 | AN37: =COUNTIFS(secondary_acts!$A$2:$A$771,$A37,secondary_acts!$E$2:$E$771,"guidance") -> 4 | AO37: =COUNTIF(guidance_web!$A$2:$A$7,$A37) -> 0 | AP37: =COUNTIFS(guidance_agencies!$A$2:$A$81,$A37,guidance_agencies!$D$2:$D$81,"EDPB") -> 0 | AQ37: =COUNTIFS(guidance_agencies!$A$2:$A$81,$A37,guidance_agencies!$D$2:$D$81,"EBA") -> 0 | AR37: =COUNTIFS(guidance_agencies!$A$2:$A$81,$A37,guidance_agencies!$D$2:$D$81,"ESMA") -> 0 | AS37: =SUMIFS(secondary_acts!$S$2:$S$771,secondary_acts!$A$2:$A$771,$A37,secondary_acts!$E$2:$E$771,"implementing")+SUMIFS(secondary_acts!$S$2:$S$771,secondary_acts!$A$2:$A$771,$A37,secondary_acts!$E$2:$E$771,"delegated") -> 173 | AV37: 6 | AW37: 2022-05-30 | AX37: 2025-10-22 | AY37: 2 | AZ37: 52017PC0256 | BA37: EUR-Lex HTML | BB37: 12019 | BC37: 118 | BD37: 3 | BE37: =IF(ISNUMBER(BB37),Q37-BB37,"") -> 8236 | BF37: =IF(AND(ISNUMBER(BB37),BB37>0),(Q37-BB37)/BB37,"") -> 0.68524836 | BG37: =IF(ISNUMBER(BC37),X37-BC37,"") -> 20 | BH37: =IF(AND(ISNUMBER(BC37),BC37>0),(X37-BC37)/BC37,"") -> 0.16949153 | BI37: =IF(ISNUMBER(BD37),AD37-BD37,"") -> 3
A38: 37 | B38: Cybersecurity Act | C38: Regulation (EU) 2019/881 | D38: Cybersecurity | E38: enacted | F38: 2017-09-13 | G38: high | H38: 2019-04-17 | I38: 2019-06-07 | J38: 2019-06-27 | K38: adopted | L38: adopted | M38: 32019R0881 | N38: Original act as published in the OJ | O38: https://eur-lex.europa.eu/legal-content/EN/TXT/?uri=CELEX:32019R0881 | P38: 55 | Q38: 30460 | R38: 12254 | S38: 12114 | T38: 17006 | U38: 1200 | V38: 0 | W38: 0 | X38: 382 | Y38: 354 | Z38: 20 | AA38: 0 | AB38: 2 | AC38: 6 | AD38: 18 | AE38: 43 | AF38: 219 | AG38: 102 | AH38: 02019R0881-20250204 | AI38: 388 | AJ38: 15 | AK38: =COUNTIFS(secondary_acts!$A$2:$A$771,$A38,secondary_acts!$E$2:$E$771,"implementing") -> 5 | AL38: =COUNTIFS(secondary_acts!$A$2:$A$771,$A38,secondary_acts!$E$2:$E$771,"delegated") -> 0 | AM38: =COUNTIFS(secondary_acts!$A$2:$A$771,$A38,secondary_acts!$E$2:$E$771,"other Commission/Council act") -> 0 | AN38: =COUNTIFS(secondary_acts!$A$2:$A$771,$A38,secondary_acts!$E$2:$E$771,"guidance") -> 0 | AO38: =COUNTIF(guidance_web!$A$2:$A$7,$A38) -> 0 | AP38: =COUNTIFS(guidance_agencies!$A$2:$A$81,$A38,guidance_agencies!$D$2:$D$81,"EDPB") -> 0 | AQ38: =COUNTIFS(guidance_agencies!$A$2:$A$81,$A38,guidance_agencies!$D$2:$D$81,"EBA") -> 0 | AR38: =COUNTIFS(guidance_agencies!$A$2:$A$81,$A38,guidance_agencies!$D$2:$D$81,"ESMA") -> 0 | AS38: =SUMIFS(secondary_acts!$S$2:$S$771,secondary_acts!$A$2:$A$771,$A38,secondary_acts!$E$2:$E$771,"implementing")+SUMIFS(secondary_acts!$S$2:$S$771,secondary_acts!$A$2:$A$771,$A38,secondary_acts!$E$2:$E$771,"delegated") -> 383 | AV38: 1 | AW38: 2024-12-19 | AX38: 2024-12-19 | AY38: 7 | AZ38: 52017PC0477 | BA38: EUR-Lex HTML | BB38: 19728 | BC38: 262 | BD38: 19 | BE38: =IF(ISNUMBER(BB38),Q38-BB38,"") -> 10732 | BF38: =IF(AND(ISNUMBER(BB38),BB38>0),(Q38-BB38)/BB38,"") -> 0.54399838 | BG38: =IF(ISNUMBER(BC38),X38-BC38,"") -> 120 | BH38: =IF(AND(ISNUMBER(BC38),BC38>0),(X38-BC38)/BC38,"") -> 0.45801527 | BI38: =IF(ISNUMBER(BD38),AD38-BD38,"") -> -1
A39: 38 | B39: Free Flow of Non-Personal Data Regulation | C39: Regulation (EU) 2018/1807 | D39: Data & Privacy | E39: enacted | F39: 2017-09-13 | G39: high | H39: 2018-11-14 | I39: 2018-11-28 | J39: 2018-12-18 | K39: adopted | L39: adopted | M39: 32018R1807 | N39: Original act as published in the OJ | O39: https://eur-lex.europa.eu/legal-content/EN/TXT/?uri=CELEX:32018R1807 | P39: 10 | Q39: 6275 | R39: 4213 | S39: 4089 | T39: 2062 | U39: 0 | V39: 0 | W39: 0 | X39: 31 | Y39: 26 | Z39: 2 | AA39: 0 | AB39: 1 | AC39: 2 | AD39: 0 | AE39: 17 | AF39: 10 | AG39: 4 | AK39: =COUNTIFS(secondary_acts!$A$2:$A$771,$A39,secondary_acts!$E$2:$E$771,"implementing") -> 0 | AL39: =COUNTIFS(secondary_acts!$A$2:$A$771,$A39,secondary_acts!$E$2:$E$771,"delegated") -> 0 | AM39: =COUNTIFS(secondary_acts!$A$2:$A$771,$A39,secondary_acts!$E$2:$E$771,"other Commission/Council act") -> 0 | AN39: =COUNTIFS(secondary_acts!$A$2:$A$771,$A39,secondary_acts!$E$2:$E$771,"guidance") -> 1 | AO39: =COUNTIF(guidance_web!$A$2:$A$7,$A39) -> 0 | AP39: =COUNTIFS(guidance_agencies!$A$2:$A$81,$A39,guidance_agencies!$D$2:$D$81,"EDPB") -> 0 | AQ39: =COUNTIFS(guidance_agencies!$A$2:$A$81,$A39,guidance_agencies!$D$2:$D$81,"EBA") -> 0 | AR39: =COUNTIFS(guidance_agencies!$A$2:$A$81,$A39,guidance_agencies!$D$2:$D$81,"ESMA") -> 0 | AS39: =SUMIFS(secondary_acts!$S$2:$S$771,secondary_acts!$A$2:$A$771,$A39,secondary_acts!$E$2:$E$771,"implementing")+SUMIFS(secondary_acts!$S$2:$S$771,secondary_acts!$A$2:$A$771,$A39,secondary_acts!$E$2:$E$771,"delegated") -> 0 | AV39: 0 | AY39: 0 | AZ39: 52017PC0495 | BA39: EUR-Lex HTML | BB39: 4345 | BC39: 29 | BD39: 0 | BE39: =IF(ISNUMBER(BB39),Q39-BB39,"") -> 1930 | BF39: =IF(AND(ISNUMBER(BB39),BB39>0),(Q39-BB39)/BB39,"") -> 0.44418872 | BG39: =IF(ISNUMBER(BC39),X39-BC39,"") -> 2 | BH39: =IF(AND(ISNUMBER(BC39),BC39>0),(X39-BC39)/BC39,"") -> 0.068965517 | BI39: =IF(ISNUMBER(BD39),AD39-BD39,"") -> 0
A40: 39 | B40: FDI Screening Regulation | C40: Regulation (EU) 2019/452 | D40: Competition & Single Market | E40: enacted | F40: 2017-09-13 | G40: high | H40: 2019-03-19 | I40: 2019-03-21 | J40: 2019-04-10 | K40: adopted | L40: adopted | M40: 32019R0452 | N40: Original act as published in the OJ | O40: https://eur-lex.europa.eu/legal-content/EN/TXT/?uri=CELEX:32019R0452 | P40: 14 | Q40: 7814 | R40: 3363 | S40: 3238 | T40: 3948 | U40: 503 | V40: 0 | W40: 0 | X40: 70 | Y40: 67 | Z40: 0 | AA40: 0 | AB40: 0 | AC40: 3 | AD40: 5 | AE40: 24 | AF40: 25 | AG40: 16 | AH40: 02019R0452-20211223 | AI40: 70 | AJ40: 5 | AK40: =COUNTIFS(secondary_acts!$A$2:$A$771,$A40,secondary_acts!$E$2:$E$771,"implementing") -> 0 | AL40: =COUNTIFS(secondary_acts!$A$2:$A$771,$A40,secondary_acts!$E$2:$E$771,"delegated") -> 2 | AM40: =COUNTIFS(secondary_acts!$A$2:$A$771,$A40,secondary_acts!$E$2:$E$771,"other Commission/Council act") -> 0 | AN40: =COUNTIFS(secondary_acts!$A$2:$A$771,$A40,secondary_acts!$E$2:$E$771,"guidance") -> 1 | AO40: =COUNTIF(guidance_web!$A$2:$A$7,$A40) -> 0 | AP40: =COUNTIFS(guidance_agencies!$A$2:$A$81,$A40,guidance_agencies!$D$2:$D$81,"EDPB") -> 0 | AQ40: =COUNTIFS(guidance_agencies!$A$2:$A$81,$A40,guidance_agencies!$D$2:$D$81,"EBA") -> 0 | AR40: =COUNTIFS(guidance_agencies!$A$2:$A$81,$A40,guidance_agencies!$D$2:$D$81,"ESMA") -> 0 | AS40: =SUMIFS(secondary_acts!$S$2:$S$771,secondary_acts!$A$2:$A$771,$A40,secondary_acts!$E$2:$E$771,"implementing")+SUMIFS(secondary_acts!$S$2:$S$771,secondary_acts!$A$2:$A$771,$A40,secondary_acts!$E$2:$E$771,"delegated") -> 1 | AV40: 2 | AW40: 2020-07-13 | AX40: 2021-09-29 | AY40: 1 | AZ40: 52017PC0487 | BA40: EUR-Lex HTML | BB40: 4087 | BC40: 31 | BD40: 2 | BE40: =IF(ISNUMBER(BB40),Q40-BB40,"") -> 3727 | BF40: =IF(AND(ISNUMBER(BB40),BB40>0),(Q40-BB40)/BB40,"") -> 0.91191583 | BG40: =IF(ISNUMBER(BC40),X40-BC40,"") -> 39 | BH40: =IF(AND(ISNUMBER(BC40),BC40>0),(X40-BC40)/BC40,"") -> 1.2580645 | BI40: =IF(ISNUMBER(BD40),AD40-BD40,"") -> 3
A41: 40 | B41: Non-cash payment fraud Directive | C41: Directive (EU) 2019/713 | D41: Law Enforcement | E41: enacted | F41: 2017-09-13 | G41: high | H41: 2019-04-17 | I41: 2019-05-10 | J41: 2019-05-30 | K41: adopted | L41: adopted | M41: 32019L0713 | N41: Original act as published in the OJ | O41: https://eur-lex.europa.eu/legal-content/EN/TXT/?uri=CELEX:32019L0713 | P41: 12 | Q41: 6609 | R41: 3611 | S41: 3493 | T41: 2998 | U41: 0 | V41: 0 | W41: 0 | X41: 52 | Y41: 46 | Z41: 1 | AA41: 0 | AB41: 0 | AC41: 5 | AD41: 1 | AE41: 42 | AF41: 7 | AG41: 2 | AK41: =COUNTIFS(secondary_acts!$A$2:$A$771,$A41,secondary_acts!$E$2:$E$771,"implementing") -> 0 | AL41: =COUNTIFS(secondary_acts!$A$2:$A$771,$A41,secondary_acts!$E$2:$E$771,"delegated") -> 0 | AM41: =COUNTIFS(secondary_acts!$A$2:$A$771,$A41,secondary_acts!$E$2:$E$771,"other Commission/Council act") -> 0 | AN41: =COUNTIFS(secondary_acts!$A$2:$A$771,$A41,secondary_acts!$E$2:$E$771,"guidance") -> 0 | AO41: =COUNTIF(guidance_web!$A$2:$A$7,$A41) -> 0 | AP41: =COUNTIFS(guidance_agencies!$A$2:$A$81,$A41,guidance_agencies!$D$2:$D$81,"EDPB") -> 0 | AQ41: =COUNTIFS(guidance_agencies!$A$2:$A$81,$A41,guidance_agencies!$D$2:$D$81,"EBA") -> 0 | AR41: =COUNTIFS(guidance_agencies!$A$2:$A$81,$A41,guidance_agencies!$D$2:$D$81,"ESMA") -> 0 | AS41: =SUMIFS(secondary_acts!$S$2:$S$771,secondary_acts!$A$2:$A$771,$A41,secondary_acts!$E$2:$E$771,"implementing")+SUMIFS(secondary_acts!$S$2:$S$771,secondary_acts!$A$2:$A$771,$A41,secondary_acts!$E$2:$E$771,"delegated") -> 0 | AT41: 2301 | AU41: 25 | AV41: 0 | AY41: 0 | AZ41: 52017PC0489 | BA41: EUR-Lex HTML | BB41: 5501 | BC41: 45 | BD41: 2 | BE41: =IF(ISNUMBER(BB41),Q41-BB41,"") -> 1108 | BF41: =IF(AND(ISNUMBER(BB41),BB41>0),(Q41-BB41)/BB41,"") -> 0.20141792 | BG41: =IF(ISNUMBER(BC41),X41-BC41,"") -> 7 | BH41: =IF(AND(ISNUMBER(BC41),BC41>0),(X41-BC41)/BC41,"") -> 0.15555556 | BI41: =IF(ISNUMBER(BD41),AD41-BD41,"") -> -1
A42: 41 | B42: Market Surveillance Regulation | C42: Regulation (EU) 2019/1020 | D42: Competition & Single Market | E42: enacted | F42: 2017-12-19 | G42: high | H42: 2019-06-20 | I42: 2019-06-25 | J42: 2019-07-15 | K42: adopted | L42: adopted | M42: 32019R1020 | N42: Original act as published in the OJ | O42: https://eur-lex.europa.eu/legal-content/EN/TXT/?uri=CELEX:32019R1020 | P42: 44 | Q42: 24088 | R42: 6826 | S42: 6697 | T42: 12819 | U42: 4443 | V42: 0 | W42: 0 | X42: 198 | Y42: 179 | Z42: 6 | AA42: 3 | AB42: 3 | AC42: 7 | AD42: 15 | AE42: 81 | AF42: 45 | AG42: 57 | AH42: 02019R1020-20260812 | AI42: 198 | AJ42: 15 | AK42: =COUNTIFS(secondary_acts!$A$2:$A$771,$A42,secondary_acts!$E$2:$E$771,"implementing") -> 10 | AL42: =COUNTIFS(secondary_acts!$A$2:$A$771,$A42,secondary_acts!$E$2:$E$771,"delegated") -> 0 | AM42: =COUNTIFS(secondary_acts!$A$2:$A$771,$A42,secondary_acts!$E$2:$E$771,"other Commission/Council act") -> 0 | AN42: =COUNTIFS(secondary_acts!$A$2:$A$771,$A42,secondary_acts!$E$2:$E$771,"guidance") -> 1 | AO42: =COUNTIF(guidance_web!$A$2:$A$7,$A42) -> 0 | AP42: =COUNTIFS(guidance_agencies!$A$2:$A$81,$A42,guidance_agencies!$D$2:$D$81,"EDPB") -> 0 | AQ42: =COUNTIFS(guidance_agencies!$A$2:$A$81,$A42,guidance_agencies!$D$2:$D$81,"EBA") -> 0 | AR42: =COUNTIFS(guidance_agencies!$A$2:$A$81,$A42,guidance_agencies!$D$2:$D$81,"ESMA") -> 0 | AS42: =SUMIFS(secondary_acts!$S$2:$S$771,secondary_acts!$A$2:$A$771,$A42,secondary_acts!$E$2:$E$771,"implementing")+SUMIFS(secondary_acts!$S$2:$S$771,secondary_acts!$A$2:$A$771,$A42,secondary_acts!$E$2:$E$771,"delegated") -> 117 | AV42: 6 | AW42: 2023-07-12 | AX42: 2026-07-08 | AY42: 12 | AZ42: 52017PC0795 | BA42: EUR-Lex HTML | BB42: 19992 | BC42: 188 | BD42: 11 | BE42: =IF(ISNUMBER(BB42),Q42-BB42,"") -> 4096 | BF42: =IF(AND(ISNUMBER(BB42),BB42>0),(Q42-BB42)/BB42,"") -> 0.20488195 | BG42: =IF(ISNUMBER(BC42),X42-BC42,"") -> 10 | BH42: =IF(AND(ISNUMBER(BC42),BC42>0),(X42-BC42)/BC42,"") -> 0.053191489 | BI42: =IF(ISNUMBER(BD42),AD42-BD42,"") -> 4
A43: 42 | B43: E-evidence Regulation | C43: Regulation (EU) 2023/1543 | D43: Law Enforcement | E43: enacted | F43: 2018-04-17 | G43: high | H43: 2023-07-12 | I43: 2023-07-28 | J43: 2023-08-17 | K43: adopted | L43: adopted | M43: 32023R1543 | N43: Original act as published in the OJ | O43: https://eur-lex.europa.eu/legal-content/EN/TXT/?uri=CELEX:32023R1543 | P43: 63 | Q43: 31180 | R43: 12820 | S43: 12696 | T43: 11844 | U43: 6516 | V43: 0 | W43: 0 | X43: 208 | Y43: 178 | Z43: 7 | AA43: 12 | AB43: 3 | AC43: 8 | AD43: 13 | AE43: 90 | AF43: 24 | AG43: 81 | AH43: 02023R1543-20230728 | AI43: 208 | AJ43: 14 | AK43: =COUNTIFS(secondary_acts!$A$2:$A$771,$A43,secondary_acts!$E$2:$E$771,"implementing") -> 1 | AL43: =COUNTIFS(secondary_acts!$A$2:$A$771,$A43,secondary_acts!$E$2:$E$771,"delegated") -> 0 | AM43: =COUNTIFS(secondary_acts!$A$2:$A$771,$A43,secondary_acts!$E$2:$E$771,"other Commission/Council act") -> 0 | AN43: =COUNTIFS(secondary_acts!$A$2:$A$771,$A43,secondary_acts!$E$2:$E$771,"guidance") -> 0 | AO43: =COUNTIF(guidance_web!$A$2:$A$7,$A43) -> 0 | AP43: =COUNTIFS(guidance_agencies!$A$2:$A$81,$A43,guidance_agencies!$D$2:$D$81,"EDPB") -> 0 | AQ43: =COUNTIFS(guidance_agencies!$A$2:$A$81,$A43,guidance_agencies!$D$2:$D$81,"EBA") -> 0 | AR43: =COUNTIFS(guidance_agencies!$A$2:$A$81,$A43,guidance_agencies!$D$2:$D$81,"ESMA") -> 0 | AS43: =SUMIFS(secondary_acts!$S$2:$S$771,secondary_acts!$A$2:$A$771,$A43,secondary_acts!$E$2:$E$771,"implementing")+SUMIFS(secondary_acts!$S$2:$S$771,secondary_acts!$A$2:$A$771,$A43,secondary_acts!$E$2:$E$771,"delegated") -> 59 | AV43: 0 | AY43: 2 | AZ43: 52018PC0225 | BA43: EUR-Lex HTML | BB43: 16549 | BC43: 137 | BD43: 4 | BE43: =IF(ISNUMBER(BB43),Q43-BB43,"") -> 14631 | BF43: =IF(AND(ISNUMBER(BB43),BB43>0),(Q43-BB43)/BB43,"") -> 0.88410176 | BG43: =IF(ISNUMBER(BC43),X43-BC43,"") -> 71 | BH43: =IF(AND(ISNUMBER(BC43),BC43>0),(X43-BC43)/BC43,"") -> 0.51824818 | BI43: =IF(ISNUMBER(BD43),AD43-BD43,"") -> 9
A44: 43 | B44: Open Data Directive (PSI) | C44: Directive (EU) 2019/1024 | D44: Data & Privacy | E44: enacted | F44: 2018-04-25 | G44: high | H44: 2019-06-20 | I44: 2019-06-26 | J44: 2019-07-16 | K44: adopted | L44: adopted | M44: 32019L1024 | N44: Original act as published in the OJ | O44: https://eur-lex.europa.eu/legal-content/EN/TXT/?uri=CELEX:32019L1024 | P44: 28 | Q44: 14648 | R44: 8645 | S44: 8528 | T44: 5395 | U44: 608 | V44: 0 | W44: 0 | X44: 98 | Y44: 79 | Z44: 11 | AA44: 0 | AB44: 4 | AC44: 4 | AD44: 8 | AE44: 39 | AF44: 11 | AG44: 40 | AK44: =COUNTIFS(secondary_acts!$A$2:$A$771,$A44,secondary_acts!$E$2:$E$771,"implementing") -> 1 | AL44: =COUNTIFS(secondary_acts!$A$2:$A$771,$A44,secondary_acts!$E$2:$E$771,"delegated") -> 0 | AM44: =COUNTIFS(secondary_acts!$A$2:$A$771,$A44,secondary_acts!$E$2:$E$771,"other Commission/Council act") -> 0 | AN44: =COUNTIFS(secondary_acts!$A$2:$A$771,$A44,secondary_acts!$E$2:$E$771,"guidance") -> 0 | AO44: =COUNTIF(guidance_web!$A$2:$A$7,$A44) -> 0 | AP44: =COUNTIFS(guidance_agencies!$A$2:$A$81,$A44,guidance_agencies!$D$2:$D$81,"EDPB") -> 0 | AQ44: =COUNTIFS(guidance_agencies!$A$2:$A$81,$A44,guidance_agencies!$D$2:$D$81,"EBA") -> 0 | AR44: =COUNTIFS(guidance_agencies!$A$2:$A$81,$A44,guidance_agencies!$D$2:$D$81,"ESMA") -> 0 | AS44: =SUMIFS(secondary_acts!$S$2:$S$771,secondary_acts!$A$2:$A$771,$A44,secondary_acts!$E$2:$E$771,"implementing")+SUMIFS(secondary_acts!$S$2:$S$771,secondary_acts!$A$2:$A$771,$A44,secondary_acts!$E$2:$E$771,"delegated") -> 59 | AT44: 1064 | AU44: 27 | AV44: 0 | AY44: 0 | AZ44: 52018PC0234 | BA44: EUR-Lex HTML | BB44: 13415 | BC44: 93 | BD44: 7 | BE44: =IF(ISNUMBER(BB44),Q44-BB44,"") -> 1233 | BF44: =IF(AND(ISNUMBER(BB44),BB44>0),(Q44-BB44)/BB44,"") -> 0.091912039 | BG44: =IF(ISNUMBER(BC44),X44-BC44,"") -> 5 | BH44: =IF(AND(ISNUMBER(BC44),BC44>0),(X44-BC44)/BC44,"") -> 0.053763441 | BI44: =IF(ISNUMBER(BD44),AD44-BD44,"") -> 1
A45: 44 | B45: Platform-to-Business (P2B) Regulation | C45: Regulation (EU) 2019/1150 | D45: Competition & Single Market | E45: enacted | F45: 2018-04-26 | G45: high | H45: 2019-06-20 | I45: 2019-07-11 | J45: 2019-07-31 | K45: adopted | L45: adopted | M45: 32019R1150 | N45: Original act as published in the OJ | O45: https://eur-lex.europa.eu/legal-content/EN/TXT/?uri=CELEX:32019R1150 | P45: 23 | Q45: 14939 | R45: 8985 | S45: 8863 | T45: 5954 | U45: 0 | V45: 0 | W45: 0 | X45: 78 | Y45: 70 | Z45: 1 | AA45: 1 | AB45: 1 | AC45: 5 | AD45: 40 | AE45: 8 | AF45: 13 | AG45: 17 | AH45: 02019R1150-20190711 | AI45: 78 | AJ45: 40 | AK45: =COUNTIFS(secondary_acts!$A$2:$A$771,$A45,secondary_acts!$E$2:$E$771,"implementing") -> 0 | AL45: =COUNTIFS(secondary_acts!$A$2:$A$771,$A45,secondary_acts!$E$2:$E$771,"delegated") -> 0 | AM45: =COUNTIFS(secondary_acts!$A$2:$A$771,$A45,secondary_acts!$E$2:$E$771,"other Commission/Council act") -> 0 | AN45: =COUNTIFS(secondary_acts!$A$2:$A$771,$A45,secondary_acts!$E$2:$E$771,"guidance") -> 1 | AO45: =COUNTIF(guidance_web!$A$2:$A$7,$A45) -> 0 | AP45: =COUNTIFS(guidance_agencies!$A$2:$A$81,$A45,guidance_agencies!$D$2:$D$81,"EDPB") -> 0 | AQ45: =COUNTIFS(guidance_agencies!$A$2:$A$81,$A45,guidance_agencies!$D$2:$D$81,"EBA") -> 0 | AR45: =COUNTIFS(guidance_agencies!$A$2:$A$81,$A45,guidance_agencies!$D$2:$D$81,"ESMA") -> 0 | AS45: =SUMIFS(secondary_acts!$S$2:$S$771,secondary_acts!$A$2:$A$771,$A45,secondary_acts!$E$2:$E$771,"implementing")+SUMIFS(secondary_acts!$S$2:$S$771,secondary_acts!$A$2:$A$771,$A45,secondary_acts!$E$2:$E$771,"delegated") -> 0 | AV45: 0 | AY45: 2 | AZ45: 52018PC0238 | BA45: EUR-Lex HTML | BB45: 7530 | BC45: 42 | BD45: 23 | BE45: =IF(ISNUMBER(BB45),Q45-BB45,"") -> 7409 | BF45: =IF(AND(ISNUMBER(BB45),BB45>0),(Q45-BB45)/BB45,"") -> 0.98393094 | BG45: =IF(ISNUMBER(BC45),X45-BC45,"") -> 36 | BH45: =IF(AND(ISNUMBER(BC45),BC45>0),(X45-BC45)/BC45,"") -> 0.85714286 | BI45: =IF(ISNUMBER(BD45),AD45-BD45,"") -> 17 | BJ45: no consolidated text with amendments in EUR-Lex; consolidated count = original
A46: 45 | B46: Digital Europe Programme | C46: Regulation (EU) 2021/694 | D46: Research & Innovation | E46: enacted | F46: 2018-06-06 | G46: high | H46: 2021-04-29 | I46: 2021-05-11 | J46: 2021-05-12 | K46: adopted | L46: adopted | M46: 32021R0694 | N46: Original act as published in the OJ | O46: https://eur-lex.europa.eu/legal-content/EN/TXT/?uri=CELEX:32021R0694 | P46: 34 | Q46: 17444 | R46: 6687 | S46: 6557 | T46: 7371 | U46: 3386 | V46: 0 | W46: 0 | X46: 132 | Y46: 115 | Z46: 3 | AA46: 1 | AB46: 1 | AC46: 12 | AD46: 8 | AE46: 2 | AF46: 45 | AG46: 77 | AH46: 02021R0694-20251223 | AI46: 143 | AJ46: 8 | AK46: =COUNTIFS(secondary_acts!$A$2:$A$771,$A46,secondary_acts!$E$2:$E$771,"implementing") -> 1 | AL46: =COUNTIFS(secondary_acts!$A$2:$A$771,$A46,secondary_acts!$E$2:$E$771,"delegated") -> 0 | AM46: =COUNTIFS(secondary_acts!$A$2:$A$771,$A46,secondary_acts!$E$2:$E$771,"other Commission/Council act") -> 0 | AN46: =COUNTIFS(secondary_acts!$A$2:$A$771,$A46,secondary_acts!$E$2:$E$771,"guidance") -> 0 | AO46: =COUNTIF(guidance_web!$A$2:$A$7,$A46) -> 0 | AP46: =COUNTIFS(guidance_agencies!$A$2:$A$81,$A46,guidance_agencies!$D$2:$D$81,"EDPB") -> 0 | AQ46: =COUNTIFS(guidance_agencies!$A$2:$A$81,$A46,guidance_agencies!$D$2:$D$81,"EBA") -> 0 | AR46: =COUNTIFS(guidance_agencies!$A$2:$A$81,$A46,guidance_agencies!$D$2:$D$81,"ESMA") -> 0 | AS46: =SUMIFS(secondary_acts!$S$2:$S$771,secondary_acts!$A$2:$A$771,$A46,secondary_acts!$E$2:$E$771,"implementing")+SUMIFS(secondary_acts!$S$2:$S$771,secondary_acts!$A$2:$A$771,$A46,secondary_acts!$E$2:$E$771,"delegated") -> 0 | AV46: 3 | AW46: 2023-09-13 | AX46: 2025-12-19 | AY46: 1 | AZ46: 52018PC0434 | BA46: EUR-Lex HTML | BB46: 11557 | BC46: 81 | BD46: 2 | BE46: =IF(ISNUMBER(BB46),Q46-BB46,"") -> 5887 | BF46: =IF(AND(ISNUMBER(BB46),BB46>0),(Q46-BB46)/BB46,"") -> 0.50938825 | BG46: =IF(ISNUMBER(BC46),X46-BC46,"") -> 51 | BH46: =IF(AND(ISNUMBER(BC46),BC46>0),(X46-BC46)/BC46,"") -> 0.62962963 | BI46: =IF(ISNUMBER(BD46),AD46-BD46,"") -> 6
A47: 46 | B47: InvestEU Programme | C47: Regulation (EU) 2021/523 | D47: Industrial Policy | E47: enacted | F47: 2018-06-06 | G47: high | H47: 2021-03-24 | I47: 2021-03-26 | J47: 2021-03-26 | K47: adopted | L47: adopted | M47: 32021R0523 | N47: Original act as published in the OJ | O47: https://eur-lex.europa.eu/legal-content/EN/TXT/?uri=CELEX:32021R0523 | P47: 60 | Q47: 32522 | R47: 9593 | S47: 9470 | T47: 16804 | U47: 6125 | V47: 0 | W47: 0 | X47: 262 | Y47: 247 | Z47: 6 | AA47: 3 | AB47: 0 | AC47: 6 | AD47: 18 | AE47: 9 | AF47: 101 | AG47: 134 | AH47: 02021R0523-20251224 | AI47: 285 | AJ47: 21 | AK47: =COUNTIFS(secondary_acts!$A$2:$A$771,$A47,secondary_acts!$E$2:$E$771,"implementing") -> 2 | AL47: =COUNTIFS(secondary_acts!$A$2:$A$771,$A47,secondary_acts!$E$2:$E$771,"delegated") -> 3 | AM47: =COUNTIFS(secondary_acts!$A$2:$A$771,$A47,secondary_acts!$E$2:$E$771,"other Commission/Council act") -> 0 | AN47: =COUNTIFS(secondary_acts!$A$2:$A$771,$A47,secondary_acts!$E$2:$E$771,"guidance") -> 2 | AO47: =COUNTIF(guidance_web!$A$2:$A$7,$A47) -> 0 | AP47: =COUNTIFS(guidance_agencies!$A$2:$A$81,$A47,guidance_agencies!$D$2:$D$81,"EDPB") -> 0 | AQ47: =COUNTIFS(guidance_agencies!$A$2:$A$81,$A47,guidance_agencies!$D$2:$D$81,"EBA") -> 0 | AR47: =COUNTIFS(guidance_agencies!$A$2:$A$81,$A47,guidance_agencies!$D$2:$D$81,"ESMA") -> 0 | AS47: =SUMIFS(secondary_acts!$S$2:$S$771,secondary_acts!$A$2:$A$771,$A47,secondary_acts!$E$2:$E$771,"implementing")+SUMIFS(secondary_acts!$S$2:$S$771,secondary_acts!$A$2:$A$771,$A47,secondary_acts!$E$2:$E$771,"delegated") -> 300 | AV47: 3 | AW47: 2024-02-29 | AX47: 2025-12-16 | AY47: 2 | AZ47: 52020PC0403 | BA47: EUR-Lex HTML | BB47: 30916 | BC47: 277 | BD47: 23 | BE47: =IF(ISNUMBER(BB47),Q47-BB47,"") -> 1606 | BF47: =IF(AND(ISNUMBER(BB47),BB47>0),(Q47-BB47)/BB47,"") -> 0.051947212 | BG47: =IF(ISNUMBER(BC47),X47-BC47,"") -> -15 | BH47: =IF(AND(ISNUMBER(BC47),BC47>0),(X47-BC47)/BC47,"") -> -0.054151625 | BI47: =IF(ISNUMBER(BD47),AD47-BD47,"") -> -5
A48: 47 | B48: Connecting Europe Facility | C48: Regulation (EU) 2021/1153 | D48: Industrial Policy | E48: enacted | F48: 2018-06-06 | G48: high | H48: 2021-07-07 | I48: 2021-07-14 | J48: 2021-07-14 | K48: adopted | L48: adopted | M48: 32021R1153 | N48: Original act as published in the OJ | O48: https://eur-lex.europa.eu/legal-content/EN/TXT/?uri=CELEX:32021R1153 | P48: 44 | Q48: 21097 | R48: 7484 | S48: 7350 | T48: 9591 | U48: 4022 | V48: 0 | W48: 0 | X48: 138 | Y48: 117 | Z48: 16 | AA48: 2 | AB48: 1 | AC48: 2 | AD48: 11 | AE48: 6 | AF48: 37 | AG48: 84 | AH48: 02021R1153-20251224 | AI48: 141 | AJ48: 11 | AK48: =COUNTIFS(secondary_acts!$A$2:$A$771,$A48,secondary_acts!$E$2:$E$771,"implementing") -> 1 | AL48: =COUNTIFS(secondary_acts!$A$2:$A$771,$A48,secondary_acts!$E$2:$E$771,"delegated") -> 6 | AM48: =COUNTIFS(secondary_acts!$A$2:$A$771,$A48,secondary_acts!$E$2:$E$771,"other Commission/Council act") -> 0 | AN48: =COUNTIFS(secondary_acts!$A$2:$A$771,$A48,secondary_acts!$E$2:$E$771,"guidance") -> 1 | AO48: =COUNTIF(guidance_web!$A$2:$A$7,$A48) -> 0 | AP48: =COUNTIFS(guidance_agencies!$A$2:$A$81,$A48,guidance_agencies!$D$2:$D$81,"EDPB") -> 0 | AQ48: =COUNTIFS(guidance_agencies!$A$2:$A$81,$A48,guidance_agencies!$D$2:$D$81,"EBA") -> 0 | AR48: =COUNTIFS(guidance_agencies!$A$2:$A$81,$A48,guidance_agencies!$D$2:$D$81,"ESMA") -> 0 | AS48: =SUMIFS(secondary_acts!$S$2:$S$771,secondary_acts!$A$2:$A$771,$A48,secondary_acts!$E$2:$E$771,"implementing")+SUMIFS(secondary_acts!$S$2:$S$771,secondary_acts!$A$2:$A$771,$A48,secondary_acts!$E$2:$E$771,"delegated") -> 53 | AV48: 3 | AW48: 2024-06-13 | AX48: 2025-12-19 | AY48: 2 | AZ48: 52018PC0438 | BA48: EUR-Lex HTML | BB48: 14679 | BC48: 91 | BD48: 6 | BE48: =IF(ISNUMBER(BB48),Q48-BB48,"") -> 6418 | BF48: =IF(AND(ISNUMBER(BB48),BB48>0),(Q48-BB48)/BB48,"") -> 0.43722324 | BG48: =IF(ISNUMBER(BC48),X48-BC48,"") -> 47 | BH48: =IF(AND(ISNUMBER(BC48),BC48>0),(X48-BC48)/BC48,"") -> 0.51648352 | BI48: =IF(ISNUMBER(BD48),AD48-BD48,"") -> 5
A49: 48 | B49: Horizon Europe | C49: Regulation (EU) 2021/695 | D49: Research & Innovation | E49: enacted | F49: 2018-06-07 | G49: high | H49: 2021-04-28 | I49: 2021-05-12 | J49: 2021-05-12 | K49: adopted | L49: adopted | M49: 32021R0695 | N49: Original act as published in the OJ | O49: https://eur-lex.europa.eu/legal-content/EN/TXT/?uri=CELEX:32021R0695 | P49: 68 | Q49: 35488 | R49: 8462 | S49: 8304 | T49: 18587 | U49: 8439 | V49: 0 | W49: 0 | X49: 365 | Y49: 304 | Z49: 17 | AA49: 1 | AB49: 4 | AC49: 39 | AD49: 52 | AE49: 6 | AF49: 66 | AG49: 241 | AH49: 02021R0695-20251224 | AI49: 372 | AJ49: 55 | AK49: =COUNTIFS(secondary_acts!$A$2:$A$771,$A49,secondary_acts!$E$2:$E$771,"implementing") -> 0 | AL49: =COUNTIFS(secondary_acts!$A$2:$A$771,$A49,secondary_acts!$E$2:$E$771,"delegated") -> 0 | AM49: =COUNTIFS(secondary_acts!$A$2:$A$771,$A49,secondary_acts!$E$2:$E$771,"other Commission/Council act") -> 0 | AN49: =COUNTIFS(secondary_acts!$A$2:$A$771,$A49,secondary_acts!$E$2:$E$771,"guidance") -> 0 | AO49: =COUNTIF(guidance_web!$A$2:$A$7,$A49) -> 0 | AP49: =COUNTIFS(guidance_agencies!$A$2:$A$81,$A49,guidance_agencies!$D$2:$D$81,"EDPB") -> 0 | AQ49: =COUNTIFS(guidance_agencies!$A$2:$A$81,$A49,guidance_agencies!$D$2:$D$81,"EBA") -> 0 | AR49: =COUNTIFS(guidance_agencies!$A$2:$A$81,$A49,guidance_agencies!$D$2:$D$81,"ESMA") -> 0 | AS49: =SUMIFS(secondary_acts!$S$2:$S$771,secondary_acts!$A$2:$A$771,$A49,secondary_acts!$E$2:$E$771,"implementing")+SUMIFS(secondary_acts!$S$2:$S$771,secondary_acts!$A$2:$A$771,$A49,secondary_acts!$E$2:$E$771,"delegated") -> 0 | AV49: 3 | AW49: 2024-02-29 | AX49: 2025-12-19 | AY49: 5 | AZ49: 52018PC0435 | BA49: EUR-Lex HTML | BB49: 22209 | BC49: 185 | BD49: 40 | BE49: =IF(ISNUMBER(BB49),Q49-BB49,"") -> 13279 | BF49: =IF(AND(ISNUMBER(BB49),BB49>0),(Q49-BB49)/BB49,"") -> 0.59791076 | BG49: =IF(ISNUMBER(BC49),X49-BC49,"") -> 180 | BH49: =IF(AND(ISNUMBER(BC49),BC49>0),(X49-BC49)/BC49,"") -> 0.97297297 | BI49: =IF(ISNUMBER(BD49),AD49-BD49,"") -> 12
A50: 49 | B50: Single Market Programme | C50: Regulation (EU) 2021/690 | D50: Competition & Single Market | E50: enacted | F50: 2018-06-07 | G50: high | H50: 2021-04-28 | I50: 2021-05-03 | J50: 2021-05-03 | K50: adopted | L50: adopted | M50: 32021R0690 | N50: Original act as published in the OJ | O50: https://eur-lex.europa.eu/legal-content/EN/TXT/?uri=CELEX:32021R0690 | P50: 47 | Q50: 25687 | R50: 12659 | S50: 12483 | T50: 8347 | U50: 4681 | V50: 0 | W50: 0 | X50: 78 | Y50: 74 | Z50: 3 | AA50: 0 | AB50: 0 | AC50: 1 | AD50: 2 | AE50: 3 | AF50: 32 | AG50: 41 | AH50: 02021R0690-20210503 | AI50: 78 | AJ50: 2 | AK50: =COUNTIFS(secondary_acts!$A$2:$A$771,$A50,secondary_acts!$E$2:$E$771,"implementing") -> 0 | AL50: =COUNTIFS(secondary_acts!$A$2:$A$771,$A50,secondary_acts!$E$2:$E$771,"delegated") -> 1 | AM50: =COUNTIFS(secondary_acts!$A$2:$A$771,$A50,secondary_acts!$E$2:$E$771,"other Commission/Council act") -> 0 | AN50: =COUNTIFS(secondary_acts!$A$2:$A$771,$A50,secondary_acts!$E$2:$E$771,"guidance") -> 0 | AO50: =COUNTIF(guidance_web!$A$2:$A$7,$A50) -> 0 | AP50: =COUNTIFS(guidance_agencies!$A$2:$A$81,$A50,guidance_agencies!$D$2:$D$81,"EDPB") -> 0 | AQ50: =COUNTIFS(guidance_agencies!$A$2:$A$81,$A50,guidance_agencies!$D$2:$D$81,"EBA") -> 0 | AR50: =COUNTIFS(guidance_agencies!$A$2:$A$81,$A50,guidance_agencies!$D$2:$D$81,"ESMA") -> 0 | AS50: =SUMIFS(secondary_acts!$S$2:$S$771,secondary_acts!$A$2:$A$771,$A50,secondary_acts!$E$2:$E$771,"implementing")+SUMIFS(secondary_acts!$S$2:$S$771,secondary_acts!$A$2:$A$771,$A50,secondary_acts!$E$2:$E$771,"delegated") -> 7 | AV50: 0 | AY50: 3 | AZ50: 52018PC0441 | BA50: EUR-Lex HTML | BB50: 17461 | BC50: 43 | BD50: 1 | BE50: =IF(ISNUMBER(BB50),Q50-BB50,"") -> 8226 | BF50: =IF(AND(ISNUMBER(BB50),BB50>0),(Q50-BB50)/BB50,"") -> 0.47110704 | BG50: =IF(ISNUMBER(BC50),X50-BC50,"") -> 35 | BH50: =IF(AND(ISNUMBER(BC50),BC50>0),(X50-BC50)/BC50,"") -> 0.81395349 | BI50: =IF(ISNUMBER(BD50),AD50-BD50,"") -> 1 | BJ50: no consolidated text with amendments in EUR-Lex; consolidated count = original
A51: 50 | B51: European Cybersecurity Competence Centre | C51: Regulation (EU) 2021/887 | D51: Cybersecurity | E51: enacted | F51: 2018-09-12 | G51: high | H51: 2021-05-20 | I51: 2021-06-08 | J51: 2021-06-28 | K51: adopted | L51: adopted | M51: 32021R0887 | N51: Original act as published in the OJ | O51: https://eur-lex.europa.eu/legal-content/EN/TXT/?uri=CELEX:32021R0887 | P51: 31 | Q51: 18406 | R51: 4968 | S51: 4844 | T51: 13438 | U51: 0 | V51: 0 | W51: 0 | X51: 241 | Y51: 227 | Z51: 7 | AA51: 0 | AB51: 0 | AC51: 7 | AD51: 6 | AE51: 32 | AF51: 102 | AG51: 101 | AK51: =COUNTIFS(secondary_acts!$A$2:$A$771,$A51,secondary_acts!$E$2:$E$771,"implementing") -> 0 | AL51: =COUNTIFS(secondary_acts!$A$2:$A$771,$A51,secondary_acts!$E$2:$E$771,"delegated") -> 0 | AM51: =COUNTIFS(secondary_acts!$A$2:$A$771,$A51,secondary_acts!$E$2:$E$771,"other Commission/Council act") -> 0 | AN51: =COUNTIFS(secondary_acts!$A$2:$A$771,$A51,secondary_acts!$E$2:$E$771,"guidance") -> 0 | AO51: =COUNTIF(guidance_web!$A$2:$A$7,$A51) -> 0 | AP51: =COUNTIFS(guidance_agencies!$A$2:$A$81,$A51,guidance_agencies!$D$2:$D$81,"EDPB") -> 0 | AQ51: =COUNTIFS(guidance_agencies!$A$2:$A$81,$A51,guidance_agencies!$D$2:$D$81,"EBA") -> 0 | AR51: =COUNTIFS(guidance_agencies!$A$2:$A$81,$A51,guidance_agencies!$D$2:$D$81,"ESMA") -> 0 | AS51: =SUMIFS(secondary_acts!$S$2:$S$771,secondary_acts!$A$2:$A$771,$A51,secondary_acts!$E$2:$E$771,"implementing")+SUMIFS(secondary_acts!$S$2:$S$771,secondary_acts!$A$2:$A$771,$A51,secondary_acts!$E$2:$E$771,"delegated") -> 0 | AV51: 0 | AY51: 0 | AZ51: 52018PC0630 | BA51: EUR-Lex HTML | BB51: 11396 | BC51: 179 | BD51: 4 | BE51: =IF(ISNUMBER(BB51),Q51-BB51,"") -> 7010 | BF51: =IF(AND(ISNUMBER(BB51),BB51>0),(Q51-BB51)/BB51,"") -> 0.61512812 | BG51: =IF(ISNUMBER(BC51),X51-BC51,"") -> 62 | BH51: =IF(AND(ISNUMBER(BC51),BC51>0),(X51-BC51)/BC51,"") -> 0.34636872 | BI51: =IF(ISNUMBER(BD51),AD51-BD51,"") -> 2
A52: 51 | B52: Terrorist Content Online Regulation | C52: Regulation (EU) 2021/784 | D52: Law Enforcement | E52: enacted | F52: 2018-09-12 | G52: high | H52: 2021-04-29 | I52: 2021-05-17 | J52: 2021-06-06 | K52: adopted | L52: adopted | M52: 32021R0784 | N52: Original act as published in the OJ | O52: https://eur-lex.europa.eu/legal-content/EN/TXT/?uri=CELEX:32021R0784 | P52: 31 | Q52: 14863 | R52: 7025 | S52: 6914 | T52: 6635 | U52: 1203 | V52: 0 | W52: 0 | X52: 118 | Y52: 101 | Z52: 6 | AA52: 0 | AB52: 1 | AC52: 10 | AD52: 37 | AE52: 37 | AF52: 11 | AG52: 33 | AH52: 02021R0784-20210517 | AI52: 118 | AJ52: 37 | AK52: =COUNTIFS(secondary_acts!$A$2:$A$771,$A52,secondary_acts!$E$2:$E$771,"implementing") -> 0 | AL52: =COUNTIFS(secondary_acts!$A$2:$A$771,$A52,secondary_acts!$E$2:$E$771,"delegated") -> 0 | AM52: =COUNTIFS(secondary_acts!$A$2:$A$771,$A52,secondary_acts!$E$2:$E$771,"other Commission/Council act") -> 0 | AN52: =COUNTIFS(secondary_acts!$A$2:$A$771,$A52,secondary_acts!$E$2:$E$771,"guidance") -> 0 | AO52: =COUNTIF(guidance_web!$A$2:$A$7,$A52) -> 0 | AP52: =COUNTIFS(guidance_agencies!$A$2:$A$81,$A52,guidance_agencies!$D$2:$D$81,"EDPB") -> 0 | AQ52: =COUNTIFS(guidance_agencies!$A$2:$A$81,$A52,guidance_agencies!$D$2:$D$81,"EBA") -> 0 | AR52: =COUNTIFS(guidance_agencies!$A$2:$A$81,$A52,guidance_agencies!$D$2:$D$81,"ESMA") -> 0 | AS52: =SUMIFS(secondary_acts!$S$2:$S$771,secondary_acts!$A$2:$A$771,$A52,secondary_acts!$E$2:$E$771,"implementing")+SUMIFS(secondary_acts!$S$2:$S$771,secondary_acts!$A$2:$A$771,$A52,secondary_acts!$E$2:$E$771,"delegated") -> 0 | AV52: 0 | AY52: 3 | AZ52: 52018PC0640 | BA52: EUR-Lex HTML | BB52: 11209 | BC52: 95 | BD52: 35 | BE52: =IF(ISNUMBER(BB52),Q52-BB52,"") -> 3654 | BF52: =IF(AND(ISNUMBER(BB52),BB52>0),(Q52-BB52)/BB52,"") -> 0.32598805 | BG52: =IF(ISNUMBER(BC52),X52-BC52,"") -> 23 | BH52: =IF(AND(ISNUMBER(BC52),BC52>0),(X52-BC52)/BC52,"") -> 0.24210526 | BI52: =IF(ISNUMBER(BD52),AD52-BD52,"") -> 2 | BJ52: no consolidated text with amendments in EUR-Lex; consolidated count = original
A53: 52 | B53: Recovery and Resilience Facility | C53: Regulation (EU) 2021/241 | D53: Industrial Policy | E53: enacted | F53: 2020-05-28 | G53: high | H53: 2021-02-12 | I53: 2021-02-18 | J53: 2021-02-19 | K53: adopted | L53: adopted | M53: 32021R0241 | N53: Original act as published in the OJ | O53: https://eur-lex.europa.eu/legal-content/EN/TXT/?uri=CELEX:32021R0241 | P53: 59 | Q53: 29391 | R53: 8842 | S53: 8721 | T53: 11556 | U53: 8993 | V53: 0 | W53: 0 | X53: 189 | Y53: 177 | Z53: 7 | AA53: 3 | AB53: 1 | AC53: 1 | AD53: 8 | AE53: 29 | AF53: 91 | AG53: 61 | AH53: 02021R0241-20240301 | AI53: 226 | AJ53: 14 | AK53: =COUNTIFS(secondary_acts!$A$2:$A$771,$A53,secondary_acts!$E$2:$E$771,"implementing") -> 1 | AL53: =COUNTIFS(secondary_acts!$A$2:$A$771,$A53,secondary_acts!$E$2:$E$771,"delegated") -> 2 | AM53: =COUNTIFS(secondary_acts!$A$2:$A$771,$A53,secondary_acts!$E$2:$E$771,"other Commission/Council act") -> 0 | AN53: =COUNTIFS(secondary_acts!$A$2:$A$771,$A53,secondary_acts!$E$2:$E$771,"guidance") -> 4 | AO53: =COUNTIF(guidance_web!$A$2:$A$7,$A53) -> 0 | AP53: =COUNTIFS(guidance_agencies!$A$2:$A$81,$A53,guidance_agencies!$D$2:$D$81,"EDPB") -> 0 | AQ53: =COUNTIFS(guidance_agencies!$A$2:$A$81,$A53,guidance_agencies!$D$2:$D$81,"EBA") -> 0 | AR53: =COUNTIFS(guidance_agencies!$A$2:$A$81,$A53,guidance_agencies!$D$2:$D$81,"ESMA") -> 0 | AS53: =SUMIFS(secondary_acts!$S$2:$S$771,secondary_acts!$A$2:$A$771,$A53,secondary_acts!$E$2:$E$771,"implementing")+SUMIFS(secondary_acts!$S$2:$S$771,secondary_acts!$A$2:$A$771,$A53,secondary_acts!$E$2:$E$771,"delegated") -> 111 | AV53: 2 | AW53: 2023-02-27 | AX53: 2024-02-29 | AY53: 9 | AZ53: 52020PC0408 | BA53: EUR-Lex HTML | BB53: 12953 | BC53: 117 | BD53: 5 | BE53: =IF(ISNUMBER(BB53),Q53-BB53,"") -> 16438 | BF53: =IF(AND(ISNUMBER(BB53),BB53>0),(Q53-BB53)/BB53,"") -> 1.2690496 | BG53: =IF(ISNUMBER(BC53),X53-BC53,"") -> 72 | BH53: =IF(AND(ISNUMBER(BC53),BC53>0),(X53-BC53)/BC53,"") -> 0.61538462 | BI53: =IF(ISNUMBER(BD53),AD53-BD53,"") -> 3
A54: 53 | B54: Temporary CSAM Derogation Regulation | C54: Regulation (EU) 2021/1232 | D54: Law Enforcement | E54: enacted | F54: 2020-09-10 | G54: high | H54: 2021-07-14 | I54: 2021-07-30 | J54: 2021-08-02 | K54: adopted | L54: adopted | M54: 32021R1232 | N54: Original act as published in the OJ | O54: https://eur-lex.europa.eu/legal-content/EN/TXT/?uri=CELEX:32021R1232 | P54: 11 | Q54: 6315 | R54: 4021 | S54: 3869 | T54: 2294 | U54: 0 | V54: 0 | W54: 0 | X54: 11 | Y54: 11 | Z54: 0 | AA54: 0 | AB54: 0 | AC54: 0 | AD54: 2 | AE54: 1 | AF54: 7 | AG54: 1 | AH54: 02021R1232-20240515 | AI54: 16 | AJ54: 2 | AK54: =COUNTIFS(secondary_acts!$A$2:$A$771,$A54,secondary_acts!$E$2:$E$771,"implementing") -> 1 | AL54: =COUNTIFS(secondary_acts!$A$2:$A$771,$A54,secondary_acts!$E$2:$E$771,"delegated") -> 0 | AM54: =COUNTIFS(secondary_acts!$A$2:$A$771,$A54,secondary_acts!$E$2:$E$771,"other Commission/Council act") -> 0 | AN54: =COUNTIFS(secondary_acts!$A$2:$A$771,$A54,secondary_acts!$E$2:$E$771,"guidance") -> 0 | AO54: =COUNTIF(guidance_web!$A$2:$A$7,$A54) -> 0 | AP54: =COUNTIFS(guidance_agencies!$A$2:$A$81,$A54,guidance_agencies!$D$2:$D$81,"EDPB") -> 0 | AQ54: =COUNTIFS(guidance_agencies!$A$2:$A$81,$A54,guidance_agencies!$D$2:$D$81,"EBA") -> 0 | AR54: =COUNTIFS(guidance_agencies!$A$2:$A$81,$A54,guidance_agencies!$D$2:$D$81,"ESMA") -> 0 | AS54: =SUMIFS(secondary_acts!$S$2:$S$771,secondary_acts!$A$2:$A$771,$A54,secondary_acts!$E$2:$E$771,"implementing")+SUMIFS(secondary_acts!$S$2:$S$771,secondary_acts!$A$2:$A$771,$A54,secondary_acts!$E$2:$E$771,"delegated") -> 1 | AV54: 1 | AW54: 2024-04-29 | AX54: 2024-04-29 | AY54: 0 | AZ54: 52020PC0568 | BA54: EUR-Lex HTML | BB54: 2709 | BC54: 1 | BD54: 1 | BE54: =IF(ISNUMBER(BB54),Q54-BB54,"") -> 3606 | BF54: =IF(AND(ISNUMBER(BB54),BB54>0),(Q54-BB54)/BB54,"") -> 1.3311185 | BG54: =IF(ISNUMBER(BC54),X54-BC54,"") -> 10 | BH54: =IF(AND(ISNUMBER(BC54),BC54>0),(X54-BC54)/BC54,"") -> 10 | BI54: =IF(ISNUMBER(BD54),AD54-BD54,"") -> 1
A55: 54 | B55: EuroHPC Joint Undertaking Regulation | C55: Regulation (EU) 2021/1173 | D55: Industrial Policy | E55: enacted | F55: 2020-09-18 | G55: high | H55: 2021-07-13 | I55: 2021-07-19 | J55: 2021-08-08 | K55: adopted | L55: adopted | M55: 32021R1173 | N55: Original act as published in the OJ | O55: https://eur-lex.europa.eu/legal-content/EN/TXT/?uri=CELEX:32021R1173 | P55: 49 | Q55: 26545 | R55: 7467 | S55: 7367 | T55: 11295 | U55: 7783 | V55: 0 | W55: 0 | X55: 340 | Y55: 313 | Z55: 18 | AA55: 3 | AB55: 1 | AC55: 5 | AD55: 33 | AE55: 7 | AF55: 204 | AG55: 96 | AH55: 02021R1173-20260120 | AI55: 438 | AJ55: 47 | AK55: =COUNTIFS(secondary_acts!$A$2:$A$771,$A55,secondary_acts!$E$2:$E$771,"implementing") -> 0 | AL55: =COUNTIFS(secondary_acts!$A$2:$A$771,$A55,secondary_acts!$E$2:$E$771,"delegated") -> 0 | AM55: =COUNTIFS(secondary_acts!$A$2:$A$771,$A55,secondary_acts!$E$2:$E$771,"other Commission/Council act") -> 0 | AN55: =COUNTIFS(secondary_acts!$A$2:$A$771,$A55,secondary_acts!$E$2:$E$771,"guidance") -> 0 | AO55: =COUNTIF(guidance_web!$A$2:$A$7,$A55) -> 0 | AP55: =COUNTIFS(guidance_agencies!$A$2:$A$81,$A55,guidance_agencies!$D$2:$D$81,"EDPB") -> 0 | AQ55: =COUNTIFS(guidance_agencies!$A$2:$A$81,$A55,guidance_agencies!$D$2:$D$81,"EBA") -> 0 | AR55: =COUNTIFS(guidance_agencies!$A$2:$A$81,$A55,guidance_agencies!$D$2:$D$81,"ESMA") -> 0 | AS55: =SUMIFS(secondary_acts!$S$2:$S$771,secondary_acts!$A$2:$A$771,$A55,secondary_acts!$E$2:$E$771,"implementing")+SUMIFS(secondary_acts!$S$2:$S$771,secondary_acts!$A$2:$A$771,$A55,secondary_acts!$E$2:$E$771,"delegated") -> 0 | AV55: 2 | AW55: 2024-06-17 | AX55: 2026-01-16 | AY55: 2 | AZ55: 52020PC0569 | BA55: EUR-Lex HTML | BB55: 24251 | BC55: 318 | BD55: 29 | BE55: =IF(ISNUMBER(BB55),Q55-BB55,"") -> 2294 | BF55: =IF(AND(ISNUMBER(BB55),BB55>0),(Q55-BB55)/BB55,"") -> 0.094594037 | BG55: =IF(ISNUMBER(BC55),X55-BC55,"") -> 22 | BH55: =IF(AND(ISNUMBER(BC55),BC55>0),(X55-BC55)/BC55,"") -> 0.06918239 | BI55: =IF(ISNUMBER(BD55),AD55-BD55,"") -> 4
A56: 55 | B56: DLT Pilot Regime Regulation | C56: Regulation (EU) 2022/858 | D56: Research & Innovation | E56: enacted | F56: 2020-09-24 | G56: high | H56: 2022-05-30 | I56: 2022-06-02 | J56: 2022-06-22 | K56: adopted | L56: adopted | M56: 32022R0858 | N56: Original act as published in the OJ | O56: https://eur-lex.europa.eu/legal-content/EN/TXT/?uri=CELEX:32022R0858 | P56: 33 | Q56: 20926 | R56: 8227 | S56: 8084 | T56: 12699 | U56: 0 | V56: 0 | W56: 0 | X56: 178 | Y56: 159 | Z56: 11 | AA56: 1 | AB56: 1 | AC56: 6 | AD56: 53 | AE56: 53 | AF56: 34 | AG56: 38 | AH56: 02022R0858-20220602 | AI56: 178 | AJ56: 53 | AK56: =COUNTIFS(secondary_acts!$A$2:$A$771,$A56,secondary_acts!$E$2:$E$771,"implementing") -> 0 | AL56: =COUNTIFS(secondary_acts!$A$2:$A$771,$A56,secondary_acts!$E$2:$E$771,"delegated") -> 0 | AM56: =COUNTIFS(secondary_acts!$A$2:$A$771,$A56,secondary_acts!$E$2:$E$771,"other Commission/Council act") -> 0 | AN56: =COUNTIFS(secondary_acts!$A$2:$A$771,$A56,secondary_acts!$E$2:$E$771,"guidance") -> 0 | AO56: =COUNTIF(guidance_web!$A$2:$A$7,$A56) -> 0 | AP56: =COUNTIFS(guidance_agencies!$A$2:$A$81,$A56,guidance_agencies!$D$2:$D$81,"EDPB") -> 0 | AQ56: =COUNTIFS(guidance_agencies!$A$2:$A$81,$A56,guidance_agencies!$D$2:$D$81,"EBA") -> 0 | AR56: =COUNTIFS(guidance_agencies!$A$2:$A$81,$A56,guidance_agencies!$D$2:$D$81,"ESMA") -> 1 | AS56: =SUMIFS(secondary_acts!$S$2:$S$771,secondary_acts!$A$2:$A$771,$A56,secondary_acts!$E$2:$E$771,"implementing")+SUMIFS(secondary_acts!$S$2:$S$771,secondary_acts!$A$2:$A$771,$A56,secondary_acts!$E$2:$E$771,"delegated") -> 0 | AV56: 0 | AY56: 1 | AZ56: 52020PC0594 | BA56: EUR-Lex HTML | BB56: 12859 | BC56: 84 | BD56: 34 | BE56: =IF(ISNUMBER(BB56),Q56-BB56,"") -> 8067 | BF56: =IF(AND(ISNUMBER(BB56),BB56>0),(Q56-BB56)/BB56,"") -> 0.62734272 | BG56: =IF(ISNUMBER(BC56),X56-BC56,"") -> 94 | BH56: =IF(AND(ISNUMBER(BC56),BC56>0),(X56-BC56)/BC56,"") -> 1.1190476 | BI56: =IF(ISNUMBER(BD56),AD56-BD56,"") -> 19 | BJ56: no consolidated text with amendments in EUR-Lex; consolidated count = original
A57: 56 | B57: Markets in Crypto-Assets (MiCA) | C57: Regulation (EU) 2023/1114 | D57: Finance | E57: enacted | F57: 2020-09-24 | G57: high | H57: 2023-05-31 | I57: 2023-06-09 | J57: 2023-06-29 | K57: adopted | L57: adopted | M57: 32023R1114 | N57: Original act as published in the OJ | O57: https://eur-lex.europa.eu/legal-content/EN/TXT/?uri=CELEX:32023R1114 | P57: 166 | Q57: 95588 | R57: 15644 | S57: 15505 | T57: 69742 | U57: 10202 | V57: 0 | W57: 0 | X57: 1117 | Y57: 969 | Z57: 84 | AA57: 13 | AB57: 14 | AC57: 37 | AD57: 444 | AE57: 209 | AF57: 262 | AG57: 202 | AH57: 02023R1114-20240109 | AI57: 1129 | AJ57: 446 | AK57: =COUNTIFS(secondary_acts!$A$2:$A$771,$A57,secondary_acts!$E$2:$E$771,"implementing") -> 8 | AL57: =COUNTIFS(secondary_acts!$A$2:$A$771,$A57,secondary_acts!$E$2:$E$771,"delegated") -> 29 | AM57: =COUNTIFS(secondary_acts!$A$2:$A$771,$A57,secondary_acts!$E$2:$E$771,"other Commission/Council act") -> 0 | AN57: =COUNTIFS(secondary_acts!$A$2:$A$771,$A57,secondary_acts!$E$2:$E$771,"guidance") -> 0 | AO57: =COUNTIF(guidance_web!$A$2:$A$7,$A57) -> 0 | AP57: =COUNTIFS(guidance_agencies!$A$2:$A$81,$A57,guidance_agencies!$D$2:$D$81,"EDPB") -> 0 | AQ57: =COUNTIFS(guidance_agencies!$A$2:$A$81,$A57,guidance_agencies!$D$2:$D$81,"EBA") -> 7 | AR57: =COUNTIFS(guidance_agencies!$A$2:$A$81,$A57,guidance_agencies!$D$2:$D$81,"ESMA") -> 7 | AS57: =SUMIFS(secondary_acts!$S$2:$S$771,secondary_acts!$A$2:$A$771,$A57,secondary_acts!$E$2:$E$771,"implementing")+SUMIFS(secondary_acts!$S$2:$S$771,secondary_acts!$A$2:$A$771,$A57,secondary_acts!$E$2:$E$771,"delegated") -> 1340 | AV57: 1 | AW57: 2023-12-13 | AX57: 2023-12-13 | AY57: 6 | AZ57: 52020PC0593 | BA57: EUR-Lex HTML | BB57: 64264 | BC57: 766 | BD57: 335 | BE57: =IF(ISNUMBER(BB57),Q57-BB57,"") -> 31324 | BF57: =IF(AND(ISNUMBER(BB57),BB57>0),(Q57-BB57)/BB57,"") -> 0.48742686 | BG57: =IF(ISNUMBER(BC57),X57-BC57,"") -> 351 | BH57: =IF(AND(ISNUMBER(BC57),BC57>0),(X57-BC57)/BC57,"") -> 0.45822454 | BI57: =IF(ISNUMBER(BD57),AD57-BD57,"") -> 109
A58: 57 | B58: Digital Operational Resilience Act (DORA) | C58: Regulation (EU) 2022/2554 | D58: Finance | E58: enacted | F58: 2020-09-24 | G58: high | H58: 2022-12-14 | I58: 2022-12-27 | J58: 2023-01-16 | K58: adopted | L58: adopted | M58: 32022R2554 | N58: Original act as published in the OJ | O58: https://eur-lex.europa.eu/legal-content/EN/TXT/?uri=CELEX:32022R2554 | P58: 79 | Q58: 43943 | R58: 14445 | S58: 14300 | T58: 29498 | U58: 0 | V58: 0 | W58: 0 | X58: 431 | Y58: 397 | Z58: 8 | AA58: 5 | AB58: 8 | AC58: 13 | AD58: 185 | AE58: 48 | AF58: 30 | AG58: 168 | AH58: 02022R2554-20221227 | AI58: 431 | AJ58: 185 | AK58: =COUNTIFS(secondary_acts!$A$2:$A$771,$A58,secondary_acts!$E$2:$E$771,"implementing") -> 2 | AL58: =COUNTIFS(secondary_acts!$A$2:$A$771,$A58,secondary_acts!$E$2:$E$771,"delegated") -> 10 | AM58: =COUNTIFS(secondary_acts!$A$2:$A$771,$A58,secondary_acts!$E$2:$E$771,"other Commission/Council act") -> 0 | AN58: =COUNTIFS(secondary_acts!$A$2:$A$771,$A58,secondary_acts!$E$2:$E$771,"guidance") -> 0 | AO58: =COUNTIF(guidance_web!$A$2:$A$7,$A58) -> 0 | AP58: =COUNTIFS(guidance_agencies!$A$2:$A$81,$A58,guidance_agencies!$D$2:$D$81,"EDPB") -> 0 | AQ58: =COUNTIFS(guidance_agencies!$A$2:$A$81,$A58,guidance_agencies!$D$2:$D$81,"EBA") -> 2 | AR58: =COUNTIFS(guidance_agencies!$A$2:$A$81,$A58,guidance_agencies!$D$2:$D$81,"ESMA") -> 0 | AS58: =SUMIFS(secondary_acts!$S$2:$S$771,secondary_acts!$A$2:$A$771,$A58,secondary_acts!$E$2:$E$771,"implementing")+SUMIFS(secondary_acts!$S$2:$S$771,secondary_acts!$A$2:$A$771,$A58,secondary_acts!$E$2:$E$771,"delegated") -> 828 | AV58: 0 | AY58: 9 | AZ58: 52020PC0595 | BA58: EUR-Lex HTML | BB58: 35110 | BC58: 323 | BD58: 162 | BE58: =IF(ISNUMBER(BB58),Q58-BB58,"") -> 8833 | BF58: =IF(AND(ISNUMBER(BB58),BB58>0),(Q58-BB58)/BB58,"") -> 0.25158075 | BG58: =IF(ISNUMBER(BC58),X58-BC58,"") -> 108 | BH58: =IF(AND(ISNUMBER(BC58),BC58>0),(X58-BC58)/BC58,"") -> 0.33436533 | BI58: =IF(ISNUMBER(BD58),AD58-BD58,"") -> 23 | BJ58: no consolidated text with amendments in EUR-Lex; consolidated count = original
A59: 58 | B59: Data Governance Act | C59: Regulation (EU) 2022/868 | D59: Data & Privacy | E59: enacted | F59: 2020-11-25 | G59: high | H59: 2022-05-30 | I59: 2022-06-03 | J59: 2022-06-23 | K59: adopted | L59: adopted | M59: 32022R0868 | N59: Original act as published in the OJ | O59: https://eur-lex.europa.eu/legal-content/EN/TXT/?uri=CELEX:32022R0868 | P59: 44 | Q59: 27006 | R59: 12417 | S59: 12294 | T59: 14589 | U59: 0 | V59: 0 | W59: 0 | X59: 215 | Y59: 191 | Z59: 15 | AA59: 0 | AB59: 1 | AC59: 8 | AD59: 54 | AE59: 78 | AF59: 37 | AG59: 46 | AH59: 02022R0868-20220603 | AI59: 215 | AJ59: 54 | AK59: =COUNTIFS(secondary_acts!$A$2:$A$771,$A59,secondary_acts!$E$2:$E$771,"implementing") -> 1 | AL59: =COUNTIFS(secondary_acts!$A$2:$A$771,$A59,secondary_acts!$E$2:$E$771,"delegated") -> 0 | AM59: =COUNTIFS(secondary_acts!$A$2:$A$771,$A59,secondary_acts!$E$2:$E$771,"other Commission/Council act") -> 0 | AN59: =COUNTIFS(secondary_acts!$A$2:$A$771,$A59,secondary_acts!$E$2:$E$771,"guidance") -> 0 | AO59: =COUNTIF(guidance_web!$A$2:$A$7,$A59) -> 1 | AP59: =COUNTIFS(guidance_agencies!$A$2:$A$81,$A59,guidance_agencies!$D$2:$D$81,"EDPB") -> 0 | AQ59: =COUNTIFS(guidance_agencies!$A$2:$A$81,$A59,guidance_agencies!$D$2:$D$81,"EBA") -> 0 | AR59: =COUNTIFS(guidance_agencies!$A$2:$A$81,$A59,guidance_agencies!$D$2:$D$81,"ESMA") -> 0 | AS59: =SUMIFS(secondary_acts!$S$2:$S$771,secondary_acts!$A$2:$A$771,$A59,secondary_acts!$E$2:$E$771,"implementing")+SUMIFS(secondary_acts!$S$2:$S$771,secondary_acts!$A$2:$A$771,$A59,secondary_acts!$E$2:$E$771,"delegated") -> 7 | AV59: 0 | AY59: 6 | AZ59: 52020PC0767 | BA59: EUR-Lex HTML | BB59: 15916 | BC59: 143 | BD59: 28 | BE59: =IF(ISNUMBER(BB59),Q59-BB59,"") -> 11090 | BF59: =IF(AND(ISNUMBER(BB59),BB59>0),(Q59-BB59)/BB59,"") -> 0.69678311 | BG59: =IF(ISNUMBER(BC59),X59-BC59,"") -> 72 | BH59: =IF(AND(ISNUMBER(BC59),BC59>0),(X59-BC59)/BC59,"") -> 0.5034965 | BI59: =IF(ISNUMBER(BD59),AD59-BD59,"") -> 26 | BJ59: no consolidated text with amendments in EUR-Lex; consolidated count = original
A60: 59 | B60: Digital Markets Act | C60: Regulation (EU) 2022/1925 | D60: Competition & Single Market | E60: enacted | F60: 2020-12-15 | G60: high | H60: 2022-09-14 | I60: 2022-10-12 | J60: 2022-11-01 | K60: adopted | L60: adopted | M60: 32022R1925 | N60: Original act as published in the OJ | O60: https://eur-lex.europa.eu/legal-content/EN/TXT/?uri=CELEX:32022R1925 | P60: 66 | Q60: 39028 | R60: 18191 | S60: 18054 | T60: 18770 | U60: 2067 | V60: 0 | W60: 0 | X60: 281 | Y60: 233 | Z60: 34 | AA60: 3 | AB60: 4 | AC60: 7 | AD60: 111 | AE60: 20 | AF60: 118 | AG60: 32 | AH60: 02022R1925-20221012 | AI60: 281 | AJ60: 111 | AK60: =COUNTIFS(secondary_acts!$A$2:$A$771,$A60,secondary_acts!$E$2:$E$771,"implementing") -> 1 | AL60: =COUNTIFS(secondary_acts!$A$2:$A$771,$A60,secondary_acts!$E$2:$E$771,"delegated") -> 0 | AM60: =COUNTIFS(secondary_acts!$A$2:$A$771,$A60,secondary_acts!$E$2:$E$771,"other Commission/Council act") -> 0 | AN60: =COUNTIFS(secondary_acts!$A$2:$A$771,$A60,secondary_acts!$E$2:$E$771,"guidance") -> 0 | AO60: =COUNTIF(guidance_web!$A$2:$A$7,$A60) -> 0 | AP60: =COUNTIFS(guidance_agencies!$A$2:$A$81,$A60,guidance_agencies!$D$2:$D$81,"EDPB") -> 0 | AQ60: =COUNTIFS(guidance_agencies!$A$2:$A$81,$A60,guidance_agencies!$D$2:$D$81,"EBA") -> 0 | AR60: =COUNTIFS(guidance_agencies!$A$2:$A$81,$A60,guidance_agencies!$D$2:$D$81,"ESMA") -> 0 | AS60: =SUMIFS(secondary_acts!$S$2:$S$771,secondary_acts!$A$2:$A$771,$A60,secondary_acts!$E$2:$E$771,"implementing")+SUMIFS(secondary_acts!$S$2:$S$771,secondary_acts!$A$2:$A$771,$A60,secondary_acts!$E$2:$E$771,"delegated") -> 72 | AV60: 0 | AY60: 3 | AZ60: 52020PC0842 | BA60: EUR-Lex HTML | BB60: 21090 | BC60: 141 | BD60: 40 | BE60: =IF(ISNUMBER(BB60),Q60-BB60,"") -> 17938 | BF60: =IF(AND(ISNUMBER(BB60),BB60>0),(Q60-BB60)/BB60,"") -> 0.85054528 | BG60: =IF(ISNUMBER(BC60),X60-BC60,"") -> 140 | BH60: =IF(AND(ISNUMBER(BC60),BC60>0),(X60-BC60)/BC60,"") -> 0.9929078 | BI60: =IF(ISNUMBER(BD60),AD60-BD60,"") -> 71
A61: 60 | B61: Digital Services Act | C61: Regulation (EU) 2022/2065 | D61: E-commerce & Consumer Protection | E61: enacted | F61: 2020-12-15 | G61: high | H61: 2022-10-19 | I61: 2022-10-27 | J61: 2022-11-16 | K61: adopted | L61: adopted | M61: 32022R2065 | N61: Original act as published in the OJ | O61: https://eur-lex.europa.eu/legal-content/EN/TXT/?uri=CELEX:32022R2065 | P61: 102 | Q61: 62625 | R61: 29191 | S61: 29060 | T61: 33434 | U61: 0 | V61: 0 | W61: 0 | X61: 479 | Y61: 413 | Z61: 28 | AA61: 4 | AB61: 2 | AC61: 32 | AD61: 139 | AE61: 101 | AF61: 151 | AG61: 88 | AH61: 02022R2065-20221027 | AI61: 479 | AJ61: 139 | AK61: =COUNTIFS(secondary_acts!$A$2:$A$771,$A61,secondary_acts!$E$2:$E$771,"implementing") -> 3 | AL61: =COUNTIFS(secondary_acts!$A$2:$A$771,$A61,secondary_acts!$E$2:$E$771,"delegated") -> 3 | AM61: =COUNTIFS(secondary_acts!$A$2:$A$771,$A61,secondary_acts!$E$2:$E$771,"other Commission/Council act") -> 0 | AN61: =COUNTIFS(secondary_acts!$A$2:$A$771,$A61,secondary_acts!$E$2:$E$771,"guidance") -> 2 | AO61: =COUNTIF(guidance_web!$A$2:$A$7,$A61) -> 0 | AP61: =COUNTIFS(guidance_agencies!$A$2:$A$81,$A61,guidance_agencies!$D$2:$D$81,"EDPB") -> 1 | AQ61: =COUNTIFS(guidance_agencies!$A$2:$A$81,$A61,guidance_agencies!$D$2:$D$81,"EBA") -> 0 | AR61: =COUNTIFS(guidance_agencies!$A$2:$A$81,$A61,guidance_agencies!$D$2:$D$81,"ESMA") -> 0 | AS61: =SUMIFS(secondary_acts!$S$2:$S$771,secondary_acts!$A$2:$A$771,$A61,secondary_acts!$E$2:$E$771,"implementing")+SUMIFS(secondary_acts!$S$2:$S$771,secondary_acts!$A$2:$A$771,$A61,secondary_acts!$E$2:$E$771,"delegated") -> 543 | AV61: 0 | AY61: 10 | AZ61: 52020PC0825 | BA61: EUR-Lex HTML | BB61: 33588 | BC61: 284 | BD61: 84 | BE61: =IF(ISNUMBER(BB61),Q61-BB61,"") -> 29037 | BF61: =IF(AND(ISNUMBER(BB61),BB61>0),(Q61-BB61)/BB61,"") -> 0.86450518 | BG61: =IF(ISNUMBER(BC61),X61-BC61,"") -> 195 | BH61: =IF(AND(ISNUMBER(BC61),BC61>0),(X61-BC61)/BC61,"") -> 0.68661972 | BI61: =IF(ISNUMBER(BD61),AD61-BD61,"") -> 55 | BJ61: no consolidated text with amendments in EUR-Lex; consolidated count = original
A62: 61 | B62: NIS 2 Directive | C62: Directive (EU) 2022/2555 | D62: Cybersecurity | E62: enacted | F62: 2020-12-16 | G62: high | H62: 2022-12-14 | I62: 2022-12-27 | J62: 2023-01-16 | K62: adopted | L62: adopted | M62: 32022L2555 | N62: Original act as published in the OJ | O62: https://eur-lex.europa.eu/legal-content/EN/TXT/?uri=CELEX:32022L2555 | P62: 73 | Q62: 40220 | R62: 18851 | S62: 18698 | T62: 18071 | U62: 3298 | V62: 0 | W62: 0 | X62: 288 | Y62: 219 | Z62: 7 | AA62: 0 | AB62: 2 | AC62: 60 | AD62: 11 | AE62: 179 | AF62: 52 | AG62: 46 | AH62: 02022L2555-20221227 | AI62: 288 | AJ62: 11 | AK62: =COUNTIFS(secondary_acts!$A$2:$A$771,$A62,secondary_acts!$E$2:$E$771,"implementing") -> 1 | AL62: =COUNTIFS(secondary_acts!$A$2:$A$771,$A62,secondary_acts!$E$2:$E$771,"delegated") -> 0 | AM62: =COUNTIFS(secondary_acts!$A$2:$A$771,$A62,secondary_acts!$E$2:$E$771,"other Commission/Council act") -> 0 | AN62: =COUNTIFS(secondary_acts!$A$2:$A$771,$A62,secondary_acts!$E$2:$E$771,"guidance") -> 3 | AO62: =COUNTIF(guidance_web!$A$2:$A$7,$A62) -> 0 | AP62: =COUNTIFS(guidance_agencies!$A$2:$A$81,$A62,guidance_agencies!$D$2:$D$81,"EDPB") -> 0 | AQ62: =COUNTIFS(guidance_agencies!$A$2:$A$81,$A62,guidance_agencies!$D$2:$D$81,"EBA") -> 0 | AR62: =COUNTIFS(guidance_agencies!$A$2:$A$81,$A62,guidance_agencies!$D$2:$D$81,"ESMA") -> 0 | AS62: =SUMIFS(secondary_acts!$S$2:$S$771,secondary_acts!$A$2:$A$771,$A62,secondary_acts!$E$2:$E$771,"implementing")+SUMIFS(secondary_acts!$S$2:$S$771,secondary_acts!$A$2:$A$771,$A62,secondary_acts!$E$2:$E$771,"delegated") -> 219 | AT62: 3232 | AU62: 25 | AV62: 0 | AY62: 9 | AZ62: 52020PC0823 | BA62: EUR-Lex HTML | BB62: 31823 | BC62: 227 | BD62: 12 | BE62: =IF(ISNUMBER(BB62),Q62-BB62,"") -> 8397 | BF62: =IF(AND(ISNUMBER(BB62),BB62>0),(Q62-BB62)/BB62,"") -> 0.26386576 | BG62: =IF(ISNUMBER(BC62),X62-BC62,"") -> 61 | BH62: =IF(AND(ISNUMBER(BC62),BC62>0),(X62-BC62)/BC62,"") -> 0.26872247 | BI62: =IF(ISNUMBER(BD62),AD62-BD62,"") -> -1
A63: 62 | B63: Joint Undertakings under Horizon Europe | C63: Regulation (EU) 2021/2085 | D63: Industrial Policy | E63: enacted | F63: 2021-02-23 | G63: high | H63: 2021-11-19 | I63: 2021-11-30 | J63: 2021-11-30 | K63: adopted | L63: adopted | M63: 32021R2085 | N63: Original act as published in the OJ | O63: https://eur-lex.europa.eu/legal-content/EN/TXT/?uri=CELEX:32021R2085 | P63: 103 | Q63: 50649 | R63: 13039 | S63: 12915 | T63: 34391 | U63: 3219 | V63: 0 | W63: 0 | X63: 553 | Y63: 504 | Z63: 28 | AA63: 2 | AB63: 3 | AC63: 16 | AD63: 13 | AE63: 11 | AF63: 361 | AG63: 168 | AH63: 02021R2085-20230921 | AI63: 573 | AJ63: 14 | AK63: =COUNTIFS(secondary_acts!$A$2:$A$771,$A63,secondary_acts!$E$2:$E$771,"implementing") -> 0 | AL63: =COUNTIFS(secondary_acts!$A$2:$A$771,$A63,secondary_acts!$E$2:$E$771,"delegated") -> 0 | AM63: =COUNTIFS(secondary_acts!$A$2:$A$771,$A63,secondary_acts!$E$2:$E$771,"other Commission/Council act") -> 0 | AN63: =COUNTIFS(secondary_acts!$A$2:$A$771,$A63,secondary_acts!$E$2:$E$771,"guidance") -> 0 | AO63: =COUNTIF(guidance_web!$A$2:$A$7,$A63) -> 0 | AP63: =COUNTIFS(guidance_agencies!$A$2:$A$81,$A63,guidance_agencies!$D$2:$D$81,"EDPB") -> 0 | AQ63: =COUNTIFS(guidance_agencies!$A$2:$A$81,$A63,guidance_agencies!$D$2:$D$81,"EBA") -> 0 | AR63: =COUNTIFS(guidance_agencies!$A$2:$A$81,$A63,guidance_agencies!$D$2:$D$81,"ESMA") -> 0 | AS63: =SUMIFS(secondary_acts!$S$2:$S$771,secondary_acts!$A$2:$A$771,$A63,secondary_acts!$E$2:$E$771,"implementing")+SUMIFS(secondary_acts!$S$2:$S$771,secondary_acts!$A$2:$A$771,$A63,secondary_acts!$E$2:$E$771,"delegated") -> 0 | AV63: 1 | AW63: 2023-07-25 | AX63: 2023-07-25 | AY63: 1 | AZ63: 52021PC0087 | BA63: EUR-Lex HTML | BB63: 46901 | BC63: 523 | BD63: 11 | BE63: =IF(ISNUMBER(BB63),Q63-BB63,"") -> 3748 | BF63: =IF(AND(ISNUMBER(BB63),BB63>0),(Q63-BB63)/BB63,"") -> 0.079913008 | BG63: =IF(ISNUMBER(BC63),X63-BC63,"") -> 30 | BH63: =IF(AND(ISNUMBER(BC63),BC63>0),(X63-BC63)/BC63,"") -> 0.057361377 | BI63: =IF(ISNUMBER(BD63),AD63-BD63,"") -> 2
A64: 63 | B64: Roaming Regulation | C64: Regulation (EU) 2022/612 | D64: Connectivity | E64: enacted | F64: 2021-02-24 | G64: high | H64: 2022-04-06 | I64: 2022-04-13 | J64: 2022-07-01 | K64: adopted | L64: adopted | M64: 32022R0612 | N64: Original act as published in the OJ | O64: https://eur-lex.europa.eu/legal-content/EN/TXT/?uri=CELEX:32022R0612 | P64: 37 | Q64: 22492 | R64: 11653 | S64: 11532 | T64: 10036 | U64: 803 | V64: 0 | W64: 0 | X64: 162 | Y64: 141 | Z64: 14 | AA64: 1 | AB64: 0 | AC64: 6 | AD64: 60 | AE64: 29 | AF64: 25 | AG64: 48 | AH64: 02022R0612-20220413 | AI64: 162 | AJ64: 60 | AK64: =COUNTIFS(secondary_acts!$A$2:$A$771,$A64,secondary_acts!$E$2:$E$771,"implementing") -> 0 | AL64: =COUNTIFS(secondary_acts!$A$2:$A$771,$A64,secondary_acts!$E$2:$E$771,"delegated") -> 0 | AM64: =COUNTIFS(secondary_acts!$A$2:$A$771,$A64,secondary_acts!$E$2:$E$771,"other Commission/Council act") -> 0 | AN64: =COUNTIFS(secondary_acts!$A$2:$A$771,$A64,secondary_acts!$E$2:$E$771,"guidance") -> 0 | AO64: =COUNTIF(guidance_web!$A$2:$A$7,$A64) -> 0 | AP64: =COUNTIFS(guidance_agencies!$A$2:$A$81,$A64,guidance_agencies!$D$2:$D$81,"EDPB") -> 0 | AQ64: =COUNTIFS(guidance_agencies!$A$2:$A$81,$A64,guidance_agencies!$D$2:$D$81,"EBA") -> 0 | AR64: =COUNTIFS(guidance_agencies!$A$2:$A$81,$A64,guidance_agencies!$D$2:$D$81,"ESMA") -> 0 | AS64: =SUMIFS(secondary_acts!$S$2:$S$771,secondary_acts!$A$2:$A$771,$A64,secondary_acts!$E$2:$E$771,"implementing")+SUMIFS(secondary_acts!$S$2:$S$771,secondary_acts!$A$2:$A$771,$A64,secondary_acts!$E$2:$E$771,"delegated") -> 0 | AV64: 0 | AY64: 2 | AZ64: 52021PC0085 | BA64: EUR-Lex HTML | BB64: 29549 | BC64: 184 | BD64: 64 | BE64: =IF(ISNUMBER(BB64),Q64-BB64,"") -> -7057 | BF64: =IF(AND(ISNUMBER(BB64),BB64>0),(Q64-BB64)/BB64,"") -> -0.23882365 | BG64: =IF(ISNUMBER(BC64),X64-BC64,"") -> -22 | BH64: =IF(AND(ISNUMBER(BC64),BC64>0),(X64-BC64)/BC64,"") -> -0.11956522 | BI64: =IF(ISNUMBER(BD64),AD64-BD64,"") -> -4 | BJ64: no consolidated text with amendments in EUR-Lex; consolidated count = original
A65: 64 | B65: Artificial Intelligence Act | C65: Regulation (EU) 2024/1689 | D65: Trust & Safety | E65: enacted | F65: 2021-04-21 | G65: high | H65: 2024-06-13 | I65: 2024-07-12 | J65: 2024-08-01 | K65: adopted | L65: adopted | M65: 32024R1689 | N65: Original act as published in the OJ | O65: https://eur-lex.europa.eu/legal-content/EN/TXT/?uri=CELEX:32024R1689 | P65: 144 | Q65: 88508 | R65: 34913 | S65: 34737 | T65: 45964 | U65: 7631 | V65: 0 | W65: 0 | X65: 767 | Y65: 688 | Z65: 37 | AA65: 4 | AB65: 5 | AC65: 33 | AD65: 217 | AE65: 133 | AF65: 173 | AG65: 244 | AH65: 02024R1689-20260727 | AI65: 863 | AJ65: 229 | AK65: =COUNTIFS(secondary_acts!$A$2:$A$771,$A65,secondary_acts!$E$2:$E$771,"implementing") -> 2 | AL65: =COUNTIFS(secondary_acts!$A$2:$A$771,$A65,secondary_acts!$E$2:$E$771,"delegated") -> 0 | AM65: =COUNTIFS(secondary_acts!$A$2:$A$771,$A65,secondary_acts!$E$2:$E$771,"other Commission/Council act") -> 0 | AN65: =COUNTIFS(secondary_acts!$A$2:$A$771,$A65,secondary_acts!$E$2:$E$771,"guidance") -> 0 | AO65: =COUNTIF(guidance_web!$A$2:$A$7,$A65) -> 3 | AP65: =COUNTIFS(guidance_agencies!$A$2:$A$81,$A65,guidance_agencies!$D$2:$D$81,"EDPB") -> 0 | AQ65: =COUNTIFS(guidance_agencies!$A$2:$A$81,$A65,guidance_agencies!$D$2:$D$81,"EBA") -> 0 | AR65: =COUNTIFS(guidance_agencies!$A$2:$A$81,$A65,guidance_agencies!$D$2:$D$81,"ESMA") -> 0 | AS65: =SUMIFS(secondary_acts!$S$2:$S$771,secondary_acts!$A$2:$A$771,$A65,secondary_acts!$E$2:$E$771,"implementing")+SUMIFS(secondary_acts!$S$2:$S$771,secondary_acts!$A$2:$A$771,$A65,secondary_acts!$E$2:$E$771,"delegated") -> 159 | AV65: 1 | AW65: 2026-07-08 | AX65: 2026-07-08 | AY65: 4 | AZ65: 52021PC0206 | BA65: EUR-Lex HTML | BB65: 38412 | BC65: 394 | BD65: 126 | BE65: =IF(ISNUMBER(BB65),Q65-BB65,"") -> 50096 | BF65: =IF(AND(ISNUMBER(BB65),BB65>0),(Q65-BB65)/BB65,"") -> 1.3041758 | BG65: =IF(ISNUMBER(BC65),X65-BC65,"") -> 373 | BH65: =IF(AND(ISNUMBER(BC65),BC65>0),(X65-BC65)/BC65,"") -> 0.94670051 | BI65: =IF(ISNUMBER(BD65),AD65-BD65,"") -> 91
A66: 65 | B66: Machinery Regulation | C66: Regulation (EU) 2023/1230 | D66: Trust & Safety | E66: enacted | F66: 2021-04-21 | G66: high | H66: 2023-06-14 | I66: 2023-06-29 | J66: 2023-07-19 | K66: adopted | L66: adopted | M66: 32023R1230 | N66: Original act as published in the OJ | O66: https://eur-lex.europa.eu/legal-content/EN/TXT/?uri=CELEX:32023R1230 | P66: 102 | Q66: 51980 | R66: 7189 | S66: 7064 | T66: 16691 | U66: 28100 | V66: 0 | W66: 0 | X66: 921 | Y66: 806 | Z66: 62 | AA66: 8 | AB66: 8 | AC66: 37 | AD66: 292 | AE66: 53 | AF66: 61 | AG66: 515 | AH66: 02023R1230-20260727 | AI66: 956 | AJ66: 297 | AK66: =COUNTIFS(secondary_acts!$A$2:$A$771,$A66,secondary_acts!$E$2:$E$771,"implementing") -> 1 | AL66: =COUNTIFS(secondary_acts!$A$2:$A$771,$A66,secondary_acts!$E$2:$E$771,"delegated") -> 0 | AM66: =COUNTIFS(secondary_acts!$A$2:$A$771,$A66,secondary_acts!$E$2:$E$771,"other Commission/Council act") -> 0 | AN66: =COUNTIFS(secondary_acts!$A$2:$A$771,$A66,secondary_acts!$E$2:$E$771,"guidance") -> 1 | AO66: =COUNTIF(guidance_web!$A$2:$A$7,$A66) -> 0 | AP66: =COUNTIFS(guidance_agencies!$A$2:$A$81,$A66,guidance_agencies!$D$2:$D$81,"EDPB") -> 0 | AQ66: =COUNTIFS(guidance_agencies!$A$2:$A$81,$A66,guidance_agencies!$D$2:$D$81,"EBA") -> 0 | AR66: =COUNTIFS(guidance_agencies!$A$2:$A$81,$A66,guidance_agencies!$D$2:$D$81,"ESMA") -> 0 | AS66: =SUMIFS(secondary_acts!$S$2:$S$771,secondary_acts!$A$2:$A$771,$A66,secondary_acts!$E$2:$E$771,"implementing")+SUMIFS(secondary_acts!$S$2:$S$771,secondary_acts!$A$2:$A$771,$A66,secondary_acts!$E$2:$E$771,"delegated") -> 1 | AV66: 2 | AW66: 2024-10-09 | AX66: 2026-07-08 | AY66: 3 | AZ66: 52021PC0202 | BA66: EUR-Lex HTML | BB66: 43556 | BC66: 814 | BD66: 240 | BE66: =IF(ISNUMBER(BB66),Q66-BB66,"") -> 8424 | BF66: =IF(AND(ISNUMBER(BB66),BB66>0),(Q66-BB66)/BB66,"") -> 0.19340619 | BG66: =IF(ISNUMBER(BC66),X66-BC66,"") -> 107 | BH66: =IF(AND(ISNUMBER(BC66),BC66>0),(X66-BC66)/BC66,"") -> 0.13144963 | BI66: =IF(ISNUMBER(BD66),AD66-BD66,"") -> 52
A67: 66 | B67: Foreign Subsidies Regulation | C67: Regulation (EU) 2022/2560 | D67: Competition & Single Market | E67: enacted | F67: 2021-05-05 | G67: high | H67: 2022-12-14 | I67: 2022-12-23 | J67: 2023-01-12 | K67: adopted | L67: adopted | M67: 32022R2560 | N67: Original act as published in the OJ | O67: https://eur-lex.europa.eu/legal-content/EN/TXT/?uri=CELEX:32022R2560 | P67: 45 | Q67: 23466 | R67: 7459 | S67: 7351 | T67: 16007 | U67: 0 | V67: 0 | W67: 0 | X67: 176 | Y67: 146 | Z67: 26 | AA67: 0 | AB67: 2 | AC67: 2 | AD67: 20 | AE67: 14 | AF67: 86 | AG67: 56 | AH67: 02022R2560-20221223 | AI67: 176 | AJ67: 20 | AK67: =COUNTIFS(secondary_acts!$A$2:$A$771,$A67,secondary_acts!$E$2:$E$771,"implementing") -> 2 | AL67: =COUNTIFS(secondary_acts!$A$2:$A$771,$A67,secondary_acts!$E$2:$E$771,"delegated") -> 0 | AM67: =COUNTIFS(secondary_acts!$A$2:$A$771,$A67,secondary_acts!$E$2:$E$771,"other Commission/Council act") -> 0 | AN67: =COUNTIFS(secondary_acts!$A$2:$A$771,$A67,secondary_acts!$E$2:$E$771,"guidance") -> 1 | AO67: =COUNTIF(guidance_web!$A$2:$A$7,$A67) -> 0 | AP67: =COUNTIFS(guidance_agencies!$A$2:$A$81,$A67,guidance_agencies!$D$2:$D$81,"EDPB") -> 0 | AQ67: =COUNTIFS(guidance_agencies!$A$2:$A$81,$A67,guidance_agencies!$D$2:$D$81,"EBA") -> 0 | AR67: =COUNTIFS(guidance_agencies!$A$2:$A$81,$A67,guidance_agencies!$D$2:$D$81,"ESMA") -> 0 | AS67: =SUMIFS(secondary_acts!$S$2:$S$771,secondary_acts!$A$2:$A$771,$A67,secondary_acts!$E$2:$E$771,"implementing")+SUMIFS(secondary_acts!$S$2:$S$771,secondary_acts!$A$2:$A$771,$A67,secondary_acts!$E$2:$E$771,"delegated") -> 191 | AV67: 0 | AY67: 2 | AZ67: 52021PC0223 | BA67: EUR-Lex HTML | BB67: 13590 | BC67: 112 | BD67: 20 | BE67: =IF(ISNUMBER(BB67),Q67-BB67,"") -> 9876 | BF67: =IF(AND(ISNUMBER(BB67),BB67>0),(Q67-BB67)/BB67,"") -> 0.72671082 | BG67: =IF(ISNUMBER(BC67),X67-BC67,"") -> 64 | BH67: =IF(AND(ISNUMBER(BC67),BC67>0),(X67-BC67)/BC67,"") -> 0.57142857 | BI67: =IF(ISNUMBER(BD67),AD67-BD67,"") -> 0
A68: 67 | B68: General Product Safety Regulation | C68: Regulation (EU) 2023/988 | D68: Trust & Safety | E68: enacted | F68: 2021-06-30 | G68: high | H68: 2023-05-10 | I68: 2023-05-23 | J68: 2023-06-12 | K68: adopted | L68: adopted | M68: 32023R0988 | N68: Original act as published in the OJ | O68: https://eur-lex.europa.eu/legal-content/EN/TXT/?uri=CELEX:32023R0988 | P68: 51 | Q68: 27494 | R68: 11555 | S68: 11402 | T68: 15446 | U68: 493 | V68: 0 | W68: 0 | X68: 249 | Y68: 209 | Z68: 11 | AA68: 7 | AB68: 1 | AC68: 21 | AD68: 102 | AE68: 33 | AF68: 74 | AG68: 40 | AH68: 02023R0988-20260529 | AI68: 248 | AJ68: 102 | AK68: =COUNTIFS(secondary_acts!$A$2:$A$771,$A68,secondary_acts!$E$2:$E$771,"implementing") -> 5 | AL68: =COUNTIFS(secondary_acts!$A$2:$A$771,$A68,secondary_acts!$E$2:$E$771,"delegated") -> 1 | AM68: =COUNTIFS(secondary_acts!$A$2:$A$771,$A68,secondary_acts!$E$2:$E$771,"other Commission/Council act") -> 0 | AN68: =COUNTIFS(secondary_acts!$A$2:$A$771,$A68,secondary_acts!$E$2:$E$771,"guidance") -> 2 | AO68: =COUNTIF(guidance_web!$A$2:$A$7,$A68) -> 0 | AP68: =COUNTIFS(guidance_agencies!$A$2:$A$81,$A68,guidance_agencies!$D$2:$D$81,"EDPB") -> 0 | AQ68: =COUNTIFS(guidance_agencies!$A$2:$A$81,$A68,guidance_agencies!$D$2:$D$81,"EBA") -> 0 | AR68: =COUNTIFS(guidance_agencies!$A$2:$A$81,$A68,guidance_agencies!$D$2:$D$81,"ESMA") -> 0 | AS68: =SUMIFS(secondary_acts!$S$2:$S$771,secondary_acts!$A$2:$A$771,$A68,secondary_acts!$E$2:$E$771,"implementing")+SUMIFS(secondary_acts!$S$2:$S$771,secondary_acts!$A$2:$A$771,$A68,secondary_acts!$E$2:$E$771,"delegated") -> 138 | AV68: 1 | AW68: 2024-10-09 | AX68: 2024-10-09 | AY68: 4 | AZ68: 52021PC0346 | BA68: EUR-Lex HTML | BB68: 19646 | BC68: 198 | BD68: 83 | BE68: =IF(ISNUMBER(BB68),Q68-BB68,"") -> 7848 | BF68: =IF(AND(ISNUMBER(BB68),BB68>0),(Q68-BB68)/BB68,"") -> 0.39947063 | BG68: =IF(ISNUMBER(BC68),X68-BC68,"") -> 51 | BH68: =IF(AND(ISNUMBER(BC68),BC68>0),(X68-BC68)/BC68,"") -> 0.25757576 | BI68: =IF(ISNUMBER(BD68),AD68-BD68,"") -> 19
A69: 68 | B69: Anti-Money Laundering Regulation | C69: Regulation (EU) 2024/1624 | D69: Finance | E69: enacted | F69: 2021-07-20 | G69: high | H69: 2024-05-31 | I69: 2024-06-19 | J69: 2024-07-09 | K69: adopted | L69: adopted | M69: 32024R1624 | N69: Original act as published in the OJ | O69: https://eur-lex.europa.eu/legal-content/EN/TXT/?uri=CELEX:32024R1624 | P69: 111 | Q69: 63417 | R69: 25391 | S69: 25257 | T69: 35314 | U69: 2712 | V69: 0 | W69: 0 | X69: 467 | Y69: 408 | Z69: 26 | AA69: 8 | AB69: 4 | AC69: 21 | AD69: 234 | AE69: 48 | AF69: 87 | AG69: 98 | AH69: 02024R1624-20240619 | AI69: 467 | AJ69: 234 | AK69: =COUNTIFS(secondary_acts!$A$2:$A$771,$A69,secondary_acts!$E$2:$E$771,"implementing") -> 0 | AL69: =COUNTIFS(secondary_acts!$A$2:$A$771,$A69,secondary_acts!$E$2:$E$771,"delegated") -> 0 | AM69: =COUNTIFS(secondary_acts!$A$2:$A$771,$A69,secondary_acts!$E$2:$E$771,"other Commission/Council act") -> 0 | AN69: =COUNTIFS(secondary_acts!$A$2:$A$771,$A69,secondary_acts!$E$2:$E$771,"guidance") -> 0 | AO69: =COUNTIF(guidance_web!$A$2:$A$7,$A69) -> 0 | AP69: =COUNTIFS(guidance_agencies!$A$2:$A$81,$A69,guidance_agencies!$D$2:$D$81,"EDPB") -> 0 | AQ69: =COUNTIFS(guidance_agencies!$A$2:$A$81,$A69,guidance_agencies!$D$2:$D$81,"EBA") -> 0 | AR69: =COUNTIFS(guidance_agencies!$A$2:$A$81,$A69,guidance_agencies!$D$2:$D$81,"ESMA") -> 0 | AS69: =SUMIFS(secondary_acts!$S$2:$S$771,secondary_acts!$A$2:$A$771,$A69,secondary_acts!$E$2:$E$771,"implementing")+SUMIFS(secondary_acts!$S$2:$S$771,secondary_acts!$A$2:$A$771,$A69,secondary_acts!$E$2:$E$771,"delegated") -> 0 | AV69: 0 | AY69: 4 | AZ69: 52021PC0420 | BA69: EUR-Lex HTML | BB69: 33016 | BC69: 264 | BD69: 129 | BE69: =IF(ISNUMBER(BB69),Q69-BB69,"") -> 30401 | BF69: =IF(AND(ISNUMBER(BB69),BB69>0),(Q69-BB69)/BB69,"") -> 0.92079598 | BG69: =IF(ISNUMBER(BC69),X69-BC69,"") -> 203 | BH69: =IF(AND(ISNUMBER(BC69),BC69>0),(X69-BC69)/BC69,"") -> 0.76893939 | BI69: =IF(ISNUMBER(BD69),AD69-BD69,"") -> 105 | BJ69: no consolidated text with amendments in EUR-Lex; consolidated count = original
A70: 69 | B70: Vertical Block Exemption Regulation | C70: Regulation (EU) 2022/720 | D70: Competition & Single Market | E70: enacted | F70: 2021-07-09 | G70: low | H70: 2022-05-10 | I70: 2022-05-11 | J70: 2022-06-01 | K70: adopted | L70: adopted | M70: 32022R0720 | N70: Original act as published in the OJ | O70: https://eur-lex.europa.eu/legal-content/EN/TXT/?uri=CELEX:32022R0720 | P70: 10 | Q70: 5548 | R70: 1985 | S70: 1860 | T70: 3563 | U70: 0 | V70: 0 | W70: 0 | X70: 4 | Y70: 3 | Z70: 1 | AA70: 0 | AB70: 0 | AC70: 0 | AD70: 1 | AE70: 0 | AF70: 0 | AG70: 3 | AH70: 02022R0720-20220511 | AI70: 4 | AJ70: 1 | AK70: =COUNTIFS(secondary_acts!$A$2:$A$771,$A70,secondary_acts!$E$2:$E$771,"implementing") -> 0 | AL70: =COUNTIFS(secondary_acts!$A$2:$A$771,$A70,secondary_acts!$E$2:$E$771,"delegated") -> 0 | AM70: =COUNTIFS(secondary_acts!$A$2:$A$771,$A70,secondary_acts!$E$2:$E$771,"other Commission/Council act") -> 0 | AN70: =COUNTIFS(secondary_acts!$A$2:$A$771,$A70,secondary_acts!$E$2:$E$771,"guidance") -> 1 | AO70: =COUNTIF(guidance_web!$A$2:$A$7,$A70) -> 0 | AP70: =COUNTIFS(guidance_agencies!$A$2:$A$81,$A70,guidance_agencies!$D$2:$D$81,"EDPB") -> 0 | AQ70: =COUNTIFS(guidance_agencies!$A$2:$A$81,$A70,guidance_agencies!$D$2:$D$81,"EBA") -> 0 | AR70: =COUNTIFS(guidance_agencies!$A$2:$A$81,$A70,guidance_agencies!$D$2:$D$81,"ESMA") -> 0 | AS70: =SUMIFS(secondary_acts!$S$2:$S$771,secondary_acts!$A$2:$A$771,$A70,secondary_acts!$E$2:$E$771,"implementing")+SUMIFS(secondary_acts!$S$2:$S$771,secondary_acts!$A$2:$A$771,$A70,secondary_acts!$E$2:$E$771,"delegated") -> 0 | AV70: 1 | AW70: 2024-01-19 | AX70: 2024-01-19 | AY70: 1 | BA70: no legislative proposal (Commission act) | BE70: =IF(ISNUMBER(BB70),Q70-BB70,"") | BF70: =IF(AND(ISNUMBER(BB70),BB70>0),(Q70-BB70)/BB70,"") | BG70: =IF(ISNUMBER(BC70),X70-BC70,"") | BH70: =IF(AND(ISNUMBER(BC70),BC70>0),(X70-BC70)/BC70,"") | BI70: =IF(ISNUMBER(BD70),AD70-BD70,"") | BJ70: Block exemption: defines a safe harbour ('the exemption shall not apply to...'), so few direct restrictions are counted; no consolidated text with amendments in EUR-Lex; consolidated count = original
A71: 70 | B71: Digital Decade Policy Programme Decision | C71: Decision (EU) 2022/2481 | D71: Industrial Policy | E71: enacted | F71: 2021-09-15 | G71: high | H71: 2022-12-14 | I71: 2022-12-19 | J71: 2023-01-08 | K71: adopted | L71: adopted | M71: 32022D2481 | N71: Original act as published in the OJ | O71: https://eur-lex.europa.eu/legal-content/EN/TXT/?uri=CELEX:32022D2481 | P71: 23 | Q71: 12229 | R71: 5675 | S71: 5557 | T71: 6391 | U71: 163 | V71: 0 | W71: 0 | X71: 114 | Y71: 110 | Z71: 2 | AA71: 0 | AB71: 1 | AC71: 1 | AD71: 0 | AE71: 20 | AF71: 50 | AG71: 44 | AK71: =COUNTIFS(secondary_acts!$A$2:$A$771,$A71,secondary_acts!$E$2:$E$771,"implementing") -> 8 | AL71: =COUNTIFS(secondary_acts!$A$2:$A$771,$A71,secondary_acts!$E$2:$E$771,"delegated") -> 0 | AM71: =COUNTIFS(secondary_acts!$A$2:$A$771,$A71,secondary_acts!$E$2:$E$771,"other Commission/Council act") -> 0 | AN71: =COUNTIFS(secondary_acts!$A$2:$A$771,$A71,secondary_acts!$E$2:$E$771,"guidance") -> 1 | AO71: =COUNTIF(guidance_web!$A$2:$A$7,$A71) -> 0 | AP71: =COUNTIFS(guidance_agencies!$A$2:$A$81,$A71,guidance_agencies!$D$2:$D$81,"EDPB") -> 0 | AQ71: =COUNTIFS(guidance_agencies!$A$2:$A$81,$A71,guidance_agencies!$D$2:$D$81,"EBA") -> 0 | AR71: =COUNTIFS(guidance_agencies!$A$2:$A$81,$A71,guidance_agencies!$D$2:$D$81,"ESMA") -> 0 | AS71: =SUMIFS(secondary_acts!$S$2:$S$771,secondary_acts!$A$2:$A$771,$A71,secondary_acts!$E$2:$E$771,"implementing")+SUMIFS(secondary_acts!$S$2:$S$771,secondary_acts!$A$2:$A$771,$A71,secondary_acts!$E$2:$E$771,"delegated") -> 68 | AV71: 0 | AY71: 0 | AZ71: 52021PC0574 | BA71: EUR-Lex HTML | BB71: 8794 | BC71: 90 | BD71: 1 | BE71: =IF(ISNUMBER(BB71),Q71-BB71,"") -> 3435 | BF71: =IF(AND(ISNUMBER(BB71),BB71>0),(Q71-BB71)/BB71,"") -> 0.39060723 | BG71: =IF(ISNUMBER(BC71),X71-BC71,"") -> 24 | BH71: =IF(AND(ISNUMBER(BC71),BC71>0),(X71-BC71)/BC71,"") -> 0.26666667 | BI71: =IF(ISNUMBER(BD71),AD71-BD71,"") -> -1
A72: 71 | B72: Political Advertising Regulation | C72: Regulation (EU) 2024/900 | D72: E-commerce & Consumer Protection | E72: enacted | F72: 2021-11-25 | G72: high | H72: 2024-03-13 | I72: 2024-03-20 | J72: 2024-04-09 | K72: adopted | L72: adopted | M72: 32024R0900 | N72: Original act as published in the OJ | O72: https://eur-lex.europa.eu/legal-content/EN/TXT/?uri=CELEX:32024R0900 | P72: 44 | Q72: 25259 | R72: 14100 | S72: 13974 | T72: 11159 | U72: 0 | V72: 0 | W72: 0 | X72: 187 | Y72: 157 | Z72: 9 | AA72: 1 | AB72: 0 | AC72: 20 | AD72: 77 | AE72: 44 | AF72: 23 | AG72: 43 | AH72: 02024R0900-20240320 | AI72: 187 | AJ72: 77 | AK72: =COUNTIFS(secondary_acts!$A$2:$A$771,$A72,secondary_acts!$E$2:$E$771,"implementing") -> 2 | AL72: =COUNTIFS(secondary_acts!$A$2:$A$771,$A72,secondary_acts!$E$2:$E$771,"delegated") -> 0 | AM72: =COUNTIFS(secondary_acts!$A$2:$A$771,$A72,secondary_acts!$E$2:$E$771,"other Commission/Council act") -> 0 | AN72: =COUNTIFS(secondary_acts!$A$2:$A$771,$A72,secondary_acts!$E$2:$E$771,"guidance") -> 1 | AO72: =COUNTIF(guidance_web!$A$2:$A$7,$A72) -> 0 | AP72: =COUNTIFS(guidance_agencies!$A$2:$A$81,$A72,guidance_agencies!$D$2:$D$81,"EDPB") -> 0 | AQ72: =COUNTIFS(guidance_agencies!$A$2:$A$81,$A72,guidance_agencies!$D$2:$D$81,"EBA") -> 0 | AR72: =COUNTIFS(guidance_agencies!$A$2:$A$81,$A72,guidance_agencies!$D$2:$D$81,"ESMA") -> 0 | AS72: =SUMIFS(secondary_acts!$S$2:$S$771,secondary_acts!$A$2:$A$771,$A72,secondary_acts!$E$2:$E$771,"implementing")+SUMIFS(secondary_acts!$S$2:$S$771,secondary_acts!$A$2:$A$771,$A72,secondary_acts!$E$2:$E$771,"delegated") -> 70 | AV72: 0 | AY72: 1 | AZ72: 52021PC0731 | BA72: EUR-Lex HTML | BB72: 12473 | BC72: 86 | BD72: 31 | BE72: =IF(ISNUMBER(BB72),Q72-BB72,"") -> 12786 | BF72: =IF(AND(ISNUMBER(BB72),BB72>0),(Q72-BB72)/BB72,"") -> 1.0250942 | BG72: =IF(ISNUMBER(BC72),X72-BC72,"") -> 101 | BH72: =IF(AND(ISNUMBER(BC72),BC72>0),(X72-BC72)/BC72,"") -> 1.1744186 | BI72: =IF(ISNUMBER(BD72),AD72-BD72,"") -> 46 | BJ72: no consolidated text with amendments in EUR-Lex; consolidated count = original
A73: 72 | B73: Digitalisation of judicial cooperation Regulation | C73: Regulation (EU) 2023/2844 | D73: Law Enforcement | E73: enacted | F73: 2021-12-01 | G73: high | H73: 2023-12-13 | I73: 2023-12-27 | J73: 2024-01-16 | K73: adopted | L73: adopted | M73: 32023R2844 | N73: Original act as published in the OJ | O73: https://eur-lex.europa.eu/legal-content/EN/TXT/?uri=CELEX:32023R2844 | P73: 29 | Q73: 15400 | R73: 5996 | S73: 5858 | T73: 8635 | U73: 769 | V73: 0 | W73: 0 | X73: 135 | Y73: 121 | Z73: 4 | AA73: 0 | AB73: 1 | AC73: 9 | AD73: 9 | AE73: 63 | AF73: 25 | AG73: 38 | AH73: 02023R2844-20231227 | AI73: 125 | AJ73: 9 | AK73: =COUNTIFS(secondary_acts!$A$2:$A$771,$A73,secondary_acts!$E$2:$E$771,"implementing") -> 2 | AL73: =COUNTIFS(secondary_acts!$A$2:$A$771,$A73,secondary_acts!$E$2:$E$771,"delegated") -> 0 | AM73: =COUNTIFS(secondary_acts!$A$2:$A$771,$A73,secondary_acts!$E$2:$E$771,"other Commission/Council act") -> 0 | AN73: =COUNTIFS(secondary_acts!$A$2:$A$771,$A73,secondary_acts!$E$2:$E$771,"guidance") -> 0 | AO73: =COUNTIF(guidance_web!$A$2:$A$7,$A73) -> 0 | AP73: =COUNTIFS(guidance_agencies!$A$2:$A$81,$A73,guidance_agencies!$D$2:$D$81,"EDPB") -> 0 | AQ73: =COUNTIFS(guidance_agencies!$A$2:$A$81,$A73,guidance_agencies!$D$2:$D$81,"EBA") -> 0 | AR73: =COUNTIFS(guidance_agencies!$A$2:$A$81,$A73,guidance_agencies!$D$2:$D$81,"ESMA") -> 0 | AS73: =SUMIFS(secondary_acts!$S$2:$S$771,secondary_acts!$A$2:$A$771,$A73,secondary_acts!$E$2:$E$771,"implementing")+SUMIFS(secondary_acts!$S$2:$S$771,secondary_acts!$A$2:$A$771,$A73,secondary_acts!$E$2:$E$771,"delegated") -> 214 | AV73: 0 | AY73: 2 | AZ73: 52021PC0759 | BA73: EUR-Lex HTML | BB73: 9442 | BC73: 101 | BD73: 1 | BE73: =IF(ISNUMBER(BB73),Q73-BB73,"") -> 5958 | BF73: =IF(AND(ISNUMBER(BB73),BB73>0),(Q73-BB73)/BB73,"") -> 0.63101038 | BG73: =IF(ISNUMBER(BC73),X73-BC73,"") -> 34 | BH73: =IF(AND(ISNUMBER(BC73),BC73>0),(X73-BC73)/BC73,"") -> 0.33663366 | BI73: =IF(ISNUMBER(BD73),AD73-BD73,"") -> 8
A74: 73 | B74: Platform Work Directive | C74: Directive (EU) 2024/2831 | D74: Competition & Single Market | E74: enacted | F74: 2021-12-09 | G74: high | H74: 2024-10-23 | I74: 2024-11-11 | J74: 2024-12-01 | K74: adopted | L74: adopted | M74: 32024L2831 | N74: Original act as published in the OJ | O74: https://eur-lex.europa.eu/legal-content/EN/TXT/?uri=CELEX:32024L2831 | P74: 26 | Q74: 16094 | R74: 9641 | S74: 9503 | T74: 6453 | U74: 0 | V74: 0 | W74: 0 | X74: 100 | Y74: 77 | Z74: 4 | AA74: 0 | AB74: 0 | AC74: 19 | AD74: 33 | AE74: 50 | AF74: 2 | AG74: 15 | AH74: 02024L2831-20241111 | AI74: 100 | AJ74: 33 | AK74: =COUNTIFS(secondary_acts!$A$2:$A$771,$A74,secondary_acts!$E$2:$E$771,"implementing") -> 0 | AL74: =COUNTIFS(secondary_acts!$A$2:$A$771,$A74,secondary_acts!$E$2:$E$771,"delegated") -> 0 | AM74: =COUNTIFS(secondary_acts!$A$2:$A$771,$A74,secondary_acts!$E$2:$E$771,"other Commission/Council act") -> 0 | AN74: =COUNTIFS(secondary_acts!$A$2:$A$771,$A74,secondary_acts!$E$2:$E$771,"guidance") -> 0 | AO74: =COUNTIF(guidance_web!$A$2:$A$7,$A74) -> 0 | AP74: =COUNTIFS(guidance_agencies!$A$2:$A$81,$A74,guidance_agencies!$D$2:$D$81,"EDPB") -> 0 | AQ74: =COUNTIFS(guidance_agencies!$A$2:$A$81,$A74,guidance_agencies!$D$2:$D$81,"EBA") -> 0 | AR74: =COUNTIFS(guidance_agencies!$A$2:$A$81,$A74,guidance_agencies!$D$2:$D$81,"ESMA") -> 0 | AS74: =SUMIFS(secondary_acts!$S$2:$S$771,secondary_acts!$A$2:$A$771,$A74,secondary_acts!$E$2:$E$771,"implementing")+SUMIFS(secondary_acts!$S$2:$S$771,secondary_acts!$A$2:$A$771,$A74,secondary_acts!$E$2:$E$771,"delegated") -> 0 | AT74: 0 | AU74: 0 | AV74: 0 | AY74: 1 | AZ74: 52021PC0762 | BA74: EUR-Lex HTML | BB74: 10937 | BC74: 67 | BD74: 18 | BE74: =IF(ISNUMBER(BB74),Q74-BB74,"") -> 5157 | BF74: =IF(AND(ISNUMBER(BB74),BB74>0),(Q74-BB74)/BB74,"") -> 0.4715187 | BG74: =IF(ISNUMBER(BC74),X74-BC74,"") -> 33 | BH74: =IF(AND(ISNUMBER(BC74),BC74>0),(X74-BC74)/BC74,"") -> 0.49253731 | BI74: =IF(ISNUMBER(BD74),AD74-BD74,"") -> 15
A75: 74 | B75: European Chips Act | C75: Regulation (EU) 2023/1781 | D75: Industrial Policy | E75: enacted | F75: 2022-02-08 | G75: high | H75: 2023-09-13 | I75: 2023-09-18 | J75: 2023-09-21 | K75: adopted | L75: adopted | M75: 32023R1781 | N75: Original act as published in the OJ | O75: https://eur-lex.europa.eu/legal-content/EN/TXT/?uri=CELEX:32023R1781 | P75: 53 | Q75: 28299 | R75: 11733 | S75: 11596 | T75: 14035 | U75: 2531 | V75: 0 | W75: 0 | X75: 242 | Y75: 210 | Z75: 12 | AA75: 0 | AB75: 5 | AC75: 15 | AD75: 14 | AE75: 28 | AF75: 114 | AG75: 86 | AK75: =COUNTIFS(secondary_acts!$A$2:$A$771,$A75,secondary_acts!$E$2:$E$771,"implementing") -> 0 | AL75: =COUNTIFS(secondary_acts!$A$2:$A$771,$A75,secondary_acts!$E$2:$E$771,"delegated") -> 0 | AM75: =COUNTIFS(secondary_acts!$A$2:$A$771,$A75,secondary_acts!$E$2:$E$771,"other Commission/Council act") -> 0 | AN75: =COUNTIFS(secondary_acts!$A$2:$A$771,$A75,secondary_acts!$E$2:$E$771,"guidance") -> 1 | AO75: =COUNTIF(guidance_web!$A$2:$A$7,$A75) -> 0 | AP75: =COUNTIFS(guidance_agencies!$A$2:$A$81,$A75,guidance_agencies!$D$2:$D$81,"EDPB") -> 0 | AQ75: =COUNTIFS(guidance_agencies!$A$2:$A$81,$A75,guidance_agencies!$D$2:$D$81,"EBA") -> 0 | AR75: =COUNTIFS(guidance_agencies!$A$2:$A$81,$A75,guidance_agencies!$D$2:$D$81,"ESMA") -> 0 | AS75: =SUMIFS(secondary_acts!$S$2:$S$771,secondary_acts!$A$2:$A$771,$A75,secondary_acts!$E$2:$E$771,"implementing")+SUMIFS(secondary_acts!$S$2:$S$771,secondary_acts!$A$2:$A$771,$A75,secondary_acts!$E$2:$E$771,"delegated") -> 0 | AV75: 0 | AY75: 0 | AZ75: 52022PC0046 | BA75: EUR-Lex HTML | BB75: 19811 | BC75: 171 | BD75: 13 | BE75: =IF(ISNUMBER(BB75),Q75-BB75,"") -> 8488 | BF75: =IF(AND(ISNUMBER(BB75),BB75>0),(Q75-BB75)/BB75,"") -> 0.42844884 | BG75: =IF(ISNUMBER(BC75),X75-BC75,"") -> 71 | BH75: =IF(AND(ISNUMBER(BC75),BC75>0),(X75-BC75)/BC75,"") -> 0.41520468 | BI75: =IF(ISNUMBER(BD75),AD75-BD75,"") -> 1
A76: 75 | B76: Union Secure Connectivity Programme | C76: Regulation (EU) 2023/588 | D76: Connectivity | E76: enacted | F76: 2022-02-15 | G76: high | H76: 2023-03-15 | I76: 2023-03-17 | J76: 2023-03-20 | K76: adopted | L76: adopted | M76: 32023R0588 | N76: Original act as published in the OJ | O76: https://eur-lex.europa.eu/legal-content/EN/TXT/?uri=CELEX:32023R0588 | P76: 39 | Q76: 19825 | R76: 8242 | S76: 8145 | T76: 10757 | U76: 826 | V76: 0 | W76: 0 | X76: 174 | Y76: 154 | Z76: 4 | AA76: 0 | AB76: 1 | AC76: 15 | AD76: 10 | AE76: 14 | AF76: 82 | AG76: 68 | AK76: =COUNTIFS(secondary_acts!$A$2:$A$771,$A76,secondary_acts!$E$2:$E$771,"implementing") -> 2 | AL76: =COUNTIFS(secondary_acts!$A$2:$A$771,$A76,secondary_acts!$E$2:$E$771,"delegated") -> 0 | AM76: =COUNTIFS(secondary_acts!$A$2:$A$771,$A76,secondary_acts!$E$2:$E$771,"other Commission/Council act") -> 0 | AN76: =COUNTIFS(secondary_acts!$A$2:$A$771,$A76,secondary_acts!$E$2:$E$771,"guidance") -> 0 | AO76: =COUNTIF(guidance_web!$A$2:$A$7,$A76) -> 0 | AP76: =COUNTIFS(guidance_agencies!$A$2:$A$81,$A76,guidance_agencies!$D$2:$D$81,"EDPB") -> 0 | AQ76: =COUNTIFS(guidance_agencies!$A$2:$A$81,$A76,guidance_agencies!$D$2:$D$81,"EBA") -> 0 | AR76: =COUNTIFS(guidance_agencies!$A$2:$A$81,$A76,guidance_agencies!$D$2:$D$81,"ESMA") -> 0 | AS76: =SUMIFS(secondary_acts!$S$2:$S$771,secondary_acts!$A$2:$A$771,$A76,secondary_acts!$E$2:$E$771,"implementing")+SUMIFS(secondary_acts!$S$2:$S$771,secondary_acts!$A$2:$A$771,$A76,secondary_acts!$E$2:$E$771,"delegated") -> 16 | AV76: 0 | AY76: 0 | AZ76: 52022PC0057 | BA76: EUR-Lex HTML | BB76: 15371 | BC76: 133 | BD76: 10 | BE76: =IF(ISNUMBER(BB76),Q76-BB76,"") -> 4454 | BF76: =IF(AND(ISNUMBER(BB76),BB76>0),(Q76-BB76)/BB76,"") -> 0.28976644 | BG76: =IF(ISNUMBER(BC76),X76-BC76,"") -> 41 | BH76: =IF(AND(ISNUMBER(BC76),BC76>0),(X76-BC76)/BC76,"") -> 0.30827068 | BI76: =IF(ISNUMBER(BD76),AD76-BD76,"") -> 0
A77: 76 | B77: Data Act | C77: Regulation (EU) 2023/2854 | D77: Data & Privacy | E77: enacted | F77: 2022-02-23 | G77: high | H77: 2023-12-13 | I77: 2023-12-22 | J77: 2024-01-11 | K77: adopted | L77: adopted | M77: 32023R2854 | N77: Original act as published in the OJ | O77: https://eur-lex.europa.eu/legal-content/EN/TXT/?uri=CELEX:32023R2854 | P77: 71 | Q77: 44522 | R77: 22506 | S77: 22355 | T77: 22016 | U77: 0 | V77: 0 | W77: 0 | X77: 264 | Y77: 216 | Z77: 37 | AA77: 2 | AB77: 5 | AC77: 4 | AD77: 110 | AE77: 44 | AF77: 56 | AG77: 54 | AH77: 02023R2854-20231222 | AI77: 264 | AJ77: 110 | AK77: =COUNTIFS(secondary_acts!$A$2:$A$771,$A77,secondary_acts!$E$2:$E$771,"implementing") -> 0 | AL77: =COUNTIFS(secondary_acts!$A$2:$A$771,$A77,secondary_acts!$E$2:$E$771,"delegated") -> 0 | AM77: =COUNTIFS(secondary_acts!$A$2:$A$771,$A77,secondary_acts!$E$2:$E$771,"other Commission/Council act") -> 0 | AN77: =COUNTIFS(secondary_acts!$A$2:$A$771,$A77,secondary_acts!$E$2:$E$771,"guidance") -> 1 | AO77: =COUNTIF(guidance_web!$A$2:$A$7,$A77) -> 0 | AP77: =COUNTIFS(guidance_agencies!$A$2:$A$81,$A77,guidance_agencies!$D$2:$D$81,"EDPB") -> 0 | AQ77: =COUNTIFS(guidance_agencies!$A$2:$A$81,$A77,guidance_agencies!$D$2:$D$81,"EBA") -> 0 | AR77: =COUNTIFS(guidance_agencies!$A$2:$A$81,$A77,guidance_agencies!$D$2:$D$81,"ESMA") -> 0 | AS77: =SUMIFS(secondary_acts!$S$2:$S$771,secondary_acts!$A$2:$A$771,$A77,secondary_acts!$E$2:$E$771,"implementing")+SUMIFS(secondary_acts!$S$2:$S$771,secondary_acts!$A$2:$A$771,$A77,secondary_acts!$E$2:$E$771,"delegated") -> 0 | AV77: 0 | AY77: 6 | AZ77: 52022PC0068 | BA77: EUR-Lex HTML | BB77: 23623 | BC77: 150 | BD77: 58 | BE77: =IF(ISNUMBER(BB77),Q77-BB77,"") -> 20899 | BF77: =IF(AND(ISNUMBER(BB77),BB77>0),(Q77-BB77)/BB77,"") -> 0.88468865 | BG77: =IF(ISNUMBER(BC77),X77-BC77,"") -> 114 | BH77: =IF(AND(ISNUMBER(BC77),BC77>0),(X77-BC77)/BC77,"") -> 0.76 | BI77: =IF(ISNUMBER(BD77),AD77-BD77,"") -> 52 | BJ77: no consolidated text with amendments in EUR-Lex; consolidated count = original
A78: 77 | B78: Violence Against Women Directive | C78: Directive (EU) 2024/1385 | D78: Law Enforcement | E78: enacted | F78: 2022-03-08 | G78: high | H78: 2024-05-14 | I78: 2024-05-24 | J78: 2024-06-13 | K78: adopted | L78: adopted | M78: 32024L1385 | N78: Original act as published in the OJ | O78: https://eur-lex.europa.eu/legal-content/EN/TXT/?uri=CELEX:32024L1385 | P78: 36 | Q78: 21341 | R78: 10771 | S78: 10658 | T78: 10570 | U78: 0 | V78: 0 | W78: 0 | X78: 206 | Y78: 132 | Z78: 3 | AA78: 0 | AB78: 0 | AC78: 71 | AD78: 6 | AE78: 131 | AF78: 3 | AG78: 66 | AK78: =COUNTIFS(secondary_acts!$A$2:$A$771,$A78,secondary_acts!$E$2:$E$771,"implementing") -> 0 | AL78: =COUNTIFS(secondary_acts!$A$2:$A$771,$A78,secondary_acts!$E$2:$E$771,"delegated") -> 0 | AM78: =COUNTIFS(secondary_acts!$A$2:$A$771,$A78,secondary_acts!$E$2:$E$771,"other Commission/Council act") -> 0 | AN78: =COUNTIFS(secondary_acts!$A$2:$A$771,$A78,secondary_acts!$E$2:$E$771,"guidance") -> 0 | AO78: =COUNTIF(guidance_web!$A$2:$A$7,$A78) -> 0 | AP78: =COUNTIFS(guidance_agencies!$A$2:$A$81,$A78,guidance_agencies!$D$2:$D$81,"EDPB") -> 0 | AQ78: =COUNTIFS(guidance_agencies!$A$2:$A$81,$A78,guidance_agencies!$D$2:$D$81,"EBA") -> 0 | AR78: =COUNTIFS(guidance_agencies!$A$2:$A$81,$A78,guidance_agencies!$D$2:$D$81,"ESMA") -> 0 | AS78: =SUMIFS(secondary_acts!$S$2:$S$771,secondary_acts!$A$2:$A$771,$A78,secondary_acts!$E$2:$E$771,"implementing")+SUMIFS(secondary_acts!$S$2:$S$771,secondary_acts!$A$2:$A$771,$A78,secondary_acts!$E$2:$E$771,"delegated") -> 0 | AT78: 3503 | AU78: 4 | AV78: 0 | AY78: 0 | AZ78: 52022PC0105 | BA78: EUR-Lex HTML | BB78: 15874 | BC78: 187 | BD78: 3 | BE78: =IF(ISNUMBER(BB78),Q78-BB78,"") -> 5467 | BF78: =IF(AND(ISNUMBER(BB78),BB78>0),(Q78-BB78)/BB78,"") -> 0.34439965 | BG78: =IF(ISNUMBER(BC78),X78-BC78,"") -> 19 | BH78: =IF(AND(ISNUMBER(BC78),BC78>0),(X78-BC78)/BC78,"") -> 0.10160428 | BI78: =IF(ISNUMBER(BD78),AD78-BD78,"") -> 3
A79: 78 | B79: Cybersecurity Regulation (EU institutions) | C79: Regulation (EU) 2023/2841 | D79: Cybersecurity | E79: enacted | F79: 2022-03-22 | G79: high | H79: 2023-12-13 | I79: 2023-12-18 | J79: 2024-01-07 | K79: adopted | L79: adopted | M79: 32023R2841 | N79: Original act as published in the OJ | O79: https://eur-lex.europa.eu/legal-content/EN/TXT/?uri=CELEX:32023R2841 | P79: 27 | Q79: 14545 | R79: 5325 | S79: 5200 | T79: 9220 | U79: 0 | V79: 0 | W79: 0 | X79: 166 | Y79: 153 | Z79: 6 | AA79: 1 | AB79: 2 | AC79: 4 | AD79: 1 | AE79: 1 | AF79: 126 | AG79: 38 | AH79: 02023R2841-20231218 | AI79: 166 | AJ79: 1 | AK79: =COUNTIFS(secondary_acts!$A$2:$A$771,$A79,secondary_acts!$E$2:$E$771,"implementing") -> 0 | AL79: =COUNTIFS(secondary_acts!$A$2:$A$771,$A79,secondary_acts!$E$2:$E$771,"delegated") -> 0 | AM79: =COUNTIFS(secondary_acts!$A$2:$A$771,$A79,secondary_acts!$E$2:$E$771,"other Commission/Council act") -> 0 | AN79: =COUNTIFS(secondary_acts!$A$2:$A$771,$A79,secondary_acts!$E$2:$E$771,"guidance") -> 0 | AO79: =COUNTIF(guidance_web!$A$2:$A$7,$A79) -> 0 | AP79: =COUNTIFS(guidance_agencies!$A$2:$A$81,$A79,guidance_agencies!$D$2:$D$81,"EDPB") -> 0 | AQ79: =COUNTIFS(guidance_agencies!$A$2:$A$81,$A79,guidance_agencies!$D$2:$D$81,"EBA") -> 0 | AR79: =COUNTIFS(guidance_agencies!$A$2:$A$81,$A79,guidance_agencies!$D$2:$D$81,"ESMA") -> 0 | AS79: =SUMIFS(secondary_acts!$S$2:$S$771,secondary_acts!$A$2:$A$771,$A79,secondary_acts!$E$2:$E$771,"implementing")+SUMIFS(secondary_acts!$S$2:$S$771,secondary_acts!$A$2:$A$771,$A79,secondary_acts!$E$2:$E$771,"delegated") -> 0 | AV79: 0 | AY79: 2 | AZ79: 52022PC0122 | BA79: EUR-Lex HTML | BB79: 7223 | BC79: 94 | BD79: 6 | BE79: =IF(ISNUMBER(BB79),Q79-BB79,"") -> 7322 | BF79: =IF(AND(ISNUMBER(BB79),BB79>0),(Q79-BB79)/BB79,"") -> 1.0137062 | BG79: =IF(ISNUMBER(BC79),X79-BC79,"") -> 72 | BH79: =IF(AND(ISNUMBER(BC79),BC79>0),(X79-BC79)/BC79,"") -> 0.76595745 | BI79: =IF(ISNUMBER(BD79),AD79-BD79,"") -> -5 | BJ79: no consolidated text with amendments in EUR-Lex; consolidated count = original
A80: 79 | B80: Information Security Regulation | C80: 2022/0084(COD) | D80: Cybersecurity | E80: proposal | F80: 2022-03-22 | G80: high | K80: proposed | L80: proposed | M80: 52022PC0119 | N80: Commission proposal (COM) | O80: https://eur-lex.europa.eu/legal-content/EN/TXT/?uri=CELEX:52022PC0119 | P80: 90 | Q80: 22121 | R80: 2056 | S80: 1958 | T80: 13090 | U80: 6975 | V80: 3755 | W80: 4388 | X80: 398 | Y80: 364 | Z80: 19 | AA80: 5 | AB80: 2 | AC80: 8 | AD80: 30 | AE80: 15 | AF80: 163 | AG80: 190 | AK80: =COUNTIFS(secondary_acts!$A$2:$A$771,$A80,secondary_acts!$E$2:$E$771,"implementing") -> 0 | AL80: =COUNTIFS(secondary_acts!$A$2:$A$771,$A80,secondary_acts!$E$2:$E$771,"delegated") -> 0 | AM80: =COUNTIFS(secondary_acts!$A$2:$A$771,$A80,secondary_acts!$E$2:$E$771,"other Commission/Council act") -> 0 | AN80: =COUNTIFS(secondary_acts!$A$2:$A$771,$A80,secondary_acts!$E$2:$E$771,"guidance") -> 0 | AO80: =COUNTIF(guidance_web!$A$2:$A$7,$A80) -> 0 | AP80: =COUNTIFS(guidance_agencies!$A$2:$A$81,$A80,guidance_agencies!$D$2:$D$81,"EDPB") -> 0 | AQ80: =COUNTIFS(guidance_agencies!$A$2:$A$81,$A80,guidance_agencies!$D$2:$D$81,"EBA") -> 0 | AR80: =COUNTIFS(guidance_agencies!$A$2:$A$81,$A80,guidance_agencies!$D$2:$D$81,"ESMA") -> 0 | AS80: =SUMIFS(secondary_acts!$S$2:$S$771,secondary_acts!$A$2:$A$771,$A80,secondary_acts!$E$2:$E$771,"implementing")+SUMIFS(secondary_acts!$S$2:$S$771,secondary_acts!$A$2:$A$771,$A80,secondary_acts!$E$2:$E$771,"delegated") -> 0 | BA80: row is itself a proposal | BE80: =IF(ISNUMBER(BB80),Q80-BB80,"") | BF80: =IF(AND(ISNUMBER(BB80),BB80>0),(Q80-BB80)/BB80,"") | BG80: =IF(ISNUMBER(BC80),X80-BC80,"") | BH80: =IF(AND(ISNUMBER(BC80),BC80>0),(X80-BC80)/BC80,"") | BI80: =IF(ISNUMBER(BD80),AD80-BD80,"")
A81: 80 | B81: Ecodesign for Sustainable Products Regulation | C81: Regulation (EU) 2024/1781 | D81: Trust & Safety | E81: enacted | F81: 2022-03-30 | G81: high | H81: 2024-06-13 | I81: 2024-06-28 | J81: 2024-07-18 | K81: adopted | L81: adopted | M81: 32024R1781 | N81: Original act as published in the OJ | O81: https://eur-lex.europa.eu/legal-content/EN/TXT/?uri=CELEX:32024R1781 | P81: 89 | Q81: 49096 | R81: 18418 | S81: 18286 | T81: 27289 | U81: 3389 | V81: 0 | W81: 0 | X81: 466 | Y81: 395 | Z81: 34 | AA81: 6 | AB81: 4 | AC81: 27 | AD81: 116 | AE81: 58 | AF81: 149 | AG81: 143 | AH81: 02024R1781-20240628 | AI81: 466 | AJ81: 116 | AK81: =COUNTIFS(secondary_acts!$A$2:$A$771,$A81,secondary_acts!$E$2:$E$771,"implementing") -> 2 | AL81: =COUNTIFS(secondary_acts!$A$2:$A$771,$A81,secondary_acts!$E$2:$E$771,"delegated") -> 1 | AM81: =COUNTIFS(secondary_acts!$A$2:$A$771,$A81,secondary_acts!$E$2:$E$771,"other Commission/Council act") -> 0 | AN81: =COUNTIFS(secondary_acts!$A$2:$A$771,$A81,secondary_acts!$E$2:$E$771,"guidance") -> 0 | AO81: =COUNTIF(guidance_web!$A$2:$A$7,$A81) -> 0 | AP81: =COUNTIFS(guidance_agencies!$A$2:$A$81,$A81,guidance_agencies!$D$2:$D$81,"EDPB") -> 0 | AQ81: =COUNTIFS(guidance_agencies!$A$2:$A$81,$A81,guidance_agencies!$D$2:$D$81,"EBA") -> 0 | AR81: =COUNTIFS(guidance_agencies!$A$2:$A$81,$A81,guidance_agencies!$D$2:$D$81,"ESMA") -> 0 | AS81: =SUMIFS(secondary_acts!$S$2:$S$771,secondary_acts!$A$2:$A$771,$A81,secondary_acts!$E$2:$E$771,"implementing")+SUMIFS(secondary_acts!$S$2:$S$771,secondary_acts!$A$2:$A$771,$A81,secondary_acts!$E$2:$E$771,"delegated") -> 145 | AV81: 0 | AY81: 4 | AZ81: 52022PC0142 | BA81: EUR-Lex HTML | BB81: 38936 | BC81: 474 | BD81: 117 | BE81: =IF(ISNUMBER(BB81),Q81-BB81,"") -> 10160 | BF81: =IF(AND(ISNUMBER(BB81),BB81>0),(Q81-BB81)/BB81,"") -> 0.26094103 | BG81: =IF(ISNUMBER(BC81),X81-BC81,"") -> -8 | BH81: =IF(AND(ISNUMBER(BC81),BC81>0),(X81-BC81)/BC81,"") -> -0.016877637 | BI81: =IF(ISNUMBER(BD81),AD81-BD81,"") -> -1
A82: 81 | B82: European Health Data Space | C82: Regulation (EU) 2025/327 | D82: Data & Privacy | E82: enacted | F82: 2022-05-03 | G82: high | H82: 2025-02-11 | I82: 2025-03-05 | J82: 2025-03-25 | K82: adopted | L82: adopted | M82: 32025R0327 | N82: Original act as published in the OJ | O82: https://eur-lex.europa.eu/legal-content/EN/TXT/?uri=CELEX:32025R0327 | P82: 96 | Q82: 59369 | R82: 22349 | S82: 22214 | T82: 35353 | U82: 1667 | V82: 0 | W82: 0 | X82: 609 | Y82: 541 | Z82: 26 | AA82: 6 | AB82: 4 | AC82: 32 | AD82: 164 | AE82: 128 | AF82: 140 | AG82: 177 | AH82: 02025R0327-20250305 | AI82: 609 | AJ82: 164 | AK82: =COUNTIFS(secondary_acts!$A$2:$A$771,$A82,secondary_acts!$E$2:$E$771,"implementing") -> 4 | AL82: =COUNTIFS(secondary_acts!$A$2:$A$771,$A82,secondary_acts!$E$2:$E$771,"delegated") -> 0 | AM82: =COUNTIFS(secondary_acts!$A$2:$A$771,$A82,secondary_acts!$E$2:$E$771,"other Commission/Council act") -> 0 | AN82: =COUNTIFS(secondary_acts!$A$2:$A$771,$A82,secondary_acts!$E$2:$E$771,"guidance") -> 0 | AO82: =COUNTIF(guidance_web!$A$2:$A$7,$A82) -> 0 | AP82: =COUNTIFS(guidance_agencies!$A$2:$A$81,$A82,guidance_agencies!$D$2:$D$81,"EDPB") -> 0 | AQ82: =COUNTIFS(guidance_agencies!$A$2:$A$81,$A82,guidance_agencies!$D$2:$D$81,"EBA") -> 0 | AR82: =COUNTIFS(guidance_agencies!$A$2:$A$81,$A82,guidance_agencies!$D$2:$D$81,"ESMA") -> 0 | AS82: =SUMIFS(secondary_acts!$S$2:$S$771,secondary_acts!$A$2:$A$771,$A82,secondary_acts!$E$2:$E$771,"implementing")+SUMIFS(secondary_acts!$S$2:$S$771,secondary_acts!$A$2:$A$771,$A82,secondary_acts!$E$2:$E$771,"delegated") -> 144 | AV82: 0 | AY82: 3 | AZ82: 52022PC0197 | BA82: EUR-Lex HTML | BB82: 37113 | BC82: 398 | BD82: 91 | BE82: =IF(ISNUMBER(BB82),Q82-BB82,"") -> 22256 | BF82: =IF(AND(ISNUMBER(BB82),BB82>0),(Q82-BB82)/BB82,"") -> 0.59968205 | BG82: =IF(ISNUMBER(BC82),X82-BC82,"") -> 211 | BH82: =IF(AND(ISNUMBER(BC82),BC82>0),(X82-BC82)/BC82,"") -> 0.53015075 | BI82: =IF(ISNUMBER(BD82),AD82-BD82,"") -> 73 | BJ82: no consolidated text with amendments in EUR-Lex; consolidated count = original
A83: 82 | B83: Child Sexual Abuse Regulation (CSAR) | C83: 2022/0155(COD) | D83: Law Enforcement | E83: proposal (listed in the cell of its enacted predecessor) | F83: 2022-05-11 | G83: high | K83: proposed | L83: proposed | M83: 52022PC0209 | N83: Commission proposal (COM) | O83: https://eur-lex.europa.eu/legal-content/EN/TXT/?uri=CELEX:52022PC0209 | P83: 156 | Q83: 41850 | R83: 9755 | S83: 9630 | T83: 28710 | U83: 3385 | V83: 10245 | W83: 8749 | X83: 467 | Y83: 410 | Z83: 20 | AA83: 5 | AB83: 5 | AC83: 27 | AD83: 67 | AE83: 124 | AF83: 125 | AG83: 151 | AK83: =COUNTIFS(secondary_acts!$A$2:$A$771,$A83,secondary_acts!$E$2:$E$771,"implementing") -> 0 | AL83: =COUNTIFS(secondary_acts!$A$2:$A$771,$A83,secondary_acts!$E$2:$E$771,"delegated") -> 0 | AM83: =COUNTIFS(secondary_acts!$A$2:$A$771,$A83,secondary_acts!$E$2:$E$771,"other Commission/Council act") -> 0 | AN83: =COUNTIFS(secondary_acts!$A$2:$A$771,$A83,secondary_acts!$E$2:$E$771,"guidance") -> 0 | AO83: =COUNTIF(guidance_web!$A$2:$A$7,$A83) -> 0 | AP83: =COUNTIFS(guidance_agencies!$A$2:$A$81,$A83,guidance_agencies!$D$2:$D$81,"EDPB") -> 0 | AQ83: =COUNTIFS(guidance_agencies!$A$2:$A$81,$A83,guidance_agencies!$D$2:$D$81,"EBA") -> 0 | AR83: =COUNTIFS(guidance_agencies!$A$2:$A$81,$A83,guidance_agencies!$D$2:$D$81,"ESMA") -> 0 | AS83: =SUMIFS(secondary_acts!$S$2:$S$771,secondary_acts!$A$2:$A$771,$A83,secondary_acts!$E$2:$E$771,"implementing")+SUMIFS(secondary_acts!$S$2:$S$771,secondary_acts!$A$2:$A$771,$A83,secondary_acts!$E$2:$E$771,"delegated") -> 0 | BA83: row is itself a proposal | BE83: =IF(ISNUMBER(BB83),Q83-BB83,"") | BF83: =IF(AND(ISNUMBER(BB83),BB83>0),(Q83-BB83)/BB83,"") | BG83: =IF(ISNUMBER(BC83),X83-BC83,"") | BH83: =IF(AND(ISNUMBER(BC83),BC83>0),(X83-BC83)/BC83,"") | BI83: =IF(ISNUMBER(BD83),AD83-BD83,"")
A84: 83 | B84: Cyber Resilience Act | C84: Regulation (EU) 2024/2847 | D84: Cybersecurity | E84: enacted | F84: 2022-09-15 | G84: high | H84: 2024-10-23 | I84: 2024-11-20 | J84: 2024-12-10 | K84: adopted | L84: adopted | M84: 32024R2847 | N84: Original act as published in the OJ | O84: https://eur-lex.europa.eu/legal-content/EN/TXT/?uri=CELEX:32024R2847 | P84: 81 | Q84: 51049 | R84: 21364 | S84: 21224 | T84: 23872 | U84: 5813 | V84: 0 | W84: 0 | X84: 501 | Y84: 451 | Z84: 18 | AA84: 2 | AB84: 3 | AC84: 27 | AD84: 183 | AE84: 90 | AF84: 102 | AG84: 126 | AH84: 02024R2847-20241120 | AI84: 501 | AJ84: 183 | AK84: =COUNTIFS(secondary_acts!$A$2:$A$771,$A84,secondary_acts!$E$2:$E$771,"implementing") -> 1 | AL84: =COUNTIFS(secondary_acts!$A$2:$A$771,$A84,secondary_acts!$E$2:$E$771,"delegated") -> 2 | AM84: =COUNTIFS(secondary_acts!$A$2:$A$771,$A84,secondary_acts!$E$2:$E$771,"other Commission/Council act") -> 0 | AN84: =COUNTIFS(secondary_acts!$A$2:$A$771,$A84,secondary_acts!$E$2:$E$771,"guidance") -> 0 | AO84: =COUNTIF(guidance_web!$A$2:$A$7,$A84) -> 2 | AP84: =COUNTIFS(guidance_agencies!$A$2:$A$81,$A84,guidance_agencies!$D$2:$D$81,"EDPB") -> 0 | AQ84: =COUNTIFS(guidance_agencies!$A$2:$A$81,$A84,guidance_agencies!$D$2:$D$81,"EBA") -> 0 | AR84: =COUNTIFS(guidance_agencies!$A$2:$A$81,$A84,guidance_agencies!$D$2:$D$81,"ESMA") -> 0 | AS84: =SUMIFS(secondary_acts!$S$2:$S$771,secondary_acts!$A$2:$A$771,$A84,secondary_acts!$E$2:$E$771,"implementing")+SUMIFS(secondary_acts!$S$2:$S$771,secondary_acts!$A$2:$A$771,$A84,secondary_acts!$E$2:$E$771,"delegated") -> 7 | AV84: 1 | AW84: 2025-02-11 | AX84: 2025-02-11 | AY84: 8 | AZ84: 52022PC0454 | BA84: EUR-Lex HTML | BB84: 30753 | BC84: 356 | BD84: 140 | BE84: =IF(ISNUMBER(BB84),Q84-BB84,"") -> 20296 | BF84: =IF(AND(ISNUMBER(BB84),BB84>0),(Q84-BB84)/BB84,"") -> 0.65996813 | BG84: =IF(ISNUMBER(BC84),X84-BC84,"") -> 145 | BH84: =IF(AND(ISNUMBER(BC84),BC84>0),(X84-BC84)/BC84,"") -> 0.40730337 | BI84: =IF(ISNUMBER(BD84),AD84-BD84,"") -> 43
A85: 84 | B85: European Media Freedom Act | C85: Regulation (EU) 2024/1083 | D85: Media | E85: enacted | F85: 2022-09-16 | G85: high | H85: 2024-04-11 | I85: 2024-04-17 | J85: 2024-05-07 | K85: adopted | L85: adopted | M85: 32024R1083 | N85: Original act as published in the OJ | O85: https://eur-lex.europa.eu/legal-content/EN/TXT/?uri=CELEX:32024R1083 | P85: 37 | Q85: 26160 | R85: 16599 | S85: 16462 | T85: 9561 | U85: 0 | V85: 0 | W85: 0 | X85: 153 | Y85: 131 | Z85: 3 | AA85: 1 | AB85: 1 | AC85: 17 | AD85: 24 | AE85: 48 | AF85: 63 | AG85: 18 | AH85: 02024R1083-20240417 | AI85: 153 | AJ85: 24 | AK85: =COUNTIFS(secondary_acts!$A$2:$A$771,$A85,secondary_acts!$E$2:$E$771,"implementing") -> 0 | AL85: =COUNTIFS(secondary_acts!$A$2:$A$771,$A85,secondary_acts!$E$2:$E$771,"delegated") -> 0 | AM85: =COUNTIFS(secondary_acts!$A$2:$A$771,$A85,secondary_acts!$E$2:$E$771,"other Commission/Council act") -> 0 | AN85: =COUNTIFS(secondary_acts!$A$2:$A$771,$A85,secondary_acts!$E$2:$E$771,"guidance") -> 1 | AO85: =COUNTIF(guidance_web!$A$2:$A$7,$A85) -> 0 | AP85: =COUNTIFS(guidance_agencies!$A$2:$A$81,$A85,guidance_agencies!$D$2:$D$81,"EDPB") -> 0 | AQ85: =COUNTIFS(guidance_agencies!$A$2:$A$81,$A85,guidance_agencies!$D$2:$D$81,"EBA") -> 0 | AR85: =COUNTIFS(guidance_agencies!$A$2:$A$81,$A85,guidance_agencies!$D$2:$D$81,"ESMA") -> 0 | AS85: =SUMIFS(secondary_acts!$S$2:$S$771,secondary_acts!$A$2:$A$771,$A85,secondary_acts!$E$2:$E$771,"implementing")+SUMIFS(secondary_acts!$S$2:$S$771,secondary_acts!$A$2:$A$771,$A85,secondary_acts!$E$2:$E$771,"delegated") -> 0 | AV85: 0 | AY85: 4 | AZ85: 52022PC0457 | BA85: EUR-Lex HTML | BB85: 14840 | BC85: 108 | BD85: 13 | BE85: =IF(ISNUMBER(BB85),Q85-BB85,"") -> 11320 | BF85: =IF(AND(ISNUMBER(BB85),BB85>0),(Q85-BB85)/BB85,"") -> 0.76280323 | BG85: =IF(ISNUMBER(BC85),X85-BC85,"") -> 45 | BH85: =IF(AND(ISNUMBER(BC85),BC85>0),(X85-BC85)/BC85,"") -> 0.41666667 | BI85: =IF(ISNUMBER(BD85),AD85-BD85,"") -> 11 | BJ85: no consolidated text with amendments in EUR-Lex; consolidated count = original
A86: 85 | B86: Single Market Emergency Instrument (IMERA) | C86: Regulation (EU) 2024/2747 | D86: Competition & Single Market | E86: enacted | F86: 2022-09-19 | G86: high | H86: 2024-10-09 | I86: 2024-11-08 | J86: 2024-11-28 | K86: adopted | L86: adopted | M86: 32024R2747 | N86: Original act as published in the OJ | O86: https://eur-lex.europa.eu/legal-content/EN/TXT/?uri=CELEX:32024R2747 | P86: 43 | Q86: 24374 | R86: 10138 | S86: 9986 | T86: 14236 | U86: 0 | V86: 0 | W86: 0 | X86: 204 | Y86: 172 | Z86: 15 | AA86: 2 | AB86: 1 | AC86: 14 | AD86: 8 | AE86: 33 | AF86: 127 | AG86: 36 | AH86: 02024R2747-20241108 | AI86: 204 | AJ86: 8 | AK86: =COUNTIFS(secondary_acts!$A$2:$A$771,$A86,secondary_acts!$E$2:$E$771,"implementing") -> 0 | AL86: =COUNTIFS(secondary_acts!$A$2:$A$771,$A86,secondary_acts!$E$2:$E$771,"delegated") -> 0 | AM86: =COUNTIFS(secondary_acts!$A$2:$A$771,$A86,secondary_acts!$E$2:$E$771,"other Commission/Council act") -> 0 | AN86: =COUNTIFS(secondary_acts!$A$2:$A$771,$A86,secondary_acts!$E$2:$E$771,"guidance") -> 0 | AO86: =COUNTIF(guidance_web!$A$2:$A$7,$A86) -> 0 | AP86: =COUNTIFS(guidance_agencies!$A$2:$A$81,$A86,guidance_agencies!$D$2:$D$81,"EDPB") -> 0 | AQ86: =COUNTIFS(guidance_agencies!$A$2:$A$81,$A86,guidance_agencies!$D$2:$D$81,"EBA") -> 0 | AR86: =COUNTIFS(guidance_agencies!$A$2:$A$81,$A86,guidance_agencies!$D$2:$D$81,"ESMA") -> 0 | AS86: =SUMIFS(secondary_acts!$S$2:$S$771,secondary_acts!$A$2:$A$771,$A86,secondary_acts!$E$2:$E$771,"implementing")+SUMIFS(secondary_acts!$S$2:$S$771,secondary_acts!$A$2:$A$771,$A86,secondary_acts!$E$2:$E$771,"delegated") -> 0 | AV86: 0 | AY86: 2 | AZ86: 52022PC0459 | BA86: EUR-Lex HTML | BB86: 16426 | BC86: 191 | BD86: 7 | BE86: =IF(ISNUMBER(BB86),Q86-BB86,"") -> 7948 | BF86: =IF(AND(ISNUMBER(BB86),BB86>0),(Q86-BB86)/BB86,"") -> 0.48386704 | BG86: =IF(ISNUMBER(BC86),X86-BC86,"") -> 13 | BH86: =IF(AND(ISNUMBER(BC86),BC86>0),(X86-BC86)/BC86,"") -> 0.068062827 | BI86: =IF(ISNUMBER(BD86),AD86-BD86,"") -> 1 | BJ86: no consolidated text with amendments in EUR-Lex; consolidated count = original
A87: 86 | B87: Product Liability Directive | C87: Directive (EU) 2024/2853 | D87: Trust & Safety | E87: enacted | F87: 2022-09-28 | G87: high | H87: 2024-10-23 | I87: 2024-11-18 | J87: 2024-12-08 | K87: adopted | L87: adopted | M87: 32024L2853 | N87: Original act as published in the OJ | O87: https://eur-lex.europa.eu/legal-content/EN/TXT/?uri=CELEX:32024L2853 | P87: 22 | Q87: 13026 | R87: 8269 | S87: 8153 | T87: 4486 | U87: 271 | V87: 0 | W87: 0 | X87: 46 | Y87: 24 | Z87: 4 | AA87: 0 | AB87: 2 | AC87: 16 | AD87: 5 | AE87: 30 | AF87: 4 | AG87: 7 | AH87: 02024L2853-20241118 | AI87: 46 | AJ87: 5 | AK87: =COUNTIFS(secondary_acts!$A$2:$A$771,$A87,secondary_acts!$E$2:$E$771,"implementing") -> 0 | AL87: =COUNTIFS(secondary_acts!$A$2:$A$771,$A87,secondary_acts!$E$2:$E$771,"delegated") -> 0 | AM87: =COUNTIFS(secondary_acts!$A$2:$A$771,$A87,secondary_acts!$E$2:$E$771,"other Commission/Council act") -> 0 | AN87: =COUNTIFS(secondary_acts!$A$2:$A$771,$A87,secondary_acts!$E$2:$E$771,"guidance") -> 0 | AO87: =COUNTIF(guidance_web!$A$2:$A$7,$A87) -> 0 | AP87: =COUNTIFS(guidance_agencies!$A$2:$A$81,$A87,guidance_agencies!$D$2:$D$81,"EDPB") -> 0 | AQ87: =COUNTIFS(guidance_agencies!$A$2:$A$81,$A87,guidance_agencies!$D$2:$D$81,"EBA") -> 0 | AR87: =COUNTIFS(guidance_agencies!$A$2:$A$81,$A87,guidance_agencies!$D$2:$D$81,"ESMA") -> 0 | AS87: =SUMIFS(secondary_acts!$S$2:$S$771,secondary_acts!$A$2:$A$771,$A87,secondary_acts!$E$2:$E$771,"implementing")+SUMIFS(secondary_acts!$S$2:$S$771,secondary_acts!$A$2:$A$771,$A87,secondary_acts!$E$2:$E$771,"delegated") -> 0 | AT87: 80 | AU87: 2 | AV87: 0 | AY87: 2 | AZ87: 52022PC0495 | BA87: EUR-Lex HTML | BB87: 8628 | BC87: 32 | BD87: 2 | BE87: =IF(ISNUMBER(BB87),Q87-BB87,"") -> 4398 | BF87: =IF(AND(ISNUMBER(BB87),BB87>0),(Q87-BB87)/BB87,"") -> 0.50973574 | BG87: =IF(ISNUMBER(BC87),X87-BC87,"") -> 14 | BH87: =IF(AND(ISNUMBER(BC87),BC87>0),(X87-BC87)/BC87,"") -> 0.4375 | BI87: =IF(ISNUMBER(BD87),AD87-BD87,"") -> 3
A88: 87 | B88: Horizontal Block Exemption Regulations | C88: Regulations (EU) 2023/1066, 2023/1067 | D88: Competition & Single Market | E88: enacted | F88: 2022-03-01 | G88: low | H88: 2023-06-01 | I88: 2023-06-02 | J88: 2023-07-01 | K88: adopted | L88: adopted | M88: 32023R1066;32023R1067 | N88: Original act as published in the OJ | O88: https://eur-lex.europa.eu/legal-content/EN/TXT/?uri=CELEX:32023R1066 ; https://eur-lex.europa.eu/legal-content/EN/TXT/?uri=CELEX:32023R1067 | P88: 18 | Q88: 8700 | R88: 3248 | S88: 2996 | T88: 5452 | U88: 0 | V88: 0 | W88: 0 | X88: 12 | Y88: 5 | Z88: 2 | AA88: 0 | AB88: 5 | AC88: 0 | AD88: 2 | AE88: 0 | AF88: 0 | AG88: 10 | AH88: 02023R1066-20230602;02023R1067-20230602 | AI88: 12 | AJ88: 2 | AK88: =COUNTIFS(secondary_acts!$A$2:$A$771,$A88,secondary_acts!$E$2:$E$771,"implementing") -> 0 | AL88: =COUNTIFS(secondary_acts!$A$2:$A$771,$A88,secondary_acts!$E$2:$E$771,"delegated") -> 0 | AM88: =COUNTIFS(secondary_acts!$A$2:$A$771,$A88,secondary_acts!$E$2:$E$771,"other Commission/Council act") -> 0 | AN88: =COUNTIFS(secondary_acts!$A$2:$A$771,$A88,secondary_acts!$E$2:$E$771,"guidance") -> 0 | AO88: =COUNTIF(guidance_web!$A$2:$A$7,$A88) -> 0 | AP88: =COUNTIFS(guidance_agencies!$A$2:$A$81,$A88,guidance_agencies!$D$2:$D$81,"EDPB") -> 0 | AQ88: =COUNTIFS(guidance_agencies!$A$2:$A$81,$A88,guidance_agencies!$D$2:$D$81,"EBA") -> 0 | AR88: =COUNTIFS(guidance_agencies!$A$2:$A$81,$A88,guidance_agencies!$D$2:$D$81,"ESMA") -> 0 | AS88: =SUMIFS(secondary_acts!$S$2:$S$771,secondary_acts!$A$2:$A$771,$A88,secondary_acts!$E$2:$E$771,"implementing")+SUMIFS(secondary_acts!$S$2:$S$771,secondary_acts!$A$2:$A$771,$A88,secondary_acts!$E$2:$E$771,"delegated") -> 0 | AV88: 0 | AY88: 2 | BA88: no legislative proposal (Commission act) | BE88: =IF(ISNUMBER(BB88),Q88-BB88,"") | BF88: =IF(AND(ISNUMBER(BB88),BB88>0),(Q88-BB88)/BB88,"") | BG88: =IF(ISNUMBER(BC88),X88-BC88,"") | BH88: =IF(AND(ISNUMBER(BC88),BC88>0),(X88-BC88)/BC88,"") | BI88: =IF(ISNUMBER(BD88),AD88-BD88,"") | BJ88: Block exemption: defines a safe harbour ('the exemption shall not apply to...'), so few direct restrictions are counted; no consolidated text with amendments in EUR-Lex; consolidated count = original
A89: 88 | B89: Interoperable Europe Act | C89: Regulation (EU) 2024/903 | D89: Data & Privacy | E89: enacted | F89: 2022-11-18 | G89: high | H89: 2024-03-13 | I89: 2024-03-22 | J89: 2024-04-11 | K89: adopted | L89: adopted | M89: 32024R0903 | N89: Original act as published in the OJ | O89: https://eur-lex.europa.eu/legal-content/EN/TXT/?uri=CELEX:32024R0903 | P89: 26 | Q89: 13633 | R89: 6335 | S89: 6206 | T89: 7199 | U89: 99 | V89: 0 | W89: 0 | X89: 129 | Y89: 116 | Z89: 8 | AA89: 0 | AB89: 1 | AC89: 4 | AD89: 6 | AE89: 14 | AF89: 66 | AG89: 43 | AK89: =COUNTIFS(secondary_acts!$A$2:$A$771,$A89,secondary_acts!$E$2:$E$771,"implementing") -> 1 | AL89: =COUNTIFS(secondary_acts!$A$2:$A$771,$A89,secondary_acts!$E$2:$E$771,"delegated") -> 0 | AM89: =COUNTIFS(secondary_acts!$A$2:$A$771,$A89,secondary_acts!$E$2:$E$771,"other Commission/Council act") -> 0 | AN89: =COUNTIFS(secondary_acts!$A$2:$A$771,$A89,secondary_acts!$E$2:$E$771,"guidance") -> 0 | AO89: =COUNTIF(guidance_web!$A$2:$A$7,$A89) -> 0 | AP89: =COUNTIFS(guidance_agencies!$A$2:$A$81,$A89,guidance_agencies!$D$2:$D$81,"EDPB") -> 0 | AQ89: =COUNTIFS(guidance_agencies!$A$2:$A$81,$A89,guidance_agencies!$D$2:$D$81,"EBA") -> 0 | AR89: =COUNTIFS(guidance_agencies!$A$2:$A$81,$A89,guidance_agencies!$D$2:$D$81,"ESMA") -> 0 | AS89: =SUMIFS(secondary_acts!$S$2:$S$771,secondary_acts!$A$2:$A$771,$A89,secondary_acts!$E$2:$E$771,"implementing")+SUMIFS(secondary_acts!$S$2:$S$771,secondary_acts!$A$2:$A$771,$A89,secondary_acts!$E$2:$E$771,"delegated") -> 55 | AV89: 0 | AY89: 0 | AZ89: 52022PC0720 | BA89: EUR-Lex HTML | BB89: 9785 | BC89: 99 | BD89: 4 | BE89: =IF(ISNUMBER(BB89),Q89-BB89,"") -> 3848 | BF89: =IF(AND(ISNUMBER(BB89),BB89>0),(Q89-BB89)/BB89,"") -> 0.39325498 | BG89: =IF(ISNUMBER(BC89),X89-BC89,"") -> 30 | BH89: =IF(AND(ISNUMBER(BC89),BC89>0),(X89-BC89)/BC89,"") -> 0.3030303 | BI89: =IF(ISNUMBER(BD89),AD89-BD89,"") -> 2
A90: 89 | B90: Design Directive | C90: Directive (EU) 2024/2823 | D90: IPR | E90: enacted | F90: 2022-11-28 | G90: high | H90: 2024-10-23 | I90: 2024-11-18 | J90: 2024-12-08 | K90: adopted | L90: adopted | M90: 32024L2823 | N90: Original act as published in the OJ | O90: https://eur-lex.europa.eu/legal-content/EN/TXT/?uri=CELEX:32024L2823 | P90: 18 | Q90: 9716 | R90: 4254 | S90: 4142 | T90: 5241 | U90: 221 | V90: 0 | W90: 0 | X90: 69 | Y90: 55 | Z90: 14 | AA90: 0 | AB90: 0 | AC90: 0 | AD90: 4 | AE90: 12 | AF90: 4 | AG90: 49 | AH90: 02024L2823-20241118 | AI90: 69 | AJ90: 4 | AK90: =COUNTIFS(secondary_acts!$A$2:$A$771,$A90,secondary_acts!$E$2:$E$771,"implementing") -> 0 | AL90: =COUNTIFS(secondary_acts!$A$2:$A$771,$A90,secondary_acts!$E$2:$E$771,"delegated") -> 0 | AM90: =COUNTIFS(secondary_acts!$A$2:$A$771,$A90,secondary_acts!$E$2:$E$771,"other Commission/Council act") -> 0 | AN90: =COUNTIFS(secondary_acts!$A$2:$A$771,$A90,secondary_acts!$E$2:$E$771,"guidance") -> 0 | AO90: =COUNTIF(guidance_web!$A$2:$A$7,$A90) -> 0 | AP90: =COUNTIFS(guidance_agencies!$A$2:$A$81,$A90,guidance_agencies!$D$2:$D$81,"EDPB") -> 0 | AQ90: =COUNTIFS(guidance_agencies!$A$2:$A$81,$A90,guidance_agencies!$D$2:$D$81,"EBA") -> 0 | AR90: =COUNTIFS(guidance_agencies!$A$2:$A$81,$A90,guidance_agencies!$D$2:$D$81,"ESMA") -> 0 | AS90: =SUMIFS(secondary_acts!$S$2:$S$771,secondary_acts!$A$2:$A$771,$A90,secondary_acts!$E$2:$E$771,"implementing")+SUMIFS(secondary_acts!$S$2:$S$771,secondary_acts!$A$2:$A$771,$A90,secondary_acts!$E$2:$E$771,"delegated") -> 0 | AT90: 0 | AU90: 0 | AV90: 0 | AY90: 2 | AZ90: 52022PC0667 | BA90: EUR-Lex HTML | BB90: 10541 | BC90: 81 | BD90: 3 | BE90: =IF(ISNUMBER(BB90),Q90-BB90,"") -> -825 | BF90: =IF(AND(ISNUMBER(BB90),BB90>0),(Q90-BB90)/BB90,"") -> -0.078265819 | BG90: =IF(ISNUMBER(BC90),X90-BC90,"") -> -12 | BH90: =IF(AND(ISNUMBER(BC90),BC90>0),(X90-BC90)/BC90,"") -> -0.14814815 | BI90: =IF(ISNUMBER(BD90),AD90-BD90,"") -> 1 | BJ90: no consolidated text with amendments in EUR-Lex; consolidated count = original
A91: 90 | B91: VAT in the Digital Age (ViDA) | C91: 2022/0407(CNS) | D91: Finance | E91: proposal (listed in the cell of its enacted predecessor) | F91: 2022-12-08 | G91: high | H91: 2025-03-11 | I91: 2025-03-25 | J91: 2025-04-14 | K91: proposed | L91: adopted | M91: 32025L0516 | N91: Original act as published in the OJ | O91: https://eur-lex.europa.eu/legal-content/EN/TXT/?uri=CELEX:32025L0516 | P91: 28 | Q91: 16279 | R91: 4856 | S91: 4745 | T91: 11423 | U91: 0 | V91: 0 | W91: 0 | X91: 86 | Y91: 76 | Z91: 7 | AA91: 0 | AB91: 3 | AC91: 0 | AD91: 19 | AE91: 31 | AF91: 4 | AG91: 32 | AH91: 02025L0516-20250325 | AI91: 86 | AJ91: 19 | AK91: =COUNTIFS(secondary_acts!$A$2:$A$771,$A91,secondary_acts!$E$2:$E$771,"implementing") -> 0 | AL91: =COUNTIFS(secondary_acts!$A$2:$A$771,$A91,secondary_acts!$E$2:$E$771,"delegated") -> 0 | AM91: =COUNTIFS(secondary_acts!$A$2:$A$771,$A91,secondary_acts!$E$2:$E$771,"other Commission/Council act") -> 0 | AN91: =COUNTIFS(secondary_acts!$A$2:$A$771,$A91,secondary_acts!$E$2:$E$771,"guidance") -> 0 | AO91: =COUNTIF(guidance_web!$A$2:$A$7,$A91) -> 0 | AP91: =COUNTIFS(guidance_agencies!$A$2:$A$81,$A91,guidance_agencies!$D$2:$D$81,"EDPB") -> 0 | AQ91: =COUNTIFS(guidance_agencies!$A$2:$A$81,$A91,guidance_agencies!$D$2:$D$81,"EBA") -> 0 | AR91: =COUNTIFS(guidance_agencies!$A$2:$A$81,$A91,guidance_agencies!$D$2:$D$81,"ESMA") -> 0 | AS91: =SUMIFS(secondary_acts!$S$2:$S$771,secondary_acts!$A$2:$A$771,$A91,secondary_acts!$E$2:$E$771,"implementing")+SUMIFS(secondary_acts!$S$2:$S$771,secondary_acts!$A$2:$A$771,$A91,secondary_acts!$E$2:$E$771,"delegated") -> 0 | AT91: 87 | AU91: 5 | AV91: 0 | AY91: 1 | AZ91: 52022PC0701 | BA91: EUR-Lex HTML | BB91: 12271 | BC91: 59 | BD91: 8 | BE91: =IF(ISNUMBER(BB91),Q91-BB91,"") -> 4008 | BF91: =IF(AND(ISNUMBER(BB91),BB91>0),(Q91-BB91)/BB91,"") -> 0.32662375 | BG91: =IF(ISNUMBER(BC91),X91-BC91,"") -> 27 | BH91: =IF(AND(ISNUMBER(BC91),BC91>0),(X91-BC91)/BC91,"") -> 0.45762712 | BI91: =IF(ISNUMBER(BD91),AD91-BD91,"") -> 11 | BJ91: Adopted after CEPS snapshot: Council Directive (EU) 2025/516 (11 Mar 2025); no consolidated text with amendments in EUR-Lex; consolidated count = original
A92: 91 | B92: Gigabit Infrastructure Act | C92: Regulation (EU) 2024/1309 | D92: Connectivity | E92: enacted | F92: 2023-02-23 | G92: high | H92: 2024-04-29 | I92: 2024-05-08 | J92: 2024-05-11 | K92: adopted | L92: adopted | M92: 32024R1309 | N92: Original act as published in the OJ | O92: https://eur-lex.europa.eu/legal-content/EN/TXT/?uri=CELEX:32024R1309 | P92: 40 | Q92: 23456 | R92: 13087 | S92: 12957 | T92: 9868 | U92: 501 | V92: 0 | W92: 0 | X92: 114 | Y92: 89 | Z92: 12 | AA92: 2 | AB92: 2 | AC92: 9 | AD92: 13 | AE92: 57 | AF92: 5 | AG92: 39 | AH92: 02024R1309-20240508 | AI92: 114 | AJ92: 13 | AK92: =COUNTIFS(secondary_acts!$A$2:$A$771,$A92,secondary_acts!$E$2:$E$771,"implementing") -> 0 | AL92: =COUNTIFS(secondary_acts!$A$2:$A$771,$A92,secondary_acts!$E$2:$E$771,"delegated") -> 0 | AM92: =COUNTIFS(secondary_acts!$A$2:$A$771,$A92,secondary_acts!$E$2:$E$771,"other Commission/Council act") -> 0 | AN92: =COUNTIFS(secondary_acts!$A$2:$A$771,$A92,secondary_acts!$E$2:$E$771,"guidance") -> 0 | AO92: =COUNTIF(guidance_web!$A$2:$A$7,$A92) -> 0 | AP92: =COUNTIFS(guidance_agencies!$A$2:$A$81,$A92,guidance_agencies!$D$2:$D$81,"EDPB") -> 0 | AQ92: =COUNTIFS(guidance_agencies!$A$2:$A$81,$A92,guidance_agencies!$D$2:$D$81,"EBA") -> 0 | AR92: =COUNTIFS(guidance_agencies!$A$2:$A$81,$A92,guidance_agencies!$D$2:$D$81,"ESMA") -> 0 | AS92: =SUMIFS(secondary_acts!$S$2:$S$771,secondary_acts!$A$2:$A$771,$A92,secondary_acts!$E$2:$E$771,"implementing")+SUMIFS(secondary_acts!$S$2:$S$771,secondary_acts!$A$2:$A$771,$A92,secondary_acts!$E$2:$E$771,"delegated") -> 0 | AV92: 0 | AY92: 3 | AZ92: 52023PC0094 | BA92: EUR-Lex HTML | BB92: 15565 | BC92: 89 | BD92: 12 | BE92: =IF(ISNUMBER(BB92),Q92-BB92,"") -> 7891 | BF92: =IF(AND(ISNUMBER(BB92),BB92>0),(Q92-BB92)/BB92,"") -> 0.50697077 | BG92: =IF(ISNUMBER(BC92),X92-BC92,"") -> 25 | BH92: =IF(AND(ISNUMBER(BC92),BC92>0),(X92-BC92)/BC92,"") -> 0.28089888 | BI92: =IF(ISNUMBER(BD92),AD92-BD92,"") -> 1
A93: 92 | B93: Critical Raw Materials Act | C93: Regulation (EU) 2024/1252 | D93: Industrial Policy | E93: enacted | F93: 2023-03-16 | G93: high | H93: 2024-04-11 | I93: 2024-05-03 | J93: 2024-05-23 | K93: adopted | L93: adopted | M93: 32024R1252 | N93: Original act as published in the OJ | O93: https://eur-lex.europa.eu/legal-content/EN/TXT/?uri=CELEX:32024R1252 | P93: 67 | Q93: 37779 | R93: 11892 | S93: 11757 | T93: 21960 | U93: 3927 | V93: 0 | W93: 0 | X93: 364 | Y93: 317 | Z93: 20 | AA93: 0 | AB93: 6 | AC93: 21 | AD93: 34 | AE93: 76 | AF93: 137 | AG93: 117 | AH93: 02024R1252-20240503 | AI93: 365 | AJ93: 34 | AK93: =COUNTIFS(secondary_acts!$A$2:$A$771,$A93,secondary_acts!$E$2:$E$771,"implementing") -> 2 | AL93: =COUNTIFS(secondary_acts!$A$2:$A$771,$A93,secondary_acts!$E$2:$E$771,"delegated") -> 0 | AM93: =COUNTIFS(secondary_acts!$A$2:$A$771,$A93,secondary_acts!$E$2:$E$771,"other Commission/Council act") -> 0 | AN93: =COUNTIFS(secondary_acts!$A$2:$A$771,$A93,secondary_acts!$E$2:$E$771,"guidance") -> 0 | AO93: =COUNTIF(guidance_web!$A$2:$A$7,$A93) -> 0 | AP93: =COUNTIFS(guidance_agencies!$A$2:$A$81,$A93,guidance_agencies!$D$2:$D$81,"EDPB") -> 0 | AQ93: =COUNTIFS(guidance_agencies!$A$2:$A$81,$A93,guidance_agencies!$D$2:$D$81,"EBA") -> 0 | AR93: =COUNTIFS(guidance_agencies!$A$2:$A$81,$A93,guidance_agencies!$D$2:$D$81,"ESMA") -> 0 | AS93: =SUMIFS(secondary_acts!$S$2:$S$771,secondary_acts!$A$2:$A$771,$A93,secondary_acts!$E$2:$E$771,"implementing")+SUMIFS(secondary_acts!$S$2:$S$771,secondary_acts!$A$2:$A$771,$A93,secondary_acts!$E$2:$E$771,"delegated") -> 1 | AV93: 0 | AY93: 5 | AZ93: 52023PC0160 | BA93: EUR-Lex HTML | BB93: 29042 | BC93: 296 | BD93: 24 | BE93: =IF(ISNUMBER(BB93),Q93-BB93,"") -> 8737 | BF93: =IF(AND(ISNUMBER(BB93),BB93>0),(Q93-BB93)/BB93,"") -> 0.30084016 | BG93: =IF(ISNUMBER(BC93),X93-BC93,"") -> 68 | BH93: =IF(AND(ISNUMBER(BC93),BC93>0),(X93-BC93)/BC93,"") -> 0.22972973 | BI93: =IF(ISNUMBER(BD93),AD93-BD93,"") -> 10
A94: 93 | B94: Net-Zero Industry Act | C94: Regulation (EU) 2024/1735 | D94: Industrial Policy | E94: enacted | F94: 2023-03-16 | G94: high | H94: 2024-06-13 | I94: 2024-06-28 | J94: 2024-06-29 | K94: adopted | L94: adopted | M94: 32024R1735 | N94: Original act as published in the OJ | O94: https://eur-lex.europa.eu/legal-content/EN/TXT/?uri=CELEX:32024R1735 | P94: 63 | Q94: 37451 | R94: 17117 | S94: 16982 | T94: 20058 | U94: 276 | V94: 0 | W94: 0 | X94: 288 | Y94: 248 | Z94: 16 | AA94: 2 | AB94: 7 | AC94: 15 | AD94: 6 | AE94: 92 | AF94: 96 | AG94: 94 | AH94: 02024R1735-20250817 | AI94: 289 | AJ94: 6 | AK94: =COUNTIFS(secondary_acts!$A$2:$A$771,$A94,secondary_acts!$E$2:$E$771,"implementing") -> 4 | AL94: =COUNTIFS(secondary_acts!$A$2:$A$771,$A94,secondary_acts!$E$2:$E$771,"delegated") -> 2 | AM94: =COUNTIFS(secondary_acts!$A$2:$A$771,$A94,secondary_acts!$E$2:$E$771,"other Commission/Council act") -> 0 | AN94: =COUNTIFS(secondary_acts!$A$2:$A$771,$A94,secondary_acts!$E$2:$E$771,"guidance") -> 3 | AO94: =COUNTIF(guidance_web!$A$2:$A$7,$A94) -> 0 | AP94: =COUNTIFS(guidance_agencies!$A$2:$A$81,$A94,guidance_agencies!$D$2:$D$81,"EDPB") -> 0 | AQ94: =COUNTIFS(guidance_agencies!$A$2:$A$81,$A94,guidance_agencies!$D$2:$D$81,"EBA") -> 0 | AR94: =COUNTIFS(guidance_agencies!$A$2:$A$81,$A94,guidance_agencies!$D$2:$D$81,"ESMA") -> 0 | AS94: =SUMIFS(secondary_acts!$S$2:$S$771,secondary_acts!$A$2:$A$771,$A94,secondary_acts!$E$2:$E$771,"implementing")+SUMIFS(secondary_acts!$S$2:$S$771,secondary_acts!$A$2:$A$771,$A94,secondary_acts!$E$2:$E$771,"delegated") -> 88 | AV94: 1 | AW94: 2025-05-23 | AX94: 2025-05-23 | AY94: 4 | AZ94: 52023PC0161 | BA94: EUR-Lex HTML | BB94: 19871 | BC94: 153 | BD94: 9 | BE94: =IF(ISNUMBER(BB94),Q94-BB94,"") -> 17580 | BF94: =IF(AND(ISNUMBER(BB94),BB94>0),(Q94-BB94)/BB94,"") -> 0.88470636 | BG94: =IF(ISNUMBER(BC94),X94-BC94,"") -> 135 | BH94: =IF(AND(ISNUMBER(BC94),BC94>0),(X94-BC94)/BC94,"") -> 0.88235294 | BI94: =IF(ISNUMBER(BD94),AD94-BD94,"") -> -3
A95: 94 | B95: Right to Repair Directive | C95: Directive (EU) 2024/1799 | D95: E-commerce & Consumer Protection | E95: enacted | F95: 2023-03-22 | G95: high | H95: 2024-06-13 | I95: 2024-07-10 | J95: 2024-07-30 | K95: adopted | L95: adopted | M95: 32024L1799 | N95: Original act as published in the OJ | O95: https://eur-lex.europa.eu/legal-content/EN/TXT/?uri=CELEX:32024L1799 | P95: 20 | Q95: 11685 | R95: 6256 | S95: 6117 | T95: 4468 | U95: 961 | V95: 0 | W95: 0 | X95: 77 | Y95: 63 | Z95: 6 | AA95: 0 | AB95: 2 | AC95: 6 | AD95: 15 | AE95: 26 | AF95: 14 | AG95: 22 | AH95: 02024L1799-20260731 | AI95: 77 | AJ95: 15 | AK95: =COUNTIFS(secondary_acts!$A$2:$A$771,$A95,secondary_acts!$E$2:$E$771,"implementing") -> 0 | AL95: =COUNTIFS(secondary_acts!$A$2:$A$771,$A95,secondary_acts!$E$2:$E$771,"delegated") -> 1 | AM95: =COUNTIFS(secondary_acts!$A$2:$A$771,$A95,secondary_acts!$E$2:$E$771,"other Commission/Council act") -> 0 | AN95: =COUNTIFS(secondary_acts!$A$2:$A$771,$A95,secondary_acts!$E$2:$E$771,"guidance") -> 0 | AO95: =COUNTIF(guidance_web!$A$2:$A$7,$A95) -> 0 | AP95: =COUNTIFS(guidance_agencies!$A$2:$A$81,$A95,guidance_agencies!$D$2:$D$81,"EDPB") -> 0 | AQ95: =COUNTIFS(guidance_agencies!$A$2:$A$81,$A95,guidance_agencies!$D$2:$D$81,"EBA") -> 0 | AR95: =COUNTIFS(guidance_agencies!$A$2:$A$81,$A95,guidance_agencies!$D$2:$D$81,"ESMA") -> 0 | AS95: =SUMIFS(secondary_acts!$S$2:$S$771,secondary_acts!$A$2:$A$771,$A95,secondary_acts!$E$2:$E$771,"implementing")+SUMIFS(secondary_acts!$S$2:$S$771,secondary_acts!$A$2:$A$771,$A95,secondary_acts!$E$2:$E$771,"delegated") -> 5 | AT95: 387 | AU95: 11 | AV95: 1 | AW95: 2026-01-12 | AX95: 2026-01-12 | AY95: 3 | AZ95: 52023PC0155 | BA95: EUR-Lex HTML | BB95: 7869 | BC95: 42 | BD95: 6 | BE95: =IF(ISNUMBER(BB95),Q95-BB95,"") -> 3816 | BF95: =IF(AND(ISNUMBER(BB95),BB95>0),(Q95-BB95)/BB95,"") -> 0.48494091 | BG95: =IF(ISNUMBER(BC95),X95-BC95,"") -> 35 | BH95: =IF(AND(ISNUMBER(BC95),BC95>0),(X95-BC95)/BC95,"") -> 0.83333333 | BI95: =IF(ISNUMBER(BD95),AD95-BD95,"") -> 9
A96: 95 | B96: Cyber Solidarity Act | C96: Regulation (EU) 2025/38 | D96: Cybersecurity | E96: enacted | F96: 2023-04-18 | G96: high | H96: 2024-12-19 | I96: 2025-01-15 | J96: 2025-02-04 | K96: adopted | L96: adopted | M96: 32025R0038 | N96: Original act as published in the OJ | O96: https://eur-lex.europa.eu/legal-content/EN/TXT/?uri=CELEX:32025R0038 | P96: 34 | Q96: 20994 | R96: 9482 | S96: 9321 | T96: 11054 | U96: 458 | V96: 0 | W96: 0 | X96: 173 | Y96: 162 | Z96: 2 | AA96: 2 | AB96: 0 | AC96: 7 | AD96: 28 | AE96: 25 | AF96: 62 | AG96: 58 | AH96: 02025R0038-20250115 | AI96: 173 | AJ96: 28 | AK96: =COUNTIFS(secondary_acts!$A$2:$A$771,$A96,secondary_acts!$E$2:$E$771,"implementing") -> 2 | AL96: =COUNTIFS(secondary_acts!$A$2:$A$771,$A96,secondary_acts!$E$2:$E$771,"delegated") -> 0 | AM96: =COUNTIFS(secondary_acts!$A$2:$A$771,$A96,secondary_acts!$E$2:$E$771,"other Commission/Council act") -> 0 | AN96: =COUNTIFS(secondary_acts!$A$2:$A$771,$A96,secondary_acts!$E$2:$E$771,"guidance") -> 0 | AO96: =COUNTIF(guidance_web!$A$2:$A$7,$A96) -> 0 | AP96: =COUNTIFS(guidance_agencies!$A$2:$A$81,$A96,guidance_agencies!$D$2:$D$81,"EDPB") -> 0 | AQ96: =COUNTIFS(guidance_agencies!$A$2:$A$81,$A96,guidance_agencies!$D$2:$D$81,"EBA") -> 0 | AR96: =COUNTIFS(guidance_agencies!$A$2:$A$81,$A96,guidance_agencies!$D$2:$D$81,"ESMA") -> 0 | AS96: =SUMIFS(secondary_acts!$S$2:$S$771,secondary_acts!$A$2:$A$771,$A96,secondary_acts!$E$2:$E$771,"implementing")+SUMIFS(secondary_acts!$S$2:$S$771,secondary_acts!$A$2:$A$771,$A96,secondary_acts!$E$2:$E$771,"delegated") -> 0 | AV96: 0 | AY96: 3 | AZ96: 52023PC0209 | BA96: EUR-Lex HTML | BB96: 10677 | BC96: 105 | BD96: 22 | BE96: =IF(ISNUMBER(BB96),Q96-BB96,"") -> 10317 | BF96: =IF(AND(ISNUMBER(BB96),BB96>0),(Q96-BB96)/BB96,"") -> 0.96628266 | BG96: =IF(ISNUMBER(BC96),X96-BC96,"") -> 68 | BH96: =IF(AND(ISNUMBER(BC96),BC96>0),(X96-BC96)/BC96,"") -> 0.64761905 | BI96: =IF(ISNUMBER(BD96),AD96-BD96,"") -> 6
A97: 96 | B97: Compulsory licensing of patents Regulation | C97: 2023/0129(COD) | D97: IPR | E97: proposal | F97: 2023-04-27 | G97: high | H97: 2025-12-16 | I97: 2025-12-30 | J97: 2026-01-19 | K97: proposed | L97: adopted | M97: 32025R2645 | N97: Original act as published in the OJ | O97: https://eur-lex.europa.eu/legal-content/EN/TXT/?uri=CELEX:32025R2645 | P97: 27 | Q97: 16187 | R97: 9032 | S97: 8906 | T97: 6911 | U97: 244 | V97: 0 | W97: 0 | X97: 112 | Y97: 91 | Z97: 10 | AA97: 1 | AB97: 3 | AC97: 7 | AD97: 17 | AE97: 7 | AF97: 60 | AG97: 28 | AK97: =COUNTIFS(secondary_acts!$A$2:$A$771,$A97,secondary_acts!$E$2:$E$771,"implementing") -> 0 | AL97: =COUNTIFS(secondary_acts!$A$2:$A$771,$A97,secondary_acts!$E$2:$E$771,"delegated") -> 0 | AM97: =COUNTIFS(secondary_acts!$A$2:$A$771,$A97,secondary_acts!$E$2:$E$771,"other Commission/Council act") -> 0 | AN97: =COUNTIFS(secondary_acts!$A$2:$A$771,$A97,secondary_acts!$E$2:$E$771,"guidance") -> 0 | AO97: =COUNTIF(guidance_web!$A$2:$A$7,$A97) -> 0 | AP97: =COUNTIFS(guidance_agencies!$A$2:$A$81,$A97,guidance_agencies!$D$2:$D$81,"EDPB") -> 0 | AQ97: =COUNTIFS(guidance_agencies!$A$2:$A$81,$A97,guidance_agencies!$D$2:$D$81,"EBA") -> 0 | AR97: =COUNTIFS(guidance_agencies!$A$2:$A$81,$A97,guidance_agencies!$D$2:$D$81,"ESMA") -> 0 | AS97: =SUMIFS(secondary_acts!$S$2:$S$771,secondary_acts!$A$2:$A$771,$A97,secondary_acts!$E$2:$E$771,"implementing")+SUMIFS(secondary_acts!$S$2:$S$771,secondary_acts!$A$2:$A$771,$A97,secondary_acts!$E$2:$E$771,"delegated") -> 0 | AV97: 0 | AY97: 0 | AZ97: 52023PC0224 | BA97: EUR-Lex HTML | BB97: 10918 | BC97: 81 | BD97: 9 | BE97: =IF(ISNUMBER(BB97),Q97-BB97,"") -> 5269 | BF97: =IF(AND(ISNUMBER(BB97),BB97>0),(Q97-BB97)/BB97,"") -> 0.48259755 | BG97: =IF(ISNUMBER(BC97),X97-BC97,"") -> 31 | BH97: =IF(AND(ISNUMBER(BC97),BC97>0),(X97-BC97)/BC97,"") -> 0.38271605 | BI97: =IF(ISNUMBER(BD97),AD97-BD97,"") -> 8 | BJ97: Adopted after CEPS snapshot: Regulation (EU) 2025/2645 (16 Dec 2025)
A98: 97 | B98: Strategic Technologies for Europe Platform (STEP) | C98: Regulation (EU) 2024/795 | D98: Industrial Policy | E98: enacted | F98: 2023-06-20 | G98: high | H98: 2024-02-29 | I98: 2024-02-29 | J98: 2024-03-01 | K98: adopted | L98: adopted | M98: 32024R0795 | N98: Original act as published in the OJ | O98: https://eur-lex.europa.eu/legal-content/EN/TXT/?uri=CELEX:32024R0795 | P98: 27 | Q98: 14337 | R98: 5782 | S98: 5603 | T98: 8555 | U98: 0 | V98: 0 | W98: 0 | X98: 48 | Y98: 45 | Z98: 2 | AA98: 0 | AB98: 0 | AC98: 1 | AD98: 3 | AE98: 7 | AF98: 11 | AG98: 27 | AH98: 02024R0795-20251223 | AI98: 49 | AJ98: 3 | AK98: =COUNTIFS(secondary_acts!$A$2:$A$771,$A98,secondary_acts!$E$2:$E$771,"implementing") -> 0 | AL98: =COUNTIFS(secondary_acts!$A$2:$A$771,$A98,secondary_acts!$E$2:$E$771,"delegated") -> 0 | AM98: =COUNTIFS(secondary_acts!$A$2:$A$771,$A98,secondary_acts!$E$2:$E$771,"other Commission/Council act") -> 0 | AN98: =COUNTIFS(secondary_acts!$A$2:$A$771,$A98,secondary_acts!$E$2:$E$771,"guidance") -> 2 | AO98: =COUNTIF(guidance_web!$A$2:$A$7,$A98) -> 0 | AP98: =COUNTIFS(guidance_agencies!$A$2:$A$81,$A98,guidance_agencies!$D$2:$D$81,"EDPB") -> 0 | AQ98: =COUNTIFS(guidance_agencies!$A$2:$A$81,$A98,guidance_agencies!$D$2:$D$81,"EBA") -> 0 | AR98: =COUNTIFS(guidance_agencies!$A$2:$A$81,$A98,guidance_agencies!$D$2:$D$81,"ESMA") -> 0 | AS98: =SUMIFS(secondary_acts!$S$2:$S$771,secondary_acts!$A$2:$A$771,$A98,secondary_acts!$E$2:$E$771,"implementing")+SUMIFS(secondary_acts!$S$2:$S$771,secondary_acts!$A$2:$A$771,$A98,secondary_acts!$E$2:$E$771,"delegated") -> 0 | AV98: 1 | AW98: 2025-12-19 | AX98: 2025-12-19 | AY98: 2 | AZ98: 52023PC0335 | BA98: EUR-Lex HTML | BB98: 9976 | BC98: 56 | BD98: 1 | BE98: =IF(ISNUMBER(BB98),Q98-BB98,"") -> 4361 | BF98: =IF(AND(ISNUMBER(BB98),BB98>0),(Q98-BB98)/BB98,"") -> 0.43714916 | BG98: =IF(ISNUMBER(BC98),X98-BC98,"") -> -8 | BH98: =IF(AND(ISNUMBER(BC98),BC98>0),(X98-BC98)/BC98,"") -> -0.14285714 | BI98: =IF(ISNUMBER(BD98),AD98-BD98,"") -> 2
A99: 98 | B99: Financial Data Access Regulation (FiDA) | C99: 2023/0205(COD) | D99: Finance | E99: proposal | F99: 2023-06-28 | G99: high | K99: proposed | L99: proposed | M99: 52023PC0360 | N99: Commission proposal (COM) | O99: https://eur-lex.europa.eu/legal-content/EN/TXT/?uri=CELEX:52023PC0360 | P99: 54 | Q99: 19053 | R99: 7197 | S99: 7086 | T99: 11856 | U99: 0 | V99: 5800 | W99: 0 | X99: 155 | Y99: 134 | Z99: 8 | AA99: 4 | AB99: 1 | AC99: 8 | AD99: 42 | AE99: 53 | AF99: 24 | AG99: 36 | AK99: =COUNTIFS(secondary_acts!$A$2:$A$771,$A99,secondary_acts!$E$2:$E$771,"implementing") -> 0 | AL99: =COUNTIFS(secondary_acts!$A$2:$A$771,$A99,secondary_acts!$E$2:$E$771,"delegated") -> 0 | AM99: =COUNTIFS(secondary_acts!$A$2:$A$771,$A99,secondary_acts!$E$2:$E$771,"other Commission/Council act") -> 0 | AN99: =COUNTIFS(secondary_acts!$A$2:$A$771,$A99,secondary_acts!$E$2:$E$771,"guidance") -> 0 | AO99: =COUNTIF(guidance_web!$A$2:$A$7,$A99) -> 0 | AP99: =COUNTIFS(guidance_agencies!$A$2:$A$81,$A99,guidance_agencies!$D$2:$D$81,"EDPB") -> 0 | AQ99: =COUNTIFS(guidance_agencies!$A$2:$A$81,$A99,guidance_agencies!$D$2:$D$81,"EBA") -> 0 | AR99: =COUNTIFS(guidance_agencies!$A$2:$A$81,$A99,guidance_agencies!$D$2:$D$81,"ESMA") -> 0 | AS99: =SUMIFS(secondary_acts!$S$2:$S$771,secondary_acts!$A$2:$A$771,$A99,secondary_acts!$E$2:$E$771,"implementing")+SUMIFS(secondary_acts!$S$2:$S$771,secondary_acts!$A$2:$A$771,$A99,secondary_acts!$E$2:$E$771,"delegated") -> 0 | BA99: row is itself a proposal | BE99: =IF(ISNUMBER(BB99),Q99-BB99,"") | BF99: =IF(AND(ISNUMBER(BB99),BB99>0),(Q99-BB99)/BB99,"") | BG99: =IF(ISNUMBER(BC99),X99-BC99,"") | BH99: =IF(AND(ISNUMBER(BC99),BC99>0),(X99-BC99)/BC99,"") | BI99: =IF(ISNUMBER(BD99),AD99-BD99,"")
A100: 99 | B100: Payment Services Regulation (PSR) | C100: 2023/0210(COD) | D100: Finance | E100: proposal | F100: 2023-06-28 | G100: high | K100: proposed | L100: agreed | M100: 52023PC0367 | N100: Commission proposal (COM) | O100: https://eur-lex.europa.eu/legal-content/EN/TXT/?uri=CELEX:52023PC0367 | P100: 159 | Q100: 55334 | R100: 19804 | S100: 19694 | T100: 32412 | U100: 3118 | V100: 5272 | W100: 0 | X100: 447 | Y100: 354 | Z100: 50 | AA100: 8 | AB100: 6 | AC100: 29 | AD100: 249 | AE100: 69 | AF100: 45 | AG100: 84 | AK100: =COUNTIFS(secondary_acts!$A$2:$A$771,$A100,secondary_acts!$E$2:$E$771,"implementing") -> 0 | AL100: =COUNTIFS(secondary_acts!$A$2:$A$771,$A100,secondary_acts!$E$2:$E$771,"delegated") -> 0 | AM100: =COUNTIFS(secondary_acts!$A$2:$A$771,$A100,secondary_acts!$E$2:$E$771,"other Commission/Council act") -> 0 | AN100: =COUNTIFS(secondary_acts!$A$2:$A$771,$A100,secondary_acts!$E$2:$E$771,"guidance") -> 0 | AO100: =COUNTIF(guidance_web!$A$2:$A$7,$A100) -> 0 | AP100: =COUNTIFS(guidance_agencies!$A$2:$A$81,$A100,guidance_agencies!$D$2:$D$81,"EDPB") -> 0 | AQ100: =COUNTIFS(guidance_agencies!$A$2:$A$81,$A100,guidance_agencies!$D$2:$D$81,"EBA") -> 0 | AR100: =COUNTIFS(guidance_agencies!$A$2:$A$81,$A100,guidance_agencies!$D$2:$D$81,"ESMA") -> 0 | AS100: =SUMIFS(secondary_acts!$S$2:$S$771,secondary_acts!$A$2:$A$771,$A100,secondary_acts!$E$2:$E$771,"implementing")+SUMIFS(secondary_acts!$S$2:$S$771,secondary_acts!$A$2:$A$771,$A100,secondary_acts!$E$2:$E$771,"delegated") -> 0 | BA100: row is itself a proposal | BE100: =IF(ISNUMBER(BB100),Q100-BB100,"") | BF100: =IF(AND(ISNUMBER(BB100),BB100>0),(Q100-BB100)/BB100,"") | BG100: =IF(ISNUMBER(BC100),X100-BC100,"") | BH100: =IF(AND(ISNUMBER(BC100),BC100>0),(X100-BC100)/BC100,"") | BI100: =IF(ISNUMBER(BD100),AD100-BD100,"") | BJ100: Provisional agreement 27 Nov 2025; measured on the 2023 Commission proposal (user choice). Council final compromise text ST 8221/26: 431 Council-format pages, 74,497 words of legal text, 588 restrictions (323 on private parties)
...

Sheet secondary_acts
A1: parent_row_id | B1: parent_name | C1: parent_celex | D1: celex | E1: kind | F1: eurlex_type | G1: date | H1: title | I1: addressed_to_specific_member_state | J1: source_url | K1: pages | L1: words_legal_text | M1: words_preamble | N1: words_recitals | O1: words_articles | P1: words_annexes | Q1: words_memorandum | R1: words_financial_statement | S1: restrictions_total | T1: r_obligation | U1: r_prohibition | V1: r_restricted_permission | W1: r_explicit_requirement | X1: r_duty_of_result | Y1: addr_private_parties | Z1: addr_member_states | AA1: addr_eu_institutions | AB1: addr_unclear | AC1: note
